Workbook
Name ColumnTitle10: ExpOct[[#Headers],[日期]]
Name ColumnTitle10: ExpSep[[#Headers],[日期]]
Name ColumnTitle10: ExpAug[[#Headers],[日期]]
Name ColumnTitle10: ExpAug[[#Headers],[日期]]
Name ColumnTitle11: #REF!
Name ColumnTitle12: #REF!
Name ColumnTitle12: #REF!
Name ColumnTitle12: #REF!
Name ColumnTitle13: ExpNov[[#Headers],[日期]]
Name ColumnTitle13: ExpNov[[#Headers],[日期]]
Name ColumnTitle13: ExpNov[[#Headers],[日期]]
Name ColumnTitle13: ExpNov[[#Headers],[日期]]
Name ColumnTitle14: ExpDec[[#Headers],[日期]]
Name ColumnTitle14: ExpDec[[#Headers],[日期]]
Name ColumnTitle14: ExpDec[[#Headers],[日期]]
Name ColumnTitle14: ExpDec[[#Headers],[日期]]
Name ColumnTitle2: 资产摘要[[#Headers],[资产归属]]
Name ColumnTitle2: 资产摘要[[#Headers],[资产归属]]
Name ColumnTitle2: 投资收益表[[#Headers],[投资分类]]
Name ColumnTitle2: 资产摘要[[#Headers],[资产归属]]
Name ColumnTitle3: ExpJan[[#Headers],[日期]]
Name ColumnTitle3: ExpJan[[#Headers],[日期]]
Name ColumnTitle3: ExpJan[[#Headers],[日期]]
Name ColumnTitle3: ExpJan[[#Headers],[日期]]
Name ColumnTitle4: ExpFeb[[#Headers],[日期]]
Name ColumnTitle4: ExpFeb[[#Headers],[日期]]
Name ColumnTitle4: ExpFeb[[#Headers],[日期]]
Name ColumnTitle4: ExpFeb[[#Headers],[日期]]
Name ColumnTitle5: ExpMar[[#Headers],[日期]]
Name ColumnTitle5: ExpMar[[#Headers],[日期]]
Name ColumnTitle5: ExpMar[[#Headers],[日期]]
Name ColumnTitle5: ExpMar[[#Headers],[日期]]
Name ColumnTitle6: ExpApr[[#Headers],[日期]]
Name ColumnTitle6: ExpApr[[#Headers],[日期]]
Name ColumnTitle6: ExpApr[[#Headers],[日期]]
Name ColumnTitle6: ExpApr[[#Headers],[日期]]
Name ColumnTitle7: ExpMay[[#Headers],[日期]]
Name ColumnTitle7: ExpMay[[#Headers],[日期]]
Name ColumnTitle7: ExpMay[[#Headers],[日期]]
Name ColumnTitle7: ExpMay[[#Headers],[日期]]
Name ColumnTitle8: ExpJun[[#Headers],[日期]]
Name ColumnTitle8: ExpJun[[#Headers],[日期]]
Name ColumnTitle8: ExpJun[[#Headers],[日期]]
Name ColumnTitle8: ExpJun[[#Headers],[日期]]
Name ColumnTitle9: ExpJul[[#Headers],[日期]]
Name ColumnTitle9: ExpJul[[#Headers],[日期]]
Name ColumnTitle9: ExpJul[[#Headers],[日期]]
Name ColumnTitle9: ExpJul[[#Headers],[日期]]
Name ExpenseCategories: 资产摘要[资产归属]
Name ExpenseCategories: 资产摘要[资产归属]
Name ExpenseCategories: 投资收益表[投资分类]
Name ExpenseCategories: 资产摘要[资产归属]
Name 类别: #REF!
Name 美股投资组合: #REF!

Sheet 总资产摘要
A1: 资产趋势 | B1: 需将下方日期手动更新
B2: =DATE(2026,1,15) -> 46037 | C2: =DATE(2026,2,15) -> 46068 | D2: =DATE(2026,3,15) -> 46096 | E2: =DATE(2026,4,15) -> 46127 | F2: =DATE(2025,5,15) -> 45792 | G2: =DATE(2025,6,15) -> 45823 | H2: =DATE(2025,7,15) -> 45853 | I2: =DATE(2025,8,15) -> 45884 | J2: =DATE(2025,9,15) -> 45915 | K2: =DATE(2025,10,15) -> 45945 | L2: =DATE(2025,11,14) -> 45975 | M2: =DATE(2025,12,15) -> 46006 | N2: 提示
A4: 资产归属 | B4: 1月 | C4: 2月 | D4: 3月 | E4: 4月 | F4: 5月 | G4: 6月 | H4: 7月 | I4: 8月 | J4: 9月 | K4: 10月 | L4: 11月 | M4: 12月 | N4: 差额小计 | O4: 环比增长 | P4: 趋势 | Q4: 占比 | R4: 意见 | S4: 判定下限 | T4: 判定上限
A5: 东莞农村商业银行 | B5: =SUMIFS(ExpJan[金额],ExpJan[类别],资产摘要[[#This Row],[资产归属]]) -> 46095 | C5: =SUMIFS(ExpFeb[金额],ExpFeb[类别],资产摘要[[#This Row],[资产归属]]) -> 0.01 | D5: =SUMIFS(ExpMar[金额],ExpMar[类别],资产摘要[[#This Row],[资产归属]]) -> 0.01 | E5: =SUMIFS(ExpApr[金额],ExpApr[类别],资产摘要[[#This Row],[资产归属]]) -> 0 | F5: =SUMIFS(ExpMay[金额],ExpMay[类别],资产摘要[[#This Row],[资产归属]]) -> 0 | G5: =SUMIFS(ExpJun[金额],ExpJun[类别],资产摘要[[#This Row],[资产归属]]) -> 81466.09 | H5: =SUMIFS(ExpJul[金额],ExpJul[类别],资产摘要[[#This Row],[资产归属]]) -> 81503.45 | I5: =SUMIFS(ExpAug[金额],ExpAug[类别],资产摘要[[#This Row],[资产归属]]) -> 81591.43 | J5: =SUMIFS(ExpSep[金额],ExpSep[类别],资产摘要[[#This Row],[资产归属]]) -> 77615.66 | K5: =SUMIFS(ExpOct[金额],ExpOct[类别],资产摘要[[#This Row],[资产归属]]) -> 73876.46 | L5: =SUMIFS(ExpNov[金额],ExpNov[类别],资产摘要[[#This Row],[资产归属]]) -> 69682.36 | M5: =SUMIFS(ExpDec[金额],ExpDec[类别],资产摘要[[#This Row],[资产归属]]) -> 56685.01 | N5: {=IFERROR( IF( INDEX(B5:M5, MONTH(TODAY())) = 0, INDEX(B5:M5, IF(MONTH(TODAY())=1, 12, MONTH(TODAY())-1)) - INDEX(B5:M5, IF(MONTH(TODAY())=1, 11, MONTH(TODAY())-2)), INDEX(B5:M5, MONTH(TODAY())) - INDEX(B5:M5, IF(MONTH(TODAY())=1, 12, MONTH(TODAY())-1)) ), "" )} -> -0.01 | O5: {=IFERROR( IF( INDEX(B5:M5, MONTH(TODAY())) = 0, INDEX(B5:M5, IF(MONTH(TODAY())=1, 12, MONTH(TODAY())-1)) - INDEX(B5:M5, IF(MONTH(TODAY())=1, 11, MONTH(TODAY())-2)), INDEX(B5:M5, MONTH(TODAY())) - INDEX(B5:M5, IF(MONTH(TODAY())=1, 12, MONTH(TODAY())-1)) ), "" )/ IFERROR( IF( INDEX(B5:M5, MONTH(TODAY())) = 0, INDEX(B5:M5,MONTH(TODAY())-1), INDEX(B5:M5,MONTH(TODAY())) ), "" )} -> #DIV/0! | Q5: =INDEX(资产摘要[#This Row], MATCH(TEXT(TODAY(),"m") & "月", 资产摘要[#Headers], 0))/INDEX(资产摘要[#Totals], MATCH(TEXT(TODAY(),"m") & "月", 资产摘要[#Headers], 0)) -> 0 | R5: =IF(AND(资产摘要[[#This Row],[占比]]>=资产摘要[[#This Row],[判定下限]], 资产摘要[[#This Row],[占比]]<=资产摘要[[#This Row],[判定上限]]),"合理","不合理") -> 合理 | S5: 0 | T5: 0.05
A6: 招商银行 | B6: =SUMIFS(ExpJan[金额],ExpJan[类别],资产摘要[[#This Row],[资产归属]]) -> 192935.76 | C6: =SUMIFS(ExpFeb[金额],ExpFeb[类别],资产摘要[[#This Row],[资产归属]]) -> 260187.53 | D6: =SUMIFS(ExpMar[金额],ExpMar[类别],资产摘要[[#This Row],[资产归属]]) -> 429074.87 | E6: =SUMIFS(ExpApr[金额],ExpApr[类别],资产摘要[[#This Row],[资产归属]]) -> 353671.01 | F6: =SUMIFS(ExpMay[金额],ExpMay[类别],资产摘要[[#This Row],[资产归属]]) -> 372604.37 | G6: =SUMIFS(ExpJun[金额],ExpJun[类别],资产摘要[[#This Row],[资产归属]]) -> 153397.45 | H6: =SUMIFS(ExpJul[金额],ExpJul[类别],资产摘要[[#This Row],[资产归属]]) -> 162079.94 | I6: =SUMIFS(ExpAug[金额],ExpAug[类别],资产摘要[[#This Row],[资产归属]]) -> 169392.9 | J6: =SUMIFS(ExpSep[金额],ExpSep[类别],资产摘要[[#This Row],[资产归属]]) -> 172458.4 | K6: =SUMIFS(ExpOct[金额],ExpOct[类别],资产摘要[[#This Row],[资产归属]]) -> 168232.73 | L6: =SUMIFS(ExpNov[金额],ExpNov[类别],资产摘要[[#This Row],[资产归属]]) -> 173631.04 | M6: =SUMIFS(ExpDec[金额],ExpDec[类别],资产摘要[[#This Row],[资产归属]]) -> 187595.64 | N6: {=IFERROR( IF( INDEX(B6:M6, MONTH(TODAY())) = 0, INDEX(B6:M6, IF(MONTH(TODAY())=1, 12, MONTH(TODAY())-1)) - INDEX(B6:M6, IF(MONTH(TODAY())=1, 11, MONTH(TODAY())-2)), INDEX(B6:M6, MONTH(TODAY())) - INDEX(B6:M6, IF(MONTH(TODAY())=1, 12, MONTH(TODAY())-1)) ), "" )} -> 18933.36 | O6: {=IFERROR( IF( INDEX(B6:M6, MONTH(TODAY())) = 0, INDEX(B6:M6, IF(MONTH(TODAY())=1, 12, MONTH(TODAY())-1)) - INDEX(B6:M6, IF(MONTH(TODAY())=1, 11, MONTH(TODAY())-2)), INDEX(B6:M6, MONTH(TODAY())) - INDEX(B6:M6, IF(MONTH(TODAY())=1, 12, MONTH(TODAY())-1)) ), "" )/ IFERROR( IF( INDEX(B6:M6, MONTH(TODAY())) = 0, INDEX(B6:M6,MONTH(TODAY())-1), INDEX(B6:M6,MONTH(TODAY())) ), "" )} -> 0.050813575 | Q6: =INDEX(资产摘要[#This Row], MATCH(TEXT(TODAY(),"m") & "月", 资产摘要[#Headers], 0))/INDEX(资产摘要[#Totals], MATCH(TEXT(TODAY(),"m") & "月", 资产摘要[#Headers], 0)) -> 0.65240945 | R6: =IF(AND(资产摘要[[#This Row],[占比]]>=资产摘要[[#This Row],[判定下限]], 资产摘要[[#This Row],[占比]]<=资产摘要[[#This Row],[判定上限]]),"合理","不合理") -> 合理 | S6: 0.6 | T6: 0.8
A7: 中国银行 | B7: =SUMIFS(ExpJan[金额],ExpJan[类别],资产摘要[[#This Row],[资产归属]]) -> 2119.37 | C7: =SUMIFS(ExpFeb[金额],ExpFeb[类别],资产摘要[[#This Row],[资产归属]]) -> 2084.81 | D7: =SUMIFS(ExpMar[金额],ExpMar[类别],资产摘要[[#This Row],[资产归属]]) -> 1973.89 | E7: =SUMIFS(ExpApr[金额],ExpApr[类别],资产摘要[[#This Row],[资产归属]]) -> 53.08 | F7: =SUMIFS(ExpMay[金额],ExpMay[类别],资产摘要[[#This Row],[资产归属]]) -> 52.95 | G7: =SUMIFS(ExpJun[金额],ExpJun[类别],资产摘要[[#This Row],[资产归属]]) -> 10458.89 | H7: =SUMIFS(ExpJul[金额],ExpJul[类别],资产摘要[[#This Row],[资产归属]]) -> 12612.22 | I7: =SUMIFS(ExpAug[金额],ExpAug[类别],资产摘要[[#This Row],[资产归属]]) -> 10057.35 | J7: =SUMIFS(ExpSep[金额],ExpSep[类别],资产摘要[[#This Row],[资产归属]]) -> 294.56 | K7: =SUMIFS(ExpOct[金额],ExpOct[类别],资产摘要[[#This Row],[资产归属]]) -> 6.86 | L7: =SUMIFS(ExpNov[金额],ExpNov[类别],资产摘要[[#This Row],[资产归属]]) -> 0.32 | M7: =SUMIFS(ExpDec[金额],ExpDec[类别],资产摘要[[#This Row],[资产归属]]) -> 468.18 | N7: {=IFERROR( IF( INDEX(B7:M7, MONTH(TODAY())) = 0, INDEX(B7:M7, IF(MONTH(TODAY())=1, 12, MONTH(TODAY())-1)) - INDEX(B7:M7, IF(MONTH(TODAY())=1, 11, MONTH(TODAY())-2)), INDEX(B7:M7, MONTH(TODAY())) - INDEX(B7:M7, IF(MONTH(TODAY())=1, 12, MONTH(TODAY())-1)) ), "" )} -> -0.13 | O7: {=IFERROR( IF( INDEX(B7:M7, MONTH(TODAY())) = 0, INDEX(B7:M7, IF(MONTH(TODAY())=1, 12, MONTH(TODAY())-1)) - INDEX(B7:M7, IF(MONTH(TODAY())=1, 11, MONTH(TODAY())-2)), INDEX(B7:M7, MONTH(TODAY())) - INDEX(B7:M7, IF(MONTH(TODAY())=1, 12, MONTH(TODAY())-1)) ), "" )/ IFERROR( IF( INDEX(B7:M7, MONTH(TODAY())) = 0, INDEX(B7:M7,MONTH(TODAY())-1), INDEX(B7:M7,MONTH(TODAY())) ), "" )} -> -0.0024551464 | Q7: =INDEX(资产摘要[#This Row], MATCH(TEXT(TODAY(),"m") & "月", 资产摘要[#Headers], 0))/INDEX(资产摘要[#Totals], MATCH(TEXT(TODAY(),"m") & "月", 资产摘要[#Headers], 0)) -> 9.2712493e-05 | R7: =IF(AND(资产摘要[[#This Row],[占比]]>=资产摘要[[#This Row],[判定下限]], 资产摘要[[#This Row],[占比]]<=资产摘要[[#This Row],[判定上限]]),"合理","不合理") -> 合理 | S7: 0 | T7: 0.5
A8: 中银香港 | B8: =SUMIFS(ExpJan[金额],ExpJan[类别],资产摘要[[#This Row],[资产归属]]) -> 0.009167 | C8: =SUMIFS(ExpFeb[金额],ExpFeb[类别],资产摘要[[#This Row],[资产归属]]) -> 0.009167 | D8: =SUMIFS(ExpMar[金额],ExpMar[类别],资产摘要[[#This Row],[资产归属]]) -> 0.009167 | E8: =SUMIFS(ExpApr[金额],ExpApr[类别],资产摘要[[#This Row],[资产归属]]) -> 0.009167 | F8: =SUMIFS(ExpMay[金额],ExpMay[类别],资产摘要[[#This Row],[资产归属]]) -> 0.009167 | G8: =SUMIFS(ExpJun[金额],ExpJun[类别],资产摘要[[#This Row],[资产归属]]) -> 5701.12 | H8: =SUMIFS(ExpJul[金额],ExpJul[类别],资产摘要[[#This Row],[资产归属]]) -> 0.071264 | I8: =SUMIFS(ExpAug[金额],ExpAug[类别],资产摘要[[#This Row],[资产归属]]) -> 0.009167 | J8: =SUMIFS(ExpSep[金额],ExpSep[类别],资产摘要[[#This Row],[资产归属]]) -> 0.09167 | K8: =SUMIFS(ExpOct[金额],ExpOct[类别],资产摘要[[#This Row],[资产归属]]) -> 0 | L8: =SUMIFS(ExpNov[金额],ExpNov[类别],资产摘要[[#This Row],[资产归属]]) -> 0.009167 | M8: =SUMIFS(ExpDec[金额],ExpDec[类别],资产摘要[[#This Row],[资产归属]]) -> 0.009167 | N8: {=IFERROR( IF( INDEX(B8:M8, MONTH(TODAY())) = 0, INDEX(B8:M8, IF(MONTH(TODAY())=1, 12, MONTH(TODAY())-1)) - INDEX(B8:M8, IF(MONTH(TODAY())=1, 11, MONTH(TODAY())-2)), INDEX(B8:M8, MONTH(TODAY())) - INDEX(B8:M8, IF(MONTH(TODAY())=1, 12, MONTH(TODAY())-1)) ), "" )} -> 0 | O8: {=IFERROR( IF( INDEX(B8:M8, MONTH(TODAY())) = 0, INDEX(B8:M8, IF(MONTH(TODAY())=1, 12, MONTH(TODAY())-1)) - INDEX(B8:M8, IF(MONTH(TODAY())=1, 11, MONTH(TODAY())-2)), INDEX(B8:M8, MONTH(TODAY())) - INDEX(B8:M8, IF(MONTH(TODAY())=1, 12, MONTH(TODAY())-1)) ), "" )/ IFERROR( IF( INDEX(B8:M8, MONTH(TODAY())) = 0, INDEX(B8:M8,MONTH(TODAY())-1), INDEX(B8:M8,MONTH(TODAY())) ), "" )} -> 0 | Q8: =INDEX(资产摘要[#This Row], MATCH(TEXT(TODAY(),"m") & "月", 资产摘要[#Headers], 0))/INDEX(资产摘要[#Totals], MATCH(TEXT(TODAY(),"m") & "月", 资产摘要[#Headers], 0)) -> 1.6050905e-08 | R8: =IF(AND(资产摘要[[#This Row],[占比]]>=资产摘要[[#This Row],[判定下限]], 资产摘要[[#This Row],[占比]]<=资产摘要[[#This Row],[判定上限]]),"合理","不合理") -> 合理 | S8: 0 | T8: 0.05
A9: 支付宝 | B9: =SUMIFS(ExpJan[金额],ExpJan[类别],资产摘要[[#This Row],[资产归属]]) -> 0.2 | C9: =SUMIFS(ExpFeb[金额],ExpFeb[类别],资产摘要[[#This Row],[资产归属]]) -> 10086.78 | D9: =SUMIFS(ExpMar[金额],ExpMar[类别],资产摘要[[#This Row],[资产归属]]) -> 0.02 | E9: =SUMIFS(ExpApr[金额],ExpApr[类别],资产摘要[[#This Row],[资产归属]]) -> 0.04 | F9: =SUMIFS(ExpMay[金额],ExpMay[类别],资产摘要[[#This Row],[资产归属]]) -> 1.04 | G9: =SUMIFS(ExpJun[金额],ExpJun[类别],资产摘要[[#This Row],[资产归属]]) -> 310.98 | H9: =SUMIFS(ExpJul[金额],ExpJul[类别],资产摘要[[#This Row],[资产归属]]) -> 46.54 | I9: =SUMIFS(ExpAug[金额],ExpAug[类别],资产摘要[[#This Row],[资产归属]]) -> 1.96 | J9: =SUMIFS(ExpSep[金额],ExpSep[类别],资产摘要[[#This Row],[资产归属]]) -> 0.96 | K9: =SUMIFS(ExpOct[金额],ExpOct[类别],资产摘要[[#This Row],[资产归属]]) -> 1.15 | L9: =SUMIFS(ExpNov[金额],ExpNov[类别],资产摘要[[#This Row],[资产归属]]) -> 0.15 | M9: =SUMIFS(ExpDec[金额],ExpDec[类别],资产摘要[[#This Row],[资产归属]]) -> 63.5 | N9: {=IFERROR( IF( INDEX(B9:M9, MONTH(TODAY())) = 0, INDEX(B9:M9, IF(MONTH(TODAY())=1, 12, MONTH(TODAY())-1)) - INDEX(B9:M9, IF(MONTH(TODAY())=1, 11, MONTH(TODAY())-2)), INDEX(B9:M9, MONTH(TODAY())) - INDEX(B9:M9, IF(MONTH(TODAY())=1, 12, MONTH(TODAY())-1)) ), "" )} -> 1 | O9: {=IFERROR( IF( INDEX(B9:M9, MONTH(TODAY())) = 0, INDEX(B9:M9, IF(MONTH(TODAY())=1, 12, MONTH(TODAY())-1)) - INDEX(B9:M9, IF(MONTH(TODAY())=1, 11, MONTH(TODAY())-2)), INDEX(B9:M9, MONTH(TODAY())) - INDEX(B9:M9, IF(MONTH(TODAY())=1, 12, MONTH(TODAY())-1)) ), "" )/ IFERROR( IF( INDEX(B9:M9, MONTH(TODAY())) = 0, INDEX(B9:M9,MONTH(TODAY())-1), INDEX(B9:M9,MONTH(TODAY())) ), "" )} -> 0.96153846 | Q9: =INDEX(资产摘要[#This Row], MATCH(TEXT(TODAY(),"m") & "月", 资产摘要[#Headers], 0))/INDEX(资产摘要[#Totals], MATCH(TEXT(TODAY(),"m") & "月", 资产摘要[#Headers], 0)) -> 1.8209819e-06 | R9: =IF(AND(资产摘要[[#This Row],[占比]]>=资产摘要[[#This Row],[判定下限]], 资产摘要[[#This Row],[占比]]<=资产摘要[[#This Row],[判定上限]]),"合理","不合理") -> 合理 | S9: 0 | T9: 0.05
A10: 微信 | B10: =SUMIFS(ExpJan[金额],ExpJan[类别],资产摘要[[#This Row],[资产归属]]) -> 134.86 | C10: =SUMIFS(ExpFeb[金额],ExpFeb[类别],资产摘要[[#This Row],[资产归属]]) -> 866.21 | D10: =SUMIFS(ExpMar[金额],ExpMar[类别],资产摘要[[#This Row],[资产归属]]) -> 7.34 | E10: =SUMIFS(ExpApr[金额],ExpApr[类别],资产摘要[[#This Row],[资产归属]]) -> 1.9 | F10: =SUMIFS(ExpMay[金额],ExpMay[类别],资产摘要[[#This Row],[资产归属]]) -> 9.9 | G10: =SUMIFS(ExpJun[金额],ExpJun[类别],资产摘要[[#This Row],[资产归属]]) -> 1286.09 | H10: =SUMIFS(ExpJul[金额],ExpJul[类别],资产摘要[[#This Row],[资产归属]]) -> 2.93 | I10: =SUMIFS(ExpAug[金额],ExpAug[类别],资产摘要[[#This Row],[资产归属]]) -> 5.95 | J10: =SUMIFS(ExpSep[金额],ExpSep[类别],资产摘要[[#This Row],[资产归属]]) -> 2 | K10: =SUMIFS(ExpOct[金额],ExpOct[类别],资产摘要[[#This Row],[资产归属]]) -> 160.93 | L10: =SUMIFS(ExpNov[金额],ExpNov[类别],资产摘要[[#This Row],[资产归属]]) -> 0.9 | M10: =SUMIFS(ExpDec[金额],ExpDec[类别],资产摘要[[#This Row],[资产归属]]) -> 1.06 | N10: {=IFERROR( INDEX(B10:M10, MONTH(TODAY())) - INDEX(B10:M10, IF(MONTH(TODAY())=1, 12, MONTH(TODAY())-1)), "")} -> 8 | O10: {=IFERROR( IF( INDEX(B10:M10, MONTH(TODAY())) = 0, INDEX(B10:M10, IF(MONTH(TODAY())=1, 12, MONTH(TODAY())-1)) - INDEX(B10:M10, IF(MONTH(TODAY())=1, 11, MONTH(TODAY())-2)), INDEX(B10:M10, MONTH(TODAY())) - INDEX(B10:M10, IF(MONTH(TODAY())=1, 12, MONTH(TODAY())-1)) ), "" )/ IFERROR( IF( INDEX(B10:M10, MONTH(TODAY())) = 0, INDEX(B10:M10,MONTH(TODAY())-1), INDEX(B10:M10,MONTH(TODAY())) ), "" )} -> 0.80808081 | Q10: =INDEX(资产摘要[#This Row], MATCH(TEXT(TODAY(),"m") & "月", 资产摘要[#Headers], 0))/INDEX(资产摘要[#Totals], MATCH(TEXT(TODAY(),"m") & "月", 资产摘要[#Headers], 0)) -> 1.7334347e-05 | R10: =IF(AND(资产摘要[[#This Row],[占比]]>=资产摘要[[#This Row],[判定下限]], 资产摘要[[#This Row],[占比]]<=资产摘要[[#This Row],[判定上限]]),"合理","不合理") -> 合理 | S10: 0 | T10: 0.05
A11: 东方财富 | B11: =SUMIFS(ExpJan[金额],ExpJan[类别],资产摘要[[#This Row],[资产归属]]) -> 41299.21 | C11: =SUMIFS(ExpFeb[金额],ExpFeb[类别],资产摘要[[#This Row],[资产归属]]) -> 42623.14 | D11: =SUMIFS(ExpMar[金额],ExpMar[类别],资产摘要[[#This Row],[资产归属]]) -> 54889.23 | E11: =SUMIFS(ExpApr[金额],ExpApr[类别],资产摘要[[#This Row],[资产归属]]) -> 140024.49 | F11: =SUMIFS(ExpMay[金额],ExpMay[类别],资产摘要[[#This Row],[资产归属]]) -> 140296.64 | G11: =SUMIFS(ExpJun[金额],ExpJun[类别],资产摘要[[#This Row],[资产归属]]) -> 21009.23 | H11: =SUMIFS(ExpJul[金额],ExpJul[类别],资产摘要[[#This Row],[资产归属]]) -> 20932.77 | I11: =SUMIFS(ExpAug[金额],ExpAug[类别],资产摘要[[#This Row],[资产归属]]) -> 21072.81 | J11: =SUMIFS(ExpSep[金额],ExpSep[类别],资产摘要[[#This Row],[资产归属]]) -> 20901.54 | K11: =SUMIFS(ExpOct[金额],ExpOct[类别],资产摘要[[#This Row],[资产归属]]) -> 21785.1 | L11: =SUMIFS(ExpNov[金额],ExpNov[类别],资产摘要[[#This Row],[资产归属]]) -> 22484.1 | M11: =SUMIFS(ExpDec[金额],ExpDec[类别],资产摘要[[#This Row],[资产归属]]) -> 26416.7 | N11: {=IFERROR( IF( INDEX(B11:M11, MONTH(TODAY())) = 0, INDEX(B11:M11, IF(MONTH(TODAY())=1, 12, MONTH(TODAY())-1)) - INDEX(B11:M11, IF(MONTH(TODAY())=1, 11, MONTH(TODAY())-2)), INDEX(B11:M11, MONTH(TODAY())) - INDEX(B11:M11, IF(MONTH(TODAY())=1, 12, MONTH(TODAY())-1)) ), "" )} -> 272.15 | O11: {=IFERROR( IF( INDEX(B11:M11, MONTH(TODAY())) = 0, INDEX(B11:M11, IF(MONTH(TODAY())=1, 12, MONTH(TODAY())-1)) - INDEX(B11:M11, IF(MONTH(TODAY())=1, 11, MONTH(TODAY())-2)), INDEX(B11:M11, MONTH(TODAY())) - INDEX(B11:M11, IF(MONTH(TODAY())=1, 12, MONTH(TODAY())-1)) ), "" )/ IFERROR( IF( INDEX(B11:M11, MONTH(TODAY())) = 0, INDEX(B11:M11,MONTH(TODAY())-1), INDEX(B11:M11,MONTH(TODAY())) ), "" )} -> 0.0019398184 | Q11: =INDEX(资产摘要[#This Row], MATCH(TEXT(TODAY(),"m") & "月", 资产摘要[#Headers], 0))/INDEX(资产摘要[#Totals], MATCH(TEXT(TODAY(),"m") & "月", 资产摘要[#Headers], 0)) -> 0.24565158 | R11: =IF(AND(资产摘要[[#This Row],[占比]]>=资产摘要[[#This Row],[判定下限]], 资产摘要[[#This Row],[占比]]<=资产摘要[[#This Row],[判定上限]]),"合理","不合理") -> 不合理 | S11: 0 | T11: 0.07
A12: 长桥证券 | B12: =SUMIFS(ExpJan[金额],ExpJan[类别],资产摘要[[#This Row],[资产归属]]) -> 46588.66 | C12: =SUMIFS(ExpFeb[金额],ExpFeb[类别],资产摘要[[#This Row],[资产归属]]) -> 48786.92 | D12: =SUMIFS(ExpMar[金额],ExpMar[类别],资产摘要[[#This Row],[资产归属]]) -> 48266.09 | E12: =SUMIFS(ExpApr[金额],ExpApr[类别],资产摘要[[#This Row],[资产归属]]) -> 48651.67 | F12: =SUMIFS(ExpMay[金额],ExpMay[类别],资产摘要[[#This Row],[资产归属]]) -> 49834.35 | G12: =SUMIFS(ExpJun[金额],ExpJun[类别],资产摘要[[#This Row],[资产归属]]) -> 8484.92 | H12: =SUMIFS(ExpJul[金额],ExpJul[类别],资产摘要[[#This Row],[资产归属]]) -> 14584.32 | I12: =SUMIFS(ExpAug[金额],ExpAug[类别],资产摘要[[#This Row],[资产归属]]) -> 14975.57 | J12: =SUMIFS(ExpSep[金额],ExpSep[类别],资产摘要[[#This Row],[资产归属]]) -> 22866.26 | K12: =SUMIFS(ExpOct[金额],ExpOct[类别],资产摘要[[#This Row],[资产归属]]) -> 43401.35 | L12: =SUMIFS(ExpNov[金额],ExpNov[类别],资产摘要[[#This Row],[资产归属]]) -> 46395.65 | M12: =SUMIFS(ExpDec[金额],ExpDec[类别],资产摘要[[#This Row],[资产归属]]) -> 45130.43 | N12: {=IFERROR( IF( INDEX(B12:M12, MONTH(TODAY())) = 0, INDEX(B12:M12, IF(MONTH(TODAY())=1, 12, MONTH(TODAY())-1)) - INDEX(B12:M12, IF(MONTH(TODAY())=1, 11, MONTH(TODAY())-2)), INDEX(B12:M12, MONTH(TODAY())) - INDEX(B12:M12, IF(MONTH(TODAY())=1, 12, MONTH(TODAY())-1)) ), "" )} -> 1182.68 | O12: {=IFERROR( IF( INDEX(B12:M12, MONTH(TODAY())) = 0, INDEX(B12:M12, IF(MONTH(TODAY())=1, 12, MONTH(TODAY())-1)) - INDEX(B12:M12, IF(MONTH(TODAY())=1, 11, MONTH(TODAY())-2)), INDEX(B12:M12, MONTH(TODAY())) - INDEX(B12:M12, IF(MONTH(TODAY())=1, 12, MONTH(TODAY())-1)) ), "" )/ IFERROR( IF( INDEX(B12:M12, MONTH(TODAY())) = 0, INDEX(B12:M12,MONTH(TODAY())-1), INDEX(B12:M12,MONTH(TODAY())) ), "" )} -> 0.023732225 | Q12: =INDEX(资产摘要[#This Row], MATCH(TEXT(TODAY(),"m") & "月", 资产摘要[#Headers], 0))/INDEX(资产摘要[#Totals], MATCH(TEXT(TODAY(),"m") & "月", 资产摘要[#Headers], 0)) -> 0.087257164 | R12: =IF(AND(资产摘要[[#This Row],[占比]]>=资产摘要[[#This Row],[判定下限]], 资产摘要[[#This Row],[占比]]<=资产摘要[[#This Row],[判定上限]]),"合理","不合理") -> 合理 | S12: 0 | T12: 0.1
A13: 币安Biance | B13: =SUMIFS(ExpJan[金额],ExpJan[类别],资产摘要[[#This Row],[资产归属]]) -> 8846.0794 | C13: =SUMIFS(ExpFeb[金额],ExpFeb[类别],资产摘要[[#This Row],[资产归属]]) -> 7530.4296 | D13: =SUMIFS(ExpMar[金额],ExpMar[类别],资产摘要[[#This Row],[资产归属]]) -> 7845.43 | E13: =SUMIFS(ExpApr[金额],ExpApr[类别],资产摘要[[#This Row],[资产归属]]) -> 7988.15 | F13: =SUMIFS(ExpMay[金额],ExpMay[类别],资产摘要[[#This Row],[资产归属]]) -> 8321.18 | G13: =SUMIFS(ExpJun[金额],ExpJun[类别],资产摘要[[#This Row],[资产归属]]) -> 9117.523 | H13: =SUMIFS(ExpJul[金额],ExpJul[类别],资产摘要[[#This Row],[资产归属]]) -> 9103.7375 | I13: =SUMIFS(ExpAug[金额],ExpAug[类别],资产摘要[[#This Row],[资产归属]]) -> 9129.9894 | J13: =SUMIFS(ExpSep[金额],ExpSep[类别],资产摘要[[#This Row],[资产归属]]) -> 8962.8624 | K13: =SUMIFS(ExpOct[金额],ExpOct[类别],资产摘要[[#This Row],[资产归属]]) -> 8791.1158 | L13: =SUMIFS(ExpNov[金额],ExpNov[类别],资产摘要[[#This Row],[资产归属]]) -> 8960.1876 | M13: =SUMIFS(ExpDec[金额],ExpDec[类别],资产摘要[[#This Row],[资产归属]]) -> 8644.3212 | N13: {=IFERROR( IF( INDEX(B13:M13, MONTH(TODAY())) = 0, INDEX(B13:M13, IF(MONTH(TODAY())=1, 12, MONTH(TODAY())-1)) - INDEX(B13:M13, IF(MONTH(TODAY())=1, 11, MONTH(TODAY())-2)), INDEX(B13:M13, MONTH(TODAY())) - INDEX(B13:M13, IF(MONTH(TODAY())=1, 12, MONTH(TODAY())-1)) ), "" )} -> 333.03 | O13: {=IFERROR( IF( INDEX(B13:M13, MONTH(TODAY())) = 0, INDEX(B13:M13, IF(MONTH(TODAY())=1, 12, MONTH(TODAY())-1)) - INDEX(B13:M13, IF(MONTH(TODAY())=1, 11, MONTH(TODAY())-2)), INDEX(B13:M13, MONTH(TODAY())) - INDEX(B13:M13, IF(MONTH(TODAY())=1, 12, MONTH(TODAY())-1)) ), "" )/ IFERROR( IF( INDEX(B13:M13, MONTH(TODAY())) = 0, INDEX(B13:M13,MONTH(TODAY())-1), INDEX(B13:M13,MONTH(TODAY())) ), "" )} -> 0.040021968 | Q13: =INDEX(资产摘要[#This Row], MATCH(TEXT(TODAY(),"m") & "月", 资产摘要[#Headers], 0))/INDEX(资产摘要[#Totals], MATCH(TEXT(TODAY(),"m") & "月", 资产摘要[#Headers], 0)) -> 0.014569922 | R13: =IF(AND(资产摘要[[#This Row],[占比]]>=资产摘要[[#This Row],[判定下限]], 资产摘要[[#This Row],[占比]]<=资产摘要[[#This Row],[判定上限]]),"合理","不合理") -> 不合理 | S13: 0.02 | T13: 0.04
A14: {=IFERROR( _xlfn.LET( _xlpm.data, B14:M14, _xlpm.nonZeroData, IF(_xlpm.data>0, _xlpm.data, ""), _xlpm.minVal, MIN(_xlpm.nonZeroData), _xlpm.maxVal, MAX(_xlpm.data), _xlpm.startPos, MATCH(_xlpm.minVal, _xlpm.nonZeroData, 0), _xlpm.endPos, MATCH(_xlpm.maxVal, _xlpm.data, 0), _xlpm.startDate, INDEX(B2:M2, _xlpm.startPos), _xlpm.endDate, INDEX(B2:M2, _xlpm.endPos), IF(_xlpm.endDate < _xlpm.startDate, "", (_xlpm.maxVal / _xlpm.minVal) -1 ) ), "" )} | B14: =SUBTOTAL(109,资产摘要[1月]) -> 338019.15 | C14: =SUBTOTAL(109,资产摘要[2月]) -> 372165.84 | D14: =SUBTOTAL(109,资产摘要[3月]) -> 542056.89 | E14: =SUBTOTAL(109,资产摘要[4月]) -> 550390.35 | F14: =SUBTOTAL(109,资产摘要[5月]) -> 571120.44 | G14: =SUBTOTAL(109,资产摘要[6月]) -> 291232.29 | H14: =SUBTOTAL(109,资产摘要[7月]) -> 300865.98 | I14: =SUBTOTAL(109,资产摘要[8月]) -> 306227.97 | J14: =SUBTOTAL(109,资产摘要[9月]) -> 303102.33 | K14: =SUBTOTAL(109,资产摘要[10月]) -> 316255.7 | L14: =SUBTOTAL(109,资产摘要[11月]) -> 321154.72 | M14: =SUBTOTAL(109,资产摘要[12月]) -> 325004.85 | N14: =SUBTOTAL(109,资产摘要[差额小计]) -> 20730.08 | O14: {=IFERROR( IF( INDEX(B14:M14, MONTH(TODAY())) = 0, INDEX(B14:M14, IF(MONTH(TODAY())=1, 12, MONTH(TODAY())-1)) - INDEX(B14:M14, IF(MONTH(TODAY())=1, 11, MONTH(TODAY())-2)), INDEX(B14:M14, MONTH(TODAY())) - INDEX(B14:M14, IF(MONTH(TODAY())=1, 12, MONTH(TODAY())-1)) ), "" )/ IFERROR( IF( INDEX(B14:M14, MONTH(TODAY())) = 0, INDEX(B14:M14,MONTH(TODAY())-1), INDEX(B14:M14,MONTH(TODAY())) ), "" )} -> 0.03629723 | P14: {=IFERROR( _xlfn.LET( _xlpm.data, B14:M14, _xlpm.nonZeroData, IF(_xlpm.data>0, _xlpm.data, ""), _xlpm.minVal, MIN(_xlpm.nonZeroData), _xlpm.maxVal, MAX(_xlpm.data), _xlpm.startPos, MATCH(_xlpm.minVal, _xlpm.nonZeroData, 0), _xlpm.endPos, MATCH(_xlpm.maxVal, _xlpm.data, 0), _xlpm.startDate, INDEX(B2:M2, _xlpm.startPos), _xlpm.endDate, INDEX(B2:M2, _xlpm.endPos), IF(_xlpm.endDate < _xlpm.startDate, "", _xlfn.LET( _xlpm.months, DATEDIF(_xlpm.startDate, _xlpm.endDate, "m") +1, (_xlpm.maxVal / _xlpm.minVal) ^ (12/_xlpm.months) -1 ) ) ), "" )} | Q14: =SUBTOTAL(109,资产摘要[占比]) -> 1 | S14: =SUBTOTAL(109,资产摘要[判定下限]) -> 0.62 | T14: =SUBTOTAL(109,资产摘要[判定上限]) -> 1.71
A15: 环比增长C | B15: =资产摘要[[#Totals],[1月]]/资产摘要[[#Totals],[12月]]-1 -> 0.040043397 | C15: =IFERROR( _xlfn.LET( _xlpm.result, 资产摘要[[#Totals],[2月]]/资产摘要[[#Totals],[1月]]-1, IF(OR(_xlpm.result=0, _xlpm.result=-1), 0, _xlpm.result) ), 0 ) -> 0.10101999 | D15: =IFERROR( _xlfn.LET( _xlpm.result, 资产摘要[[#Totals],[3月]]/资产摘要[[#Totals],[2月]]-1, IF(OR(_xlpm.result=0, _xlpm.result=-1), 0, _xlpm.result) ), 0 ) -> 0.45649287 | E15: =IFERROR( _xlfn.LET( _xlpm.result, 资产摘要[[#Totals],[4月]]/资产摘要[[#Totals],[3月]]-1, IF(OR(_xlpm.result=0, _xlpm.result=-1), 0, _xlpm.result) ), 0 ) -> 0.015373774 | F15: =IFERROR( _xlfn.LET( _xlpm.result, 资产摘要[[#Totals],[5月]]/资产摘要[[#Totals],[4月]]-1, IF(OR(_xlpm.result=0, _xlpm.result=-1), 0, _xlpm.result) ), 0 ) -> 0.037664341 | G15: =IFERROR( _xlfn.LET( _xlpm.result, 资产摘要[[#Totals],[6月]]/资产摘要[[#Totals],[5月]]-1, IF(OR(_xlpm.result=0, _xlpm.result=-1), 0, _xlpm.result) ), 0 ) -> -0.49006852 | H15: =IFERROR( _xlfn.LET( _xlpm.result, 资产摘要[[#Totals],[7月]]/资产摘要[[#Totals],[6月]]-1, IF(OR(_xlpm.result=0, _xlpm.result=-1), 0, _xlpm.result) ), 0 ) -> 0.033079044 | I15: =IFERROR( _xlfn.LET( _xlpm.result, 资产摘要[[#Totals],[8月]]/资产摘要[[#Totals],[7月]]-1, IF(OR(_xlpm.result=0, _xlpm.result=-1), 0, _xlpm.result) ), 0 ) -> 0.017821855 | J15: =IFERROR( _xlfn.LET( _xlpm.result, 资产摘要[[#Totals],[9月]]/资产摘要[[#Totals],[8月]]-1, IF(OR(_xlpm.result=0, _xlpm.result=-1), 0, _xlpm.result) ), 0 ) -> -0.010206888 | K15: =IFERROR( _xlfn.LET( _xlpm.result, 资产摘要[[#Totals],[10月]]/资产摘要[[#Totals],[9月]]-1, IF(OR(_xlpm.result=0, _xlpm.result=-1), 0, _xlpm.result) ), 0 ) -> 0.043395778 | L15: =IFERROR( _xlfn.LET( _xlpm.result, 资产摘要[[#Totals],[11月]]/资产摘要[[#Totals],[10月]]-1, IF(OR(_xlpm.result=0, _xlpm.result=-1), 0, _xlpm.result) ), 0 ) -> 0.015490696 | M15: =IFERROR( _xlfn.LET( _xlpm.result, 资产摘要[[#Totals],[12月]]/资产摘要[[#Totals],[11月]]-1, IF(OR(_xlpm.result=0, _xlpm.result=-1), 0, _xlpm.result) ), 0 ) -> 0.011988407 | N15: =IF(COUNTIF(B15:M15, ">-10%")>0, SUMIF(B15:M15, ">-10%")/COUNTIF(B15:M15, ">-10%"), 0) -> 0.069287569
U17: 预测年份 | V17: 预测年末资产（元）
U18: =YEAR(TODAY()) -> 2026 | V18: =MAX(资产摘要[[#Totals],[1月]:[12月]])* (1+$N$15)^( (U18 - YEAR(TODAY())) * 12 + (12 - MONTH(TODAY())) ) -> 912828.79
U19: =U18+1 -> 2027 | V19: =MAX(资产摘要[[#Totals],[1月]:[12月]])* (1+$N$15)^( (U19 - YEAR(TODAY())) * 12 + (12 - MONTH(TODAY())) ) -> 2039499.2
U20: =U19+1 -> 2028 | V20: =MAX(资产摘要[[#Totals],[1月]:[12月]])* (1+$N$15)^( (U20 - YEAR(TODAY())) * 12 + (12 - MONTH(TODAY())) ) -> 4556776.8
U21: =U20+1 -> 2029 | V21: =MAX(资产摘要[[#Totals],[1月]:[12月]])* (1+$N$15)^( (U21 - YEAR(TODAY())) * 12 + (12 - MONTH(TODAY())) ) -> 10181036
U22: =U21+1 -> 2030 | V22: =MAX(资产摘要[[#Totals],[1月]:[12月]])* (1+$N$15)^( (U22 - YEAR(TODAY())) * 12 + (12 - MONTH(TODAY())) ) -> 22747108

Sheet 投资收益表
A1: 投资收益率趋势 | B1: 需将下方日期手动更新
B2: =DATE(2026,1,30) -> 46052 | C2: =DATE(2026,2,28) -> 46081 | D2: =DATE(2026,3,30) -> 46111 | E2: =DATE(2026,4,30) -> 46142 | F2: =总资产摘要!F2 -> 45792 | G2: =总资产摘要!G2 -> 45823 | H2: =总资产摘要!H2 -> 45853 | I2: =总资产摘要!I2 -> 45884 | J2: =总资产摘要!J2 -> 45915 | K2: =总资产摘要!K2 -> 45945 | L2: =总资产摘要!L2 -> 45975 | M2: =总资产摘要!M2 -> 46006 | N2: 提示
A4: 投资分类 | B4: 1月 | C4: 2月 | D4: 3月 | E4: 4月 | F4: 5月 | G4: 6月 | H4: 7月 | I4: 8月 | J4: 9月 | K4: 10月 | L4: 11月 | M4: 12月 | N4: 全年统计 | O4: 环比增长 | P4: 趋势 | Q4: 占比 | R4: 意见 | S4: 判定下限 | T4: 判定上限
A5: 东方财富（A股） | B5: =SUMIFS(ExpJan投资组合[金额],ExpJan投资组合[分类],投资收益表[[#This Row],[投资分类]]) -> 1789.74 | C5: =SUMIFS(ExpFeb投资组合[金额],ExpFeb投资组合[分类],投资收益表[[#This Row],[投资分类]]) -> 682.66 | D5: =SUMIFS(ExpMar投资组合[金额],ExpMar投资组合[分类],投资收益表[[#This Row],[投资分类]]) -> -558.57 | E5: =SUMIFS(ExpApr投资组合[金额],ExpApr投资组合[分类],投资收益表[[#This Row],[投资分类]]) -> 1059.07 | F5: =SUMIFS(ExpMay投资组合[金额],ExpMay投资组合[分类],投资收益表[[#This Row],[投资分类]]) -> 388.65 | G5: =SUMIFS(ExpJun投资组合[金额],ExpJun投资组合[分类],投资收益表[[#This Row],[投资分类]]) -> 626.84 | H5: =SUMIFS(ExpJul投资组合[金额],ExpJul投资组合[分类],投资收益表[[#This Row],[投资分类]]) -> 172.98 | I5: =SUMIFS(ExpAug投资组合[金额],ExpAug投资组合[分类],投资收益表[[#This Row],[投资分类]]) -> -59.03 | J5: =SUMIFS(ExpSep投资组合[金额],ExpSep投资组合[分类],投资收益表[[#This Row],[投资分类]]) -> -167.04 | K5: =SUMIFS(ExpOct投资组合[金额],ExpOct投资组合[分类],投资收益表[[#This Row],[投资分类]]) -> 1083.94 | L5: =SUMIFS(ExpNov投资组合[金额],ExpNov投资组合[分类],投资收益表[[#This Row],[投资分类]]) -> -841 | M5: =SUMIFS(ExpDec投资组合[金额],ExpDec投资组合[分类],投资收益表[[#This Row],[投资分类]]) -> 9.07 | N5: =SUBTOTAL(9,投资收益表[[#This Row],[1月]:[12月]]) -> 4187.31 | O5: {=IFERROR( IF( INDEX(B5:M5, MONTH(TODAY())) = 0, INDEX(B5:M5, IF(MONTH(TODAY())=1, 12, MONTH(TODAY())-1)) - INDEX(B5:M5, IF(MONTH(TODAY())=1, 11, MONTH(TODAY())-2)), INDEX(B5:M5, MONTH(TODAY())) - INDEX(B5:M5, IF(MONTH(TODAY())=1, 12, MONTH(TODAY())-1)) ), "" )/ IFERROR( IF( INDEX(B5:M5, MONTH(TODAY())) = 0, INDEX(B5:M5,MONTH(TODAY())-1), INDEX(B5:M5,MONTH(TODAY())) ), "" )} -> -1.7249968 | Q5: =INDEX(投资收益表[#This Row], MATCH(TEXT(TODAY(),"m") & "月", 投资收益表[#Headers], 0))/INDEX(投资收益表[#Totals], MATCH(TEXT(TODAY(),"m") & "月", 投资收益表[#Headers], 0)) -> 0.18003057 | R5: =IF(AND(投资收益表[[#This Row],[占比]]>=投资收益表[[#This Row],[判定下限]], 投资收益表[[#This Row],[占比]]<=投资收益表[[#This Row],[判定上限]]),"合理","不合理") -> 不合理 | S5: 0 | T5: 0.05
A6: 长桥证券（美港股） | B6: =SUMIFS(ExpJan投资组合[金额],ExpJan投资组合[分类],投资收益表[[#This Row],[投资分类]]) -> 4060.96 | C6: =SUMIFS(ExpFeb投资组合[金额],ExpFeb投资组合[分类],投资收益表[[#This Row],[投资分类]]) -> 367.93 | D6: =SUMIFS(ExpMar投资组合[金额],ExpMar投资组合[分类],投资收益表[[#This Row],[投资分类]]) -> -1445.84 | E6: =SUMIFS(ExpApr投资组合[金额],ExpApr投资组合[分类],投资收益表[[#This Row],[投资分类]]) -> 2811.09 | F6: =SUMIFS(ExpMay投资组合[金额],ExpMay投资组合[分类],投资收益表[[#This Row],[投资分类]]) -> 1088.01 | G6: =SUMIFS(ExpJun投资组合[金额],ExpJun投资组合[分类],投资收益表[[#This Row],[投资分类]]) -> 210.78 | H6: =SUMIFS(ExpJul投资组合[金额],ExpJul投资组合[分类],投资收益表[[#This Row],[投资分类]]) -> 78.74 | I6: =SUMIFS(ExpAug投资组合[金额],ExpAug投资组合[分类],投资收益表[[#This Row],[投资分类]]) -> 631.32 | J6: =SUMIFS(ExpSep投资组合[金额],ExpSep投资组合[分类],投资收益表[[#This Row],[投资分类]]) -> 393.22 | K6: =SUMIFS(ExpOct投资组合[金额],ExpOct投资组合[分类],投资收益表[[#This Row],[投资分类]]) -> 1154.26 | L6: =SUMIFS(ExpNov投资组合[金额],ExpNov投资组合[分类],投资收益表[[#This Row],[投资分类]]) -> 1667.26 | M6: =SUMIFS(ExpDec投资组合[金额],ExpDec投资组合[分类],投资收益表[[#This Row],[投资分类]]) -> 219.6 | N6: =SUBTOTAL(9,投资收益表[[#This Row],[1月]:[12月]]) -> 11237.33 | O6: {=IFERROR( IF( INDEX(B6:M6, MONTH(TODAY())) = 0, INDEX(B6:M6, IF(MONTH(TODAY())=1, 12, MONTH(TODAY())-1)) - INDEX(B6:M6, IF(MONTH(TODAY())=1, 11, MONTH(TODAY())-2)), INDEX(B6:M6, MONTH(TODAY())) - INDEX(B6:M6, IF(MONTH(TODAY())=1, 12, MONTH(TODAY())-1)) ), "" )/ IFERROR( IF( INDEX(B6:M6, MONTH(TODAY())) = 0, INDEX(B6:M6,MONTH(TODAY())-1), INDEX(B6:M6,MONTH(TODAY())) ), "" )} -> -1.5836987 | Q6: =INDEX(投资收益表[#This Row], MATCH(TEXT(TODAY(),"m") & "月", 投资收益表[#Headers], 0))/INDEX(投资收益表[#Totals], MATCH(TEXT(TODAY(),"m") & "月", 投资收益表[#Headers], 0)) -> 0.50398833 | R6: =IF(AND(投资收益表[[#This Row],[占比]]>=投资收益表[[#This Row],[判定下限]], 投资收益表[[#This Row],[占比]]<=投资收益表[[#This Row],[判定上限]]),"合理","不合理") -> 不合理 | S6: 0.6 | T6: 0.8 | W6: 每月消费 | X6: 每年消费 | Y6: 被动收入 年化收益率 | Z6: 被动资产
A7: 比特币 | B7: =SUMIFS(ExpJan投资组合[金额],ExpJan投资组合[分类],投资收益表[[#This Row],[投资分类]]) -> 0.071264 | C7: =SUMIFS(ExpFeb投资组合[金额],ExpFeb投资组合[分类],投资收益表[[#This Row],[投资分类]]) -> 0.071264 | D7: =SUMIFS(ExpMar投资组合[金额],ExpMar投资组合[分类],投资收益表[[#This Row],[投资分类]]) -> 0.071264 | E7: =SUMIFS(ExpApr投资组合[金额],ExpApr投资组合[分类],投资收益表[[#This Row],[投资分类]]) -> 0.071264 | F7: =SUMIFS(ExpMay投资组合[金额],ExpMay投资组合[分类],投资收益表[[#This Row],[投资分类]]) -> 0.071264 | G7: =SUMIFS(ExpJun投资组合[金额],ExpJun投资组合[分类],投资收益表[[#This Row],[投资分类]]) -> 0.071264 | H7: =SUMIFS(ExpJul投资组合[金额],ExpJul投资组合[分类],投资收益表[[#This Row],[投资分类]]) -> 0.071264 | I7: =SUMIFS(ExpAug投资组合[金额],ExpAug投资组合[分类],投资收益表[[#This Row],[投资分类]]) -> 0.071264 | J7: =SUMIFS(ExpSep投资组合[金额],ExpSep投资组合[分类],投资收益表[[#This Row],[投资分类]]) -> 0.071264 | K7: =SUMIFS(ExpOct投资组合[金额],ExpOct投资组合[分类],投资收益表[[#This Row],[投资分类]]) -> 0.071264 | L7: =SUMIFS(ExpNov投资组合[金额],ExpNov投资组合[分类],投资收益表[[#This Row],[投资分类]]) -> 0.071264 | M7: =SUMIFS(ExpDec投资组合[金额],ExpDec投资组合[分类],投资收益表[[#This Row],[投资分类]]) -> 0 | N7: {=IFERROR( IF( INDEX(B7:M7, MONTH(TODAY())) = 0, INDEX(B7:M7, IF(MONTH(TODAY())=1, 12, MONTH(TODAY())-1)) - INDEX(B7:M7, IF(MONTH(TODAY())=1, 11, MONTH(TODAY())-2)), INDEX(B7:M7, MONTH(TODAY())) - INDEX(B7:M7, IF(MONTH(TODAY())=1, 12, MONTH(TODAY())-1)) ), "" )} -> 0 | O7: {=IFERROR( IF( INDEX(B7:M7, MONTH(TODAY())) = 0, INDEX(B7:M7, IF(MONTH(TODAY())=1, 12, MONTH(TODAY())-1)) - INDEX(B7:M7, IF(MONTH(TODAY())=1, 11, MONTH(TODAY())-2)), INDEX(B7:M7, MONTH(TODAY())) - INDEX(B7:M7, IF(MONTH(TODAY())=1, 12, MONTH(TODAY())-1)) ), "" )/ IFERROR( IF( INDEX(B7:M7, MONTH(TODAY())) = 0, INDEX(B7:M7,MONTH(TODAY())-1), INDEX(B7:M7,MONTH(TODAY())) ), "" )} -> 0 | Q7: =INDEX(投资收益表[#This Row], MATCH(TEXT(TODAY(),"m") & "月", 投资收益表[#Headers], 0))/INDEX(投资收益表[#Totals], MATCH(TEXT(TODAY(),"m") & "月", 投资收益表[#Headers], 0)) -> 3.3010932e-05 | R7: =IF(AND(投资收益表[[#This Row],[占比]]>=投资收益表[[#This Row],[判定下限]], 投资收益表[[#This Row],[占比]]<=投资收益表[[#This Row],[判定上限]]),"合理","不合理") -> 合理 | S7: 0 | T7: 0.07 | W7: 2500 | X7: =表11[[#This Row],[每月消费]]*12 -> 30000 | Y7: 0.07 | Z7: =表11[[#This Row],[每年消费]]/表11[[#This Row],[被动收入 年化收益率]] -> 428571.43
A8: 基金（招行） | B8: =SUMIFS(ExpJan投资组合[金额],ExpJan投资组合[分类],投资收益表[[#This Row],[投资分类]]) -> 1661.3 | C8: =SUMIFS(ExpFeb投资组合[金额],ExpFeb投资组合[分类],投资收益表[[#This Row],[投资分类]]) -> 921.04 | D8: =SUMIFS(ExpMar投资组合[金额],ExpMar投资组合[分类],投资收益表[[#This Row],[投资分类]]) -> -1154.66 | E8: =SUMIFS(ExpApr投资组合[金额],ExpApr投资组合[分类],投资收益表[[#This Row],[投资分类]]) -> 1325.68 | F8: =SUMIFS(ExpMay投资组合[金额],ExpMay投资组合[分类],投资收益表[[#This Row],[投资分类]]) -> 682.14 | G8: =SUMIFS(ExpJun投资组合[金额],ExpJun投资组合[分类],投资收益表[[#This Row],[投资分类]]) -> 1217.79 | H8: =SUMIFS(ExpJul投资组合[金额],ExpJul投资组合[分类],投资收益表[[#This Row],[投资分类]]) -> 511.63 | I8: =SUMIFS(ExpAug投资组合[金额],ExpAug投资组合[分类],投资收益表[[#This Row],[投资分类]]) -> 709.94 | J8: =SUMIFS(ExpSep投资组合[金额],ExpSep投资组合[分类],投资收益表[[#This Row],[投资分类]]) -> 290.64 | K8: =SUMIFS(ExpOct投资组合[金额],ExpOct投资组合[分类],投资收益表[[#This Row],[投资分类]]) -> 603.17 | L8: =SUMIFS(ExpNov投资组合[金额],ExpNov投资组合[分类],投资收益表[[#This Row],[投资分类]]) -> -91.75 | M8: =SUMIFS(ExpDec投资组合[金额],ExpDec投资组合[分类],投资收益表[[#This Row],[投资分类]]) -> 289.77 | N8: =SUBTOTAL(9,投资收益表[[#This Row],[1月]:[12月]]) -> 6966.69 | O8: {=IFERROR( IF( INDEX(B8:M8, MONTH(TODAY())) = 0, INDEX(B8:M8, IF(MONTH(TODAY())=1, 12, MONTH(TODAY())-1)) - INDEX(B8:M8, IF(MONTH(TODAY())=1, 11, MONTH(TODAY())-2)), INDEX(B8:M8, MONTH(TODAY())) - INDEX(B8:M8, IF(MONTH(TODAY())=1, 12, MONTH(TODAY())-1)) ), "" )/ IFERROR( IF( INDEX(B8:M8, MONTH(TODAY())) = 0, INDEX(B8:M8,MONTH(TODAY())-1), INDEX(B8:M8,MONTH(TODAY())) ), "" )} -> -0.94341338 | Q8: =INDEX(投资收益表[#This Row], MATCH(TEXT(TODAY(),"m") & "月", 投资收益表[#Headers], 0))/INDEX(投资收益表[#Totals], MATCH(TEXT(TODAY(),"m") & "月", 投资收益表[#Headers], 0)) -> 0.3159811 | R8: =IF(AND(投资收益表[[#This Row],[占比]]>=投资收益表[[#This Row],[判定下限]], 投资收益表[[#This Row],[占比]]<=投资收益表[[#This Row],[判定上限]]),"合理","不合理") -> 合理 | S8: 0 | T8: 0.5 | W8: 2500 | X8: =表11[[#This Row],[每月消费]]*12 -> 30000 | Y8: 0.1 | Z8: =表11[[#This Row],[每年消费]]/表11[[#This Row],[被动收入 年化收益率]] -> 300000
A9: 定期 | B9: =SUMIFS(ExpJan[金额],ExpJan[分类],投资收益表[[#This Row],[投资分类]]) -> 0 | C9: =SUMIFS(ExpFeb[金额],ExpFeb[分类],投资收益表[[#This Row],[投资分类]]) -> 0 | D9: =SUMIFS(ExpMar[金额],ExpMar[分类],投资收益表[[#This Row],[投资分类]]) -> 0 | E9: =SUMIFS(ExpApr[金额],ExpApr[分类],投资收益表[[#This Row],[投资分类]]) -> 0 | F9: =SUMIFS(ExpMay[金额],ExpMay[分类],投资收益表[[#This Row],[投资分类]]) -> 0 | G9: =SUMIFS(ExpJun[金额],ExpJun[分类],投资收益表[[#This Row],[投资分类]]) -> 0 | H9: =SUMIFS(ExpJul[金额],ExpJul[分类],投资收益表[[#This Row],[投资分类]]) -> 0 | I9: =SUMIFS(ExpAug[金额],ExpAug[分类],投资收益表[[#This Row],[投资分类]]) -> 0 | J9: =SUMIFS(ExpSep[金额],ExpSep[分类],投资收益表[[#This Row],[投资分类]]) -> 0 | K9: =SUMIFS(ExpOct[金额],ExpOct[分类],投资收益表[[#This Row],[投资分类]]) -> 0 | L9: =SUMIFS(ExpNov[金额],ExpNov[分类],投资收益表[[#This Row],[投资分类]]) -> 0 | M9: 1365 | N9: =SUBTOTAL(9,投资收益表[[#This Row],[1月]:[12月]]) -> 0 | O9: {=IFERROR( IF( INDEX(B9:M9, MONTH(TODAY())) = 0, INDEX(B9:M9, IF(MONTH(TODAY())=1, 12, MONTH(TODAY())-1)) - INDEX(B9:M9, IF(MONTH(TODAY())=1, 11, MONTH(TODAY())-2)), INDEX(B9:M9, MONTH(TODAY())) - INDEX(B9:M9, IF(MONTH(TODAY())=1, 12, MONTH(TODAY())-1)) ), "" )/ IFERROR( IF( INDEX(B9:M9, MONTH(TODAY())) = 0, INDEX(B9:M9,MONTH(TODAY())-1), INDEX(B9:M9,MONTH(TODAY())) ), "" )} -> #DIV/0! | Q9: =INDEX(投资收益表[#This Row], MATCH(TEXT(TODAY(),"m") & "月", 投资收益表[#Headers], 0))/INDEX(投资收益表[#Totals], MATCH(TEXT(TODAY(),"m") & "月", 投资收益表[#Headers], 0)) -> 0 | R9: =IF(AND(投资收益表[[#This Row],[占比]]>=投资收益表[[#This Row],[判定下限]], 投资收益表[[#This Row],[占比]]<=投资收益表[[#This Row],[判定上限]]),"合理","不合理") -> 合理
A10: 活期 | B10: =SUMIFS(ExpJan[金额],ExpJan[分类],投资收益表[[#This Row],[投资分类]]) -> 0 | C10: =SUMIFS(ExpFeb[金额],ExpFeb[分类],投资收益表[[#This Row],[投资分类]]) -> 13037.809 | D10: =SUMIFS(ExpMar[金额],ExpMar[分类],投资收益表[[#This Row],[投资分类]]) -> 1981.2592 | E10: =SUMIFS(ExpApr[金额],ExpApr[分类],投资收益表[[#This Row],[投资分类]]) -> 55.029167 | F10: =SUMIFS(ExpMay[金额],ExpMay[分类],投资收益表[[#This Row],[投资分类]]) -> 63.899167 | G10: =SUMIFS(ExpJun[金额],ExpJun[分类],投资收益表[[#This Row],[投资分类]]) -> 17757.08 | H10: =SUMIFS(ExpJul[金额],ExpJul[分类],投资收益表[[#This Row],[投资分类]]) -> 12661.761 | I10: =SUMIFS(ExpAug[金额],ExpAug[分类],投资收益表[[#This Row],[投资分类]]) -> 10065.269 | J10: =SUMIFS(ExpSep[金额],ExpSep[分类],投资收益表[[#This Row],[投资分类]]) -> 0 | K10: =SUMIFS(ExpOct[金额],ExpOct[分类],投资收益表[[#This Row],[投资分类]]) -> 0 | L10: =SUMIFS(ExpNov[金额],ExpNov[分类],投资收益表[[#This Row],[投资分类]]) -> 1.379167 | M10: =SUMIFS(ExpDec[金额],ExpDec[分类],投资收益表[[#This Row],[投资分类]]) -> 532.74917 | N10: {=IFERROR( INDEX(B10:M10, MONTH(TODAY())) - INDEX(B10:M10, IF(MONTH(TODAY())=1, 12, MONTH(TODAY())-1)), "")} -> 8.87 | O10: {=IFERROR( IF( INDEX(B10:M10, MONTH(TODAY())) = 0, INDEX(B10:M10, IF(MONTH(TODAY())=1, 12, MONTH(TODAY())-1)) - INDEX(B10:M10, IF(MONTH(TODAY())=1, 11, MONTH(TODAY())-2)), INDEX(B10:M10, MONTH(TODAY())) - INDEX(B10:M10, IF(MONTH(TODAY())=1, 12, MONTH(TODAY())-1)) ), "" )/ IFERROR( IF( INDEX(B10:M10, MONTH(TODAY())) = 0, INDEX(B10:M10,MONTH(TODAY())-1), INDEX(B10:M10,MONTH(TODAY())) ), "" )} -> 0.13881245 | Q10: =INDEX(投资收益表[#This Row], MATCH(TEXT(TODAY(),"m") & "月", 投资收益表[#Headers], 0))/INDEX(投资收益表[#Totals], MATCH(TEXT(TODAY(),"m") & "月", 投资收益表[#Headers], 0)) -> 0.029599392 | R10: =IF(AND(投资收益表[[#This Row],[占比]]>=投资收益表[[#This Row],[判定下限]], 投资收益表[[#This Row],[占比]]<=投资收益表[[#This Row],[判定上限]]),"合理","不合理") -> 不合理
A11: 紧急预备金 | B11: =SUMIFS(ExpJan[金额],ExpJan[分类],投资收益表[[#This Row],[投资分类]]) -> 0 | C11: =SUMIFS(ExpFeb[金额],ExpFeb[分类],投资收益表[[#This Row],[投资分类]]) -> 0 | D11: =SUMIFS(ExpMar[金额],ExpMar[分类],投资收益表[[#This Row],[投资分类]]) -> 0 | E11: =SUMIFS(ExpApr[金额],ExpApr[分类],投资收益表[[#This Row],[投资分类]]) -> 0 | F11: =SUMIFS(ExpMay[金额],ExpMay[分类],投资收益表[[#This Row],[投资分类]]) -> 0 | G11: =SUMIFS(ExpJun[金额],ExpJun[分类],投资收益表[[#This Row],[投资分类]]) -> 0 | H11: =SUMIFS(ExpJul[金额],ExpJul[分类],投资收益表[[#This Row],[投资分类]]) -> 0 | I11: =SUMIFS(ExpAug[金额],ExpAug[分类],投资收益表[[#This Row],[投资分类]]) -> 0 | J11: =SUMIFS(ExpSep[金额],ExpSep[分类],投资收益表[[#This Row],[投资分类]]) -> 0 | K11: =SUMIFS(ExpOct[金额],ExpOct[分类],投资收益表[[#This Row],[投资分类]]) -> 0 | L11: =SUMIFS(ExpNov[金额],ExpNov[分类],投资收益表[[#This Row],[投资分类]]) -> 0 | M11: =SUMIFS(ExpDec[金额],ExpDec[分类],投资收益表[[#This Row],[投资分类]]) -> 0 | N11: {=IFERROR( IF( INDEX(B11:M11, MONTH(TODAY())) = 0, INDEX(B11:M11, IF(MONTH(TODAY())=1, 12, MONTH(TODAY())-1)) - INDEX(B11:M11, IF(MONTH(TODAY())=1, 11, MONTH(TODAY())-2)), INDEX(B11:M11, MONTH(TODAY())) - INDEX(B11:M11, IF(MONTH(TODAY())=1, 12, MONTH(TODAY())-1)) ), "" )} -> 0 | O11: {=IFERROR( IF( INDEX(B11:M11, MONTH(TODAY())) = 0, INDEX(B11:M11, IF(MONTH(TODAY())=1, 12, MONTH(TODAY())-1)) - INDEX(B11:M11, IF(MONTH(TODAY())=1, 11, MONTH(TODAY())-2)), INDEX(B11:M11, MONTH(TODAY())) - INDEX(B11:M11, IF(MONTH(TODAY())=1, 12, MONTH(TODAY())-1)) ), "" )/ IFERROR( IF( INDEX(B11:M11, MONTH(TODAY())) = 0, INDEX(B11:M11,MONTH(TODAY())-1), INDEX(B11:M11,MONTH(TODAY())) ), "" )} -> #DIV/0! | Q11: =INDEX(投资收益表[#This Row], MATCH(TEXT(TODAY(),"m") & "月", 投资收益表[#Headers], 0))/INDEX(投资收益表[#Totals], MATCH(TEXT(TODAY(),"m") & "月", 投资收益表[#Headers], 0)) -> 0 | R11: =IF(AND(投资收益表[[#This Row],[占比]]>=投资收益表[[#This Row],[判定下限]], 投资收益表[[#This Row],[占比]]<=投资收益表[[#This Row],[判定上限]]),"合理","不合理") -> 合理 | S11: 0 | T11: 0.1
A12: {=IFERROR( _xlfn.LET( _xlpm.data, B12:M12, _xlpm.nonZeroData, IF(_xlpm.data>0, _xlpm.data, ""), _xlpm.minVal, MIN(_xlpm.nonZeroData), _xlpm.maxVal, MAX(_xlpm.data), _xlpm.startPos, MATCH(_xlpm.minVal, _xlpm.nonZeroData, 0), _xlpm.endPos, MATCH(_xlpm.maxVal, _xlpm.data, 0), _xlpm.startDate, INDEX(B2:M2, _xlpm.startPos), _xlpm.endDate, INDEX(B2:M2, _xlpm.endPos), IF(_xlpm.endDate < _xlpm.startDate, "", (_xlpm.maxVal / _xlpm.minVal) -1 ) ), "" )} -> 13.535041 | B12: =SUBTOTAL(109,投资收益表[1月]) -> 7512 | C12: =SUBTOTAL(109,投资收益表[2月]) -> 1971.63 | D12: =SUBTOTAL(109,投资收益表[3月]) -> -3159.07 | E12: =SUBTOTAL(109,投资收益表[4月]) -> 5195.84 | F12: =SUBTOTAL(109,投资收益表[5月]) -> 2158.8 | G12: =SUBTOTAL(109,投资收益表[6月]) -> 2055.41 | H12: =SUBTOTAL(109,投资收益表[7月]) -> 763.35 | I12: =SUBTOTAL(109,投资收益表[8月]) -> 1282.23 | J12: =SUBTOTAL(109,投资收益表[9月]) -> 516.82 | K12: =SUBTOTAL(109,投资收益表[10月]) -> 2841.37 | L12: =SUBTOTAL(109,投资收益表[11月]) -> 734.51 | M12: =SUBTOTAL(109,投资收益表[12月]) -> 518.44 | N12: =N5+N6+N8+N9 -> 22391.33 | O12: {=IFERROR( IF( INDEX(B12:M12, MONTH(TODAY())) = 0, INDEX(B12:M12, IF(MONTH(TODAY())=1, 12, MONTH(TODAY())-1)) - INDEX(B12:M12, IF(MONTH(TODAY())=1, 11, MONTH(TODAY())-2)), INDEX(B12:M12, MONTH(TODAY())) - INDEX(B12:M12, IF(MONTH(TODAY())=1, 12, MONTH(TODAY())-1)) ), "" )/ IFERROR( IF( INDEX(B12:M12, MONTH(TODAY())) = 0, INDEX(B12:M12,MONTH(TODAY())-1), INDEX(B12:M12,MONTH(TODAY())) ), "" )} -> -1.4068186 | P12: {=IFERROR( _xlfn.LET( _xlpm.data, B12:M12, _xlpm.nonZeroData, IF(_xlpm.data>0, _xlpm.data, ""), _xlpm.minVal, MIN(_xlpm.nonZeroData), _xlpm.maxVal, MAX(_xlpm.data), _xlpm.startPos, MATCH(_xlpm.minVal, _xlpm.nonZeroData, 0), _xlpm.endPos, MATCH(_xlpm.maxVal, _xlpm.data, 0), _xlpm.startDate, INDEX(B2:M2, _xlpm.startPos), _xlpm.endDate, INDEX(B2:M2, _xlpm.endPos), IF(_xlpm.endDate < _xlpm.startDate, "", _xlfn.LET( _xlpm.months, DATEDIF(_xlpm.startDate, _xlpm.endDate, "m") +1, (_xlpm.maxVal / _xlpm.minVal) ^ (12/_xlpm.months) -1 ) ) ), "" )} -> 615.30976 | Q12: =SUBTOTAL(109,投资收益表[占比]) -> 1 | S12: =SUBTOTAL(109,投资收益表[判定下限]) -> 0.6 | T12: =SUBTOTAL(109,投资收益表[判定上限]) -> 1.35
A13: 环比增长C | B13: =投资收益表[[#Totals],[1月]]/投资收益表[[#Totals],[12月]]-1 -> 13.489623 | C13: =IFERROR( _xlfn.LET( _xlpm.result, 投资收益表[[#Totals],[2月]]/投资收益表[[#Totals],[1月]]-1, IF(OR(_xlpm.result=0, _xlpm.result=-1), 0, _xlpm.result) ), 0 ) -> -0.73753594 | D13: =IFERROR( _xlfn.LET( _xlpm.result, 投资收益表[[#Totals],[3月]]/投资收益表[[#Totals],[2月]]-1, IF(OR(_xlpm.result=0, _xlpm.result=-1), 0, _xlpm.result) ), 0 ) -> -2.6022631 | E13: =IFERROR( _xlfn.LET( _xlpm.result, 投资收益表[[#Totals],[4月]]/投资收益表[[#Totals],[3月]]-1, IF(OR(_xlpm.result=0, _xlpm.result=-1), 0, _xlpm.result) ), 0 ) -> -2.6447372 | F13: =IFERROR( _xlfn.LET( _xlpm.result, 投资收益表[[#Totals],[5月]]/投资收益表[[#Totals],[4月]]-1, IF(OR(_xlpm.result=0, _xlpm.result=-1), 0, _xlpm.result) ), 0 ) -> -0.58451376 | G13: =IFERROR( _xlfn.LET( _xlpm.result, 投资收益表[[#Totals],[6月]]/投资收益表[[#Totals],[5月]]-1, IF(OR(_xlpm.result=0, _xlpm.result=-1), 0, _xlpm.result) ), 0 ) -> -0.047892348 | H13: =IFERROR( _xlfn.LET( _xlpm.result, 投资收益表[[#Totals],[7月]]/投资收益表[[#Totals],[6月]]-1, IF(OR(_xlpm.result=0, _xlpm.result=-1), 0, _xlpm.result) ), 0 ) -> -0.62861424 | I13: =IFERROR( _xlfn.LET( _xlpm.result, 投资收益表[[#Totals],[8月]]/投资收益表[[#Totals],[7月]]-1, IF(OR(_xlpm.result=0, _xlpm.result=-1), 0, _xlpm.result) ), 0 ) -> 0.67974062 | J13: =IFERROR( _xlfn.LET( _xlpm.result, 投资收益表[[#Totals],[9月]]/投资收益表[[#Totals],[8月]]-1, IF(OR(_xlpm.result=0, _xlpm.result=-1), 0, _xlpm.result) ), 0 ) -> -0.59693659 | K13: =IFERROR( _xlfn.LET( _xlpm.result, 投资收益表[[#Totals],[10月]]/投资收益表[[#Totals],[9月]]-1, IF(OR(_xlpm.result=0, _xlpm.result=-1), 0, _xlpm.result) ), 0 ) -> 4.4977942 | L13: =IFERROR( _xlfn.LET( _xlpm.result, 投资收益表[[#Totals],[11月]]/投资收益表[[#Totals],[10月]]-1, IF(OR(_xlpm.result=0, _xlpm.result=-1), 0, _xlpm.result) ), 0 ) -> -0.74149442 | M13: =IFERROR( _xlfn.LET( _xlpm.result, 投资收益表[[#Totals],[12月]]/投资收益表[[#Totals],[11月]]-1, IF(OR(_xlpm.result=0, _xlpm.result=-1), 0, _xlpm.result) ), 0 ) -> -0.2941689 | N13: =SUMIF(B13:M13, ">0") / COUNTIF(B13:M13, ">0") -> 6.2223858 | O13: =投资收益表[[#Totals],[全年统计]]/(AVERAGE(资产摘要[[#Totals],[1月]:[12月]])) -> 0.059215481
B15: 基金简称 | C15: 基金代码 | D15: 持有起始日期 | E15: 持有天数 | F15: %基金N日净值增长率 | G15: 账面价值 | H15: 每2天定投 | I15: 每月平均 | J15: 当前比例 | K15: 推荐比例
B16: =[1]!EM_F_INFO_NAME(C16) -> Refreshing | C16: 110017 | D16: 45631 | E16: =([1]!EM_DATECOUNT(D16,$C$23,"CNSESH")) -> #NAME? | F16: =[1]!EM_F_NQ_NAVCHANGE(基金[[#This Row],[基金代码]],-E16) -> #NAME? | G16: 64765.22 | H16: 160 | I16: 200 | J16: =基金[[#This Row],[账面价值]]/基金[[#Totals],[账面价值]] -> 0.95984721 | K16: 0.5
B17: =[1]!EM_F_INFO_NAME(C17) -> Refreshing | C17: 270042 | D17: 45632 | E17: =([1]!EM_DATECOUNT(D17,$C$23,"CNSESH")) -> #NAME? | F17: =[1]!EM_F_NQ_NAVCHANGE(基金[[#This Row],[基金代码]],-E17) -> #NAME? | G17: 0 | H17: 100 | I17: =基金[[#This Row],[每2天定投]]*11 -> 1100 | J17: =基金[[#This Row],[账面价值]]/基金[[#Totals],[账面价值]] -> 0 | K17: 0.15
B18: =[1]!EM_F_INFO_NAME(C18) -> Refreshing | C18: 007280 | D18: 45895 | E18: =([1]!EM_DATECOUNT(D18,$C$23,"CNSESH")) -> #NAME? | F18: =[1]!EM_F_NQ_NAVCHANGE(基金[[#This Row],[基金代码]],-E18) -> #NAME? | G18: 204.93 | H18: 100 | I18: =基金[[#This Row],[每2天定投]]*11 -> 1100 | J18: =基金[[#This Row],[账面价值]]/基金[[#Totals],[账面价值]] -> 0.0030371469 | K18: 0.15
B19: =[1]!EM_F_INFO_NAME(C19) -> Refreshing | C19: 007721 | D19: 45940 | E19: =([1]!EM_DATECOUNT(D19,$C$23,"CNSESH")) -> #NAME? | F19: =[1]!EM_F_NQ_NAVCHANGE(基金[[#This Row],[基金代码]],-E19) -> #NAME? | G19: 2405.47 | H19: 100 | I19: =基金[[#This Row],[每2天定投]]*11 -> 1100 | J19: =基金[[#This Row],[账面价值]]/基金[[#Totals],[账面价值]] -> 0.035650055 | K19: 0.15
B20: =[1]!EM_F_INFO_NAME(C20) -> Refreshing | C20: 000390 | D20: 45904 | E20: =([1]!EM_DATECOUNT(D20,$C$23,"CNSESH")) -> #NAME? | F20: =[1]!EM_F_NQ_NAVCHANGE(基金[[#This Row],[基金代码]],-E20) -> #NAME? | G20: 98.89 | H20: 26.66 | I20: =基金[[#This Row],[每2天定投]]*11 -> 293.26 | J20: =基金[[#This Row],[账面价值]]/基金[[#Totals],[账面价值]] -> 0.0014655905 | K20: 0.05
B21: =[1]!EM_F_INFO_NAME(C21) -> Refreshing | C21: 000216 | D21: 45924 | E21: =([1]!EM_DATECOUNT(D21,$C$23,"CNSESH")) -> #NAME? | F21: =[1]!EM_F_NQ_NAVCHANGE(基金[[#This Row],[基金代码]],-E21) -> #NAME? | G21: 966.87 | H21: 0 | I21: =基金[[#This Row],[每2天定投]]*11 -> 0 | J21: =基金[[#This Row],[每2天定投]]/基金[[#Totals],[每2天定投]] -> 0 | K21: 0
B22: =[1]!EM_F_INFO_NAME(C22) -> Refreshing | C22: 096001 | D22: 45902 | E22: =([1]!EM_DATECOUNT(D22,$C$23,"CNSESH")) -> #NAME? | F22: =[1]!EM_F_NQ_NAVCHANGE(基金[[#This Row],[基金代码]],-E22) -> #NAME? | G22: 5270.51 | H22: 0.01 | I22: =基金[[#This Row],[每2天定投]]*11 -> 0.11 | J22: =基金[[#This Row],[每2天定投]]/基金[[#Totals],[每2天定投]] -> 2.0548227e-05 | K22: 0
B23: 汇总 | C23: =TODAY() -> 46166 | G23: =SUBTOTAL(109,基金[账面价值]) -> 67474.51 | H23: =SUBTOTAL(109,基金[每2天定投]) -> 486.66 | I23: =SUBTOTAL(109,基金[每月平均]) -> 3793.26 | J23: =SUBTOTAL(109,基金[当前比例]) -> 1 | K23: =SUBTOTAL(109,基金[推荐比例]) -> 1
B25: 公司 | C25: 代码 | D25: 股份 | E25: 成本价 | F25: 当前价格 | G25: 变化（百分比） | H25: 持仓成本 | I25: 账面价值 | J25: 当前比例 | K25: 推荐比例
B26: #VALUE! | C26: SPY | D26: 3 | E26: 664.49 | F26: =_FV(美股投资表[[#This Row],[公司]],"Price") -> 662.23 | G26: =美股投资表[[#This Row],[账面价值]]/美股投资表[[#This Row],[持仓成本]]-1 -> -0.0034011046 | H26: =美股投资表[[#This Row],[股份]]*美股投资表[[#This Row],[成本价]] -> 1993.47 | I26: =美股投资表[[#This Row],[股份]]*美股投资表[[#This Row],[当前价格]] -> 1986.69 | J26: =IFERROR(I26/SUBTOTAL(109,美股投资表[账面价值]),"") -> 0.46088161 | K26: 0.5
B27: #VALUE! | C27: SCHD | D27: 40 | E27: 26.523 | F27: =_FV(美股投资表[[#This Row],[公司]],"Price") -> 26.87 | G27: =美股投资表[[#This Row],[账面价值]]/美股投资表[[#This Row],[持仓成本]]-1 -> 0.013082985 | H27: =美股投资表[[#This Row],[股份]]*美股投资表[[#This Row],[成本价]] -> 1060.92 | I27: =美股投资表[[#This Row],[股份]]*美股投资表[[#This Row],[当前价格]] -> 1074.8 | J27: =IFERROR(I27/SUBTOTAL(109,美股投资表[账面价值]),"") -> 0.24933712 | K27: 0.2
B28: #VALUE! | C28: QQQ | D28: 2 | E28: 608.095 | F28: =_FV(美股投资表[[#This Row],[公司]],"Price") -> 624.5699 | G28: =美股投资表[[#This Row],[账面价值]]/美股投资表[[#This Row],[持仓成本]]-1 -> 0.027092642 | H28: =美股投资表[[#This Row],[股份]]*美股投资表[[#This Row],[成本价]] -> 1216.19 | I28: =美股投资表[[#This Row],[股份]]*美股投资表[[#This Row],[当前价格]] -> 1249.1398 | J28: =IFERROR(I28/SUBTOTAL(109,美股投资表[账面价值]),"") -> 0.28978128 | K28: 0.3
B29: #VALUE! | C29: DGRO | D29: 11 | E29: 64.909 | F29: =_FV(美股投资表[[#This Row],[公司]],"Price") -> 68.07 | G29: =美股投资表[[#This Row],[账面价值]]/美股投资表[[#This Row],[持仓成本]]-1 -> 0.048698948 | H29: =美股投资表[[#This Row],[股份]]*美股投资表[[#This Row],[成本价]] -> 713.999 | I29: =美股投资表[[#This Row],[股份]]*美股投资表[[#This Row],[当前价格]] -> 748.77 | J29: =IFERROR(I29/SUBTOTAL(109,美股投资表[账面价值]),"") -> 0.17370316 | K29: 0
B30: =[1]!EM_S_INFO_HKSHARENAME(C30) -> Refreshing | C30: 00883 | D30: 1000 | E30: 2.38 | F30: =[1]!EM_HKS_DQ_CLOSE(C30,"N","3","1") -> #NAME? | G30: =美股投资表[[#This Row],[账面价值]]/美股投资表[[#This Row],[持仓成本]]-1 -> #NAME? | H30: =美股投资表[[#This Row],[股份]]*美股投资表[[#This Row],[成本价]] -> 2380 | I30: =美股投资表[[#This Row],[股份]]*美股投资表[[#This Row],[当前价格]] -> #NAME? | J30: =IFERROR(I30/SUBTOTAL(109,美股投资表[账面价值]),"")
B31: 汇总 | G31: =美股投资表[[#Totals],[账面价值]]/美股投资表[[#Totals],[持仓成本]]-1 -> 0.0093780704 | H31: =SUBTOTAL(109,美股投资表[持仓成本]) -> 4270.58 | I31: =SUBTOTAL(109,美股投资表[账面价值]) -> 4310.6298
B34: 公司 | C34: 证券代码 | D34: 股份 | E34: 成本价 | F34: 当前价格 | G34: 变化（百分比） | H34: 持仓成本 | I34: 账面价值 | J34: 买入理由 | K34: 推荐比例
B35: =[1]!EM_S_INFO_COMPNAME(C35) -> Refreshing | C35: 601919 | D35: 1400 | E35: 14.004 | F35: =[1]!EM_S_DQ_CLOSE(C35,"N","1") -> Refreshing | G35: =A股投资表[[#This Row],[账面价值]]/A股投资表[[#This Row],[持仓成本]]-1 -> #VALUE! | H35: =A股投资表[[#This Row],[股份]]*A股投资表[[#This Row],[成本价]] -> 19605.6 | I35: =A股投资表[[#This Row],[股份]]*A股投资表[[#This Row],[当前价格]] -> #VALUE!
B36: =[1]!EM_S_INFO_COMPNAME(C36) -> Refreshing | C36: 600060 | D36: 300 | E36: 22.797 | F36: =[1]!EM_S_DQ_CLOSE(C36,"N","1") -> Refreshing | G36: =A股投资表[[#This Row],[账面价值]]/A股投资表[[#This Row],[持仓成本]]-1 -> #VALUE! | H36: =A股投资表[[#This Row],[股份]]*A股投资表[[#This Row],[成本价]] -> 6839.1 | I36: =A股投资表[[#This Row],[股份]]*A股投资表[[#This Row],[当前价格]] -> #VALUE!
B37: =[1]!EM_S_INFO_COMPNAME(C37) -> Refreshing | C37: 300770 | D37: 0 | F37: =[1]!EM_S_DQ_CLOSE(C37,"N","1") -> Refreshing | G37: =A股投资表[[#This Row],[账面价值]]/A股投资表[[#This Row],[持仓成本]]-1 -> #VALUE! | H37: =A股投资表[[#This Row],[股份]]*A股投资表[[#This Row],[成本价]] -> 0 | I37: =A股投资表[[#This Row],[股份]]*A股投资表[[#This Row],[当前价格]] -> #VALUE! | J37: 1.营业收入： 1）IPTV业务维持8.3亿左右规模 2）互联网视听业务维持5%增长，>6.33亿 2.分红回报和管理层决策 3）股利支付率持续>70%，股息率>4.5% 3.政策支持 4）到27年年底免税政策25%免税 4.市场地位: 7个牌照持有者之一（电视内容管控商） | K37: 内在价值计算出是40元 安全边际： 20%→32元→PE11.7→2w投入 30%→28元→PE10.2→3w投入 40%→24元→PE8.8→4w投入 考虑2028年税收政策取消后 内在价值仅剩下 28元，可基于此重新估算
B38: =[1]!EM_S_INFO_COMPNAME(C38) -> Refreshing | C38: 600941 | D38: 100 | E38: 94.241 | F38: =[1]!EM_S_DQ_CLOSE(C38,"N","1") -> Refreshing | G38: =A股投资表[[#This Row],[账面价值]]/A股投资表[[#This Row],[持仓成本]]-1 -> #VALUE! | H38: =A股投资表[[#This Row],[股份]]*A股投资表[[#This Row],[成本价]] -> 9424.1 | I38: =A股投资表[[#This Row],[股份]]*A股投资表[[#This Row],[当前价格]] -> #VALUE!
B39: 汇总 | G39: =A股投资表[[#Totals],[账面价值]]/A股投资表[[#Totals],[持仓成本]]-1 -> #VALUE! | H39: =SUBTOTAL(109,A股投资表[持仓成本]) -> 35868.8 | I39: =SUBTOTAL(109,A股投资表[账面价值]) -> #VALUE!
B42: 列1 | C42: 指标名称 | D42: 严苛指标 | E42: 列4 | F42: 放宽指标 | G42: 列6 | H42: 列7
C43: XX年自由现金流倍数
C44: 净资产收益率ROE | D44: 连续3年大于10%
C45: 加权净资产收益率 | D45: >10%
C46: 销售毛利率 | D46: 筛选>50%
C47: 销售净利率 | D47: 筛选>10%
B48: 筛选轻资产企业 | C48: XX年固定资产/总资产 | D48: 连续3年低于20%，属于是轻资产
B49: 筛选轻资产企业 | C49: 1/(有形资产/带息债务) | D49: 低于15%
B50: 筛选轻资产企业 | C50: 经营活动产生的现金流量净额/净利润 | D50: 推荐>1
C51: 资本支出TTM/营业总收入 | D51: 推荐0`50
B52: 可选项 | C52: 资本支出/折旧摊销 | E52: >100%，则说明在扩张，可能可以搭配ROE
B53: 可选性 | C53: 总市值/股权自由现金流FCFE（正推法） | D53: 15>默认>0 | E53: 自由现金流倍数，可评估股价高低 市值 = 股价 × 总股本
B54: 可选性 | C54: EV/FCFF（企业价值/企业自由现金流） | D54: 今年18> >0 | E54: EV = 市 值 + 总 负 债 − 货 币 资 金 其中： 选择 “企业价值EV2（剔除货币资金）” 选择“企业自由现金流FCFF（反推法）” | F54: 适用于评估负债

Sheet 1 月
A1: 1 月支出 | D1: 摘要 | E1: 提示
A2: 日期 | B2: PO# | C2: 汇率（特殊-CNY） | D2: 特殊币种 | E2: 金额 | F2: 类别 | G2: 描述 | H2: 分类
B3: A-12345 | E3: 192935.76 | F3: 招商银行
B4: A-12346 | E4: 2119.37 | F4: 中国银行
E5: 41299.21 | F5: 东方财富
C6: #VALUE! | D6: 0.01 | E6: {=ExpJan[[#This Row],[特殊币种]]*_FV(ExpJan[[#This Row],[汇率（特殊-CNY）]],"Price")} -> 0.009167 | F6: 中银香港
C7: 6.83 | D7: 1295.18 | E7: =ExpJan[[#This Row],[汇率（特殊-CNY）]]*ExpJan[[#This Row],[特殊币种]] -> 8846.0794 | F7: 币安Biance
E8: 46588.66 | F8: 长桥证券
E9: 46095 | F9: 东莞农村商业银行
E10: =134.84+0.02 -> 134.86 | F10: 微信
E11: 0.2 | F11: 支付宝
A12: 汇总 | E12: =SUBTOTAL(109,ExpJan[金额]) -> 338019.15
A14: 日期 | B14: PO# | C14: 汇率（特殊-CNY） | D14: 特殊币种 | E14: 金额 | F14: 类别 | G14: 描述 | H14: 分类
E15: 1789.74 | F15: 东方财富（A股） | G15: 填写收益 | H15: 东方财富（A股）
E16: 4060.96 | F16: 长桥证券（美港股） | H16: 长桥证券（美港股）
C17: #VALUE! | D17: 0.01 | E17: {=ExpJan投资组合[[#This Row],[特殊币种]]*_FV(ExpJan投资组合[[#This Row],[汇率（特殊-CNY）]],"Price")} -> 0.071264 | F17: 比特币 | H17: 比特币
E18: 1661.3 | F18: 基金（招行） | H18: 基金（招行）
A19: 汇总 | E19: =SUBTOTAL(109,ExpJan投资组合[金额]) -> 7512.0713

Sheet 2 月
A1: 2 月支出 | F1: 摘要 | G1: 提示
A2: 日期 | B2: PO# | C2: 汇率（特殊-CNY） | D2: 特殊币种 | E2: 金额 | F2: 类别 | G2: 描述 | H2: 分类
E3: 260187.53 | F3: 招商银行 | G3: TRUE | H3: 基金
E4: 2084.81 | F4: 中国银行 | G4: TRUE | H4: 活期
E5: 42623.14 | F5: 东方财富 | G5: TRUE | H5: 股票
C6: #VALUE! | D6: 0.01 | E6: {=ExpFeb[[#This Row],[特殊币种]]*_FV(ExpFeb[[#This Row],[汇率（特殊-CNY）]],"Price")} -> 0.009167 | F6: 中银香港 | G6: TRUE | H6: 活期
C7: 6.84 | D7: 1100.94 | E7: =ExpFeb[[#This Row],[汇率（特殊-CNY）]]*ExpFeb[[#This Row],[特殊币种]] -> 7530.4296 | F7: 币安Biance | G7: TRUE | H7: 比特币
E8: 48786.92 | F8: 长桥证券 | G8: TRUE | H8: 股票
E9: 0.01 | F9: 东莞农村商业银行 | G9: TRUE | H9: 定期等安全投资
E10: =668.45+197.76 -> 866.21 | F10: 微信 | G10: TRUE | H10: 活期
E11: 10086.78 | F11: 支付宝 | G11: TRUE | H11: 活期
A12: 汇总 | E12: =SUBTOTAL(109,ExpFeb[金额]) -> 372165.84
A14: 日期 | B14: PO# | C14: 汇率（特殊-CNY） | D14: 特殊币种 | E14: 金额 | F14: 类别 | G14: 描述 | H14: 分类
E15: 682.66 | F15: 东方财富（A股） | G15: 填写收益 | H15: 东方财富（A股）
E16: 367.93 | F16: 长桥证券（美港股） | H16: 长桥证券（美港股）
C17: #VALUE! | D17: 0.01 | E17: {=ExpFeb投资组合[[#This Row],[特殊币种]]*_FV(ExpFeb投资组合[[#This Row],[汇率（特殊-CNY）]],"Price")} -> 0.071264 | F17: 比特币 | H17: 比特币
E18: 921.04 | F18: 基金（招行） | H18: 基金（招行）
A19: 汇总 | E19: =SUBTOTAL(109,ExpFeb投资组合[金额]) -> 1971.7013

Sheet 3 月
A1: 3 月支出 | D1: 摘要 | E1: 提示
A2: 日期 | B2: PO# | C2: 汇率（特殊-CNY） | D2: 特殊币种 | E2: 金额 | F2: 类别 | G2: 描述 | H2: 分类
B3: A-12345 | E3: 429074.87 | F3: 招商银行 | G3: 补给 | H3: 基金
B4: A-12346 | E4: 1973.89 | F4: 中国银行 | H4: 活期
E5: 54889.23 | F5: 东方财富 | H5: 股票
C6: #VALUE! | D6: 0.01 | E6: {=ExpMar[[#This Row],[特殊币种]]*_FV(ExpMar[[#This Row],[汇率（特殊-CNY）]],"Price")} -> 0.009167 | F6: 中银香港 | H6: 活期
E7: 7845.43 | F7: 币安Biance | H7: 比特币
E8: 48266.09 | F8: 长桥证券 | H8: 股票
E9: 0.01 | F9: 东莞农村商业银行 | H9: 定期等安全投资
E10: =4.08+3.26 -> 7.34 | F10: 微信 | H10: 活期
E11: 0.02 | F11: 支付宝 | H11: 活期
A12: 汇总 | E12: =SUBTOTAL(109,ExpMar[金额]) -> 542056.89
A14: 日期 | B14: PO# | C14: 汇率（特殊-CNY） | D14: 特殊币种 | E14: 金额 | F14: 类别 | G14: 描述 | H14: 分类
E15: -558.57 | F15: 东方财富（A股） | G15: 填写收益 | H15: 东方财富（A股）
E16: -1445.84 | F16: 长桥证券（美港股） | H16: 长桥证券（美港股）
C17: #VALUE! | D17: 0.01 | E17: {=ExpMar投资组合[[#This Row],[特殊币种]]*_FV(ExpMar投资组合[[#This Row],[汇率（特殊-CNY）]],"Price")} -> 0.071264 | F17: 比特币 | H17: 比特币
E18: -1154.66 | F18: 基金（招行） | H18: 基金（招行）
A19: 汇总 | E19: =SUBTOTAL(109,ExpMar投资组合[金额]) -> -3158.9987

Sheet 4 月
A1: 4 月支出 | F1: 摘要 | G1: 提示
A2: 日期 | B2: PO# | C2: 汇率（特殊-CNY） | D2: 特殊币种 | E2: 金额 | F2: 类别 | G2: 描述 | H2: 分类
E3: 353671.01 | F3: 招商银行 | H3: 基金
E4: 53.08 | F4: 中国银行 | H4: 活期
E5: 140024.49 | F5: 东方财富 | H5: 股票
C6: #VALUE! | D6: 0.01 | E6: {=_FV(ExpApr[[#This Row],[汇率（特殊-CNY）]],"Price")*ExpApr[[#This Row],[特殊币种]]} -> 0.009167 | F6: 中银香港 | H6: 活期
C7: 7.29 | D7: 1229.17 | E7: 7988.15 | F7: 币安Biance | G7: 使用首页显示 | H7: 比特币
E8: 48651.67 | F8: 长桥证券 | G8: 使用首页显示 | H8: 股票
E9: 0 | F9: 东莞农村商业银行 | H9: 定期等安全投资
E10: =1.64+0.26 -> 1.9 | F10: 微信 | H10: 活期
E11: 0.04 | F11: 支付宝 | H11: 活期
A12: 汇总 | E12: =SUBTOTAL(109,ExpApr[金额]) -> 550390.35
A14: 日期 | B14: PO# | C14: 汇率（特殊-CNY） | D14: 特殊币种 | E14: 金额 | F14: 类别 | G14: 描述 | H14: 分类
E15: 1059.07 | F15: 东方财富（A股） | G15: 填写收益 | H15: 东方财富（A股）
E16: 2811.09 | F16: 长桥证券（美港股） | H16: 长桥证券（美港股）
C17: #VALUE! | D17: 0.01 | E17: {=ExpApr投资组合[[#This Row],[特殊币种]]*_FV(ExpApr投资组合[[#This Row],[汇率（特殊-CNY）]],"Price")} -> 0.071264 | F17: 比特币 | H17: 比特币
E18: 1325.68 | F18: 基金（招行） | H18: 基金（招行）
A19: 汇总 | E19: =SUBTOTAL(109,ExpApr投资组合[金额]) -> 5195.9113

Sheet 5 月
A1: 5 月支出 | F1: 摘要 | G1: 提示
A2: 日期 | B2: PO# | C2: 汇率（特殊-CNY） | D2: 特殊币种 | E2: 金额 | F2: 类别 | G2: 描述 | H2: 分类
B3: A-12345 | E3: 372604.37 | F3: 招商银行 | H3: 基金
B4: A-12346 | E4: 52.95 | F4: 中国银行 | H4: 活期
E5: 140296.64 | F5: 东方财富 | H5: 股票
C6: #VALUE! | D6: 0.01 | E6: {=_FV(ExpMay[[#This Row],[汇率（特殊-CNY）]],"Price")*ExpMay[[#This Row],[特殊币种]]} -> 0.009167 | F6: 中银香港 | H6: 活期
C7: 7.21 | D7: 1268.88 | E7: 8321.18 | F7: 币安Biance | H7: 比特币
E8: 49834.35 | F8: 长桥证券 | H8: 股票
E9: 0 | F9: 东莞农村商业银行 | H9: 定期等安全投资
E10: =0.26+9.64 -> 9.9 | F10: 微信 | H10: 活期
E11: 1.04 | F11: 支付宝 | H11: 活期
A12: 汇总 | E12: =SUBTOTAL(109,ExpMay[金额]) -> 571120.44
A14: 日期 | B14: PO# | C14: 汇率（特殊-CNY） | D14: 特殊币种 | E14: 金额 | F14: 类别 | G14: 描述 | H14: 分类
E15: 388.65 | F15: 东方财富（A股） | G15: 填写收益 | H15: 东方财富（A股）
E16: 1088.01 | F16: 长桥证券（美港股） | H16: 长桥证券（美港股）
C17: #VALUE! | D17: 0.01 | E17: {=ExpMay投资组合[[#This Row],[特殊币种]]*_FV(ExpMay投资组合[[#This Row],[汇率（特殊-CNY）]],"Price")} -> 0.071264 | F17: 比特币 | H17: 比特币
E18: 682.14 | F18: 基金（招行） | H18: 基金（招行）
A19: 汇总 | E19: =SUBTOTAL(109,ExpMay投资组合[金额]) -> 2158.8713

Sheet 6 月
A1: 6 月支出 | F1: 摘要 | G1: 提示
A2: 日期 | B2: PO# | C2: 汇率（特殊-CNY） | D2: 特殊币种 | E2: 金额 | F2: 类别 | G2: 描述 | H2: 分类
E3: 153397.45 | F3: 招商银行 | G3: 补给 | H3: 基金
E4: 10458.89 | F4: 中国银行 | H4: 活期
E5: 21009.23 | F5: 东方财富 | H5: 股票
C6: #VALUE! | D6: 800 | E6: {=_FV(ExpJun[[#This Row],[汇率（特殊-CNY）]],"Price")*ExpJun[[#This Row],[特殊币种]]} -> 5701.12 | F6: 中银香港 | H6: 活期
C7: 7.18 | D7: 1269.85 | E7: =ExpJun[[#This Row],[汇率（特殊-CNY）]]*ExpJun[[#This Row],[特殊币种]] -> 9117.523 | F7: 币安Biance | H7: 比特币
E8: 8484.92 | F8: 长桥证券 | H8: 股票
E9: 81466.09 | F9: 东莞农村商业银行 | H9: 定期等安全投资
E10: =1168.89+117.2 -> 1286.09 | F10: 微信 | H10: 活期
E11: 310.98 | F11: 支付宝 | H11: 活期
A12: 汇总 | E12: =SUBTOTAL(109,ExpJun[金额]) -> 291232.29
A14: 日期 | B14: PO# | C14: 汇率（特殊-CNY） | D14: 特殊币种 | E14: 金额 | F14: 类别 | G14: 描述 | H14: 分类
E15: 626.84 | F15: 东方财富（A股） | G15: 填写收益 | H15: 东方财富（A股）
E16: 210.78 | F16: 长桥证券（美港股） | H16: 长桥证券（美港股）
C17: #VALUE! | D17: 0.01 | E17: {=ExpJun投资组合[[#This Row],[特殊币种]]*_FV(ExpJun投资组合[[#This Row],[汇率（特殊-CNY）]],"Price")} -> 0.071264 | F17: 比特币 | H17: 比特币
E18: 1217.79 | F18: 基金（招行） | H18: 基金（招行）
A19: 汇总 | E19: =SUBTOTAL(109,ExpJun投资组合[金额]) -> 2055.4813

Sheet 7 月
A1: 7 月支出 | F1: 摘要 | G1: 提示
A2: 日期 | B2: PO# | C2: 汇率（特殊-CNY） | D2: 特殊币种 | E2: 金额 | F2: 类别 | G2: 描述 | H2: 分类
E3: 162079.94 | F3: 招商银行 | G3: 补给 | H3: 基金
E4: 12612.22 | F4: 中国银行 | H4: 活期
E5: 20932.77 | F5: 东方财富 | H5: 股票
C6: #VALUE! | D6: 0.01 | E6: {=_FV(ExpJul[[#This Row],[汇率（特殊-CNY）]],"Price")*ExpJul[[#This Row],[特殊币种]]} -> 0.071264 | F6: 中银香港 | H6: 活期
C7: 7.15 | D7: 1273.25 | E7: =ExpJul[[#This Row],[特殊币种]]*ExpJul[[#This Row],[汇率（特殊-CNY）]] -> 9103.7375 | F7: 币安Biance | H7: 比特币
E8: =8840+5744.32 -> 14584.32 | F8: 长桥证券 | H8: 股票
E9: 81503.45 | F9: 东莞农村商业银行 | H9: 定期等安全投资
E10: =1.23+1.7 -> 2.93 | F10: 微信 | H10: 活期
E11: 46.54 | F11: 支付宝 | H11: 活期
A12: 汇总 | E12: =SUBTOTAL(109,ExpJul[金额]) -> 300865.98
A14: 日期 | B14: PO# | C14: 汇率（特殊-CNY） | D14: 特殊币种 | E14: 金额 | F14: 类别 | G14: 描述 | H14: 分类
E15: 172.98 | F15: 东方财富（A股） | G15: 填写收益 | H15: 东方财富（A股）
E16: 78.74 | F16: 长桥证券（美港股） | H16: 长桥证券（美港股）
C17: #VALUE! | D17: 0.01 | E17: {=ExpJul投资组合[[#This Row],[特殊币种]]*_FV(ExpJul投资组合[[#This Row],[汇率（特殊-CNY）]],"Price")} -> 0.071264 | F17: 比特币 | H17: 比特币
E18: 511.63 | F18: 基金（招行） | H18: 基金（招行）
A19: 汇总 | E19: =SUBTOTAL(109,ExpJul投资组合[金额]) -> 763.42126

Sheet 8 月
A1: 8 月资产统计 | F1: 摘要 | G1: 提示
A2: 日期 | B2: PO# | C2: 汇率（特殊-CNY） | D2: 特殊币种 | E2: 金额 | F2: 类别 | G2: 描述 | H2: 分类
B3: A-12345 | E3: 169392.9 | F3: 招商银行 | H3: 基金
B4: A-12346 | E4: 10057.35 | F4: 中国银行 | H4: 活期
E5: 21072.81 | F5: 东方财富 | H5: 股票
C6: #VALUE! | D6: 0.01 | E6: {=ExpAug[[#This Row],[特殊币种]]*_FV(ExpAug[[#This Row],[汇率（特殊-CNY）]],"Price")} -> 0.009167 | F6: 中银香港 | H6: 活期
C7: 7.14 | D7: 1278.71 | E7: =ExpAug[[#This Row],[特殊币种]]*ExpAug[[#This Row],[汇率（特殊-CNY）]] -> 9129.9894 | F7: 币安Biance | H7: 比特币
E8: 14975.57 | F8: 长桥证券 | H8: 股票
E9: 81591.43 | F9: 东莞农村商业银行 | H9: 定期等安全投资
E10: =2.55+3.4 -> 5.95 | F10: 微信 | H10: 活期
E11: 1.96 | F11: 支付宝 | H11: 活期
A12: 汇总 | E12: =SUBTOTAL(109,ExpAug[金额]) -> 306227.97
A14: 日期 | B14: PO# | C14: 汇率（特殊-CNY） | D14: 特殊币种 | E14: 金额 | F14: 类别 | G14: 描述 | H14: 分类
E15: -59.03 | F15: 东方财富（A股） | G15: 填写收益 | H15: 东方财富（A股）
E16: 631.32 | F16: 长桥证券（美港股） | H16: 长桥证券（美港股）
C17: #VALUE! | D17: 0.01 | E17: {=ExpAug投资组合[[#This Row],[特殊币种]]*_FV(ExpAug投资组合[[#This Row],[汇率（特殊-CNY）]],"Price")} -> 0.071264 | F17: 比特币 | H17: 比特币
E18: 709.94 | F18: 基金（招行） | H18: 基金（招行）
A19: 汇总 | E19: =SUBTOTAL(109,ExpAug投资组合[金额]) -> 1282.3013

Sheet 9月
A1: 9月资产统计 | F1: 摘要 | G1: 提示
A2: 日期 | B2: PO# | C2: 汇率（特殊-CNY） | D2: 特殊币种 | E2: 金额 | F2: 类别 | G2: 描述 | H2: 分类
B3: A-12345 | E3: =21348.29 -> 21348.29 | F3: 招商银行
E4: 14351.12 | F4: 招商银行
E5: 104792.71 | F5: 招商银行
E6: 17668.31 | F6: 招商银行
E7: 14297.97 | F7: 招商银行
B8: A-12346 | E8: 294.56 | F8: 中国银行
E9: 20901.54 | F9: 东方财富
C10: #VALUE! | D10: 0.1 | E10: {=ExpSep[[#This Row],[特殊币种]]*_FV(ExpSep[[#This Row],[汇率（特殊-CNY）]],"Price")} -> 0.09167 | F10: 中银香港
C11: 6.97 | D11: 1285.92 | E11: =ExpSep[[#This Row],[特殊币种]]*ExpSep[[#This Row],[汇率（特殊-CNY）]] -> 8962.8624 | F11: 币安Biance
E12: 22866.26 | F12: 长桥证券
E13: 77615.66 | F13: 东莞农村商业银行
E14: =0.19+1.81 -> 2 | F14: 微信
E15: 0.96 | F15: 支付宝
A16: 汇总 | E16: =SUBTOTAL(109,ExpSep[金额]) -> 303102.33
A18: 日期 | B18: PO# | C18: 汇率（特殊-CNY） | D18: 特殊币种 | E18: 金额 | F18: 类别 | G18: 描述 | H18: 分类
E19: -167.04 | F19: 东方财富（A股） | G19: 填写收益 | H19: 东方财富（A股）
E20: 393.22 | F20: 长桥证券（美港股） | H20: 长桥证券（美港股）
C21: #VALUE! | D21: 0.01 | E21: {=ExpSep投资组合[[#This Row],[特殊币种]]*_FV(ExpSep投资组合[[#This Row],[汇率（特殊-CNY）]],"Price")} -> 0.071264 | F21: 比特币 | H21: 比特币
E22: 290.64 | F22: 基金（招行） | H22: 基金（招行）
A23: 汇总 | E23: =SUBTOTAL(109,ExpSep投资组合[金额]) -> 516.89126

Sheet 10月
A1: 10月资产统计 | F1: 摘要 | G1: 提示
A2: 日期 | B2: PO# | C2: 汇率（特殊-CNY） | D2: 特殊币种 | E2: 金额 | F2: 类别 | G2: 描述 | H2: 分类
B3: A-12345 | E3: 168232.73 | F3: 招商银行
B4: A-12346 | E4: 6.86 | F4: 中国银行
E5: 21785.1 | F5: 东方财富
C6: #VALUE! | D6: 0 | E6: {=ExpOct[[#This Row],[特殊币种]]*_FV(ExpOct[[#This Row],[汇率（特殊-CNY）]],"Price")} -> 0 | F6: 中银香港
C7: 6.77 | D7: 1298.54 | E7: =ExpOct[[#This Row],[特殊币种]]*ExpOct[[#This Row],[汇率（特殊-CNY）]] -> 8791.1158 | F7: 币安Biance
E8: 43401.35 | F8: 长桥证券
E9: 73876.46 | F9: 东莞农村商业银行 | G9: 切换成预算
E10: =6.29+154.64 -> 160.93 | F10: 微信
E11: 1.15 | F11: 支付宝
A12: 汇总 | E12: =SUBTOTAL(109,ExpOct[金额]) -> 316255.7
A14: 日期 | B14: PO# | C14: 汇率（特殊-CNY） | D14: 特殊币种 | E14: 金额 | F14: 类别 | G14: 描述 | H14: 分类
E15: 1083.94 | F15: 东方财富（A股） | G15: 填写收益 | H15: 东方财富（A股）
E16: 1154.26 | F16: 长桥证券（美港股） | H16: 长桥证券（美港股）
C17: #VALUE! | D17: 0.01 | E17: {=ExpOct投资组合[[#This Row],[特殊币种]]*_FV(ExpOct投资组合[[#This Row],[汇率（特殊-CNY）]],"Price")} -> 0.071264 | F17: 比特币 | H17: 比特币
E18: 603.17 | F18: 基金（招行） | H18: 基金（招行）
A19: 汇总 | E19: =SUBTOTAL(109,ExpOct投资组合[金额]) -> 2841.4413

Sheet 11 月
A1: 11 月支出 | F1: 摘要 | G1: 提示
A2: 日期 | B2: PO# | C2: 汇率（特殊-CNY） | D2: 特殊币种 | E2: 金额 | F2: 类别 | G2: 描述 | H2: 分类
E3: 173631.04 | F3: 招商银行 | G3: 补给 | H3: 基金
E4: 0.32 | F4: 中国银行 | H4: 活期
E5: 22484.1 | F5: 东方财富 | H5: 股票
C6: #VALUE! | D6: 0.01 | E6: {=ExpNov[[#This Row],[特殊币种]]*_FV(ExpNov[[#This Row],[汇率（特殊-CNY）]],"Price")} -> 0.009167 | F6: 中银香港 | H6: 活期
C7: 7.02 | D7: 1276.38 | E7: =ExpNov[[#This Row],[特殊币种]]*ExpNov[[#This Row],[汇率（特殊-CNY）]] -> 8960.1876 | F7: 币安Biance | H7: 比特币
E8: 46395.65 | F8: 长桥证券 | H8: 股票
E9: 69682.36 | F9: 东莞农村商业银行 | H9: 定期等安全投资
E10: 0.9 | F10: 微信 | H10: 活期
E11: 0.15 | F11: 支付宝 | H11: 活期
A12: 汇总 | E12: =SUBTOTAL(109,ExpNov[金额]) -> 321154.72
A14: 日期 | B14: PO# | C14: 汇率（特殊-CNY） | D14: 特殊币种 | E14: 金额 | F14: 类别 | G14: 描述 | H14: 分类
E15: -841 | F15: 东方财富（A股） | G15: 填写收益 | H15: 东方财富（A股）
E16: 1667.26 | F16: 长桥证券（美港股） | H16: 长桥证券（美港股）
C17: #VALUE! | D17: 0.01 | E17: {=ExpNov投资组合[[#This Row],[特殊币种]]*_FV(ExpNov投资组合[[#This Row],[汇率（特殊-CNY）]],"Price")} -> 0.071264 | F17: 比特币 | H17: 比特币
E18: -91.75 | F18: 基金（招行） | H18: 基金（招行）
A19: 汇总 | E19: =SUBTOTAL(109,ExpNov投资组合[金额]) -> 734.58126

Sheet 12 月
A1: 12 月支出 | F1: 摘要 | G1: 提示
A2: 日期 | B2: PO# | C2: 汇率（特殊-CNY） | D2: 特殊币种 | E2: 金额 | F2: 类别 | G2: 描述 | H2: 分类
E3: 187595.64 | F3: 招商银行 | H3: 基金
E4: 468.18 | F4: 中国银行 | H4: 活期
E5: 26416.7 | F5: 东方财富 | H5: 股票
C6: #VALUE! | D6: 0.01 | E6: {=ExpDec[[#This Row],[特殊币种]]*_FV(ExpDec[[#This Row],[汇率（特殊-CNY）]],"Price")} -> 0.009167 | F6: 中银香港 | H6: 活期
C7: 6.83 | D7: 1265.64 | E7: =ExpDec[[#This Row],[汇率（特殊-CNY）]]*ExpDec[[#This Row],[特殊币种]] -> 8644.3212 | F7: 币安Biance | H7: 比特币
E8: 45130.43 | F8: 长桥证券 | H8: 股票
E9: 56685.01 | F9: 东莞农村商业银行 | H9: 定期等安全投资
E10: =1.04+0.02 -> 1.06 | F10: 微信 | H10: 活期
E11: 63.5 | F11: 支付宝 | H11: 活期
A12: 汇总 | E12: =SUBTOTAL(109,ExpDec[金额]) -> 325004.85
A14: 日期 | B14: PO# | C14: 汇率（特殊-CNY） | D14: 特殊币种 | E14: 金额 | F14: 类别 | G14: 描述 | H14: 分类
E15: 9.07 | F15: 东方财富（A股） | G15: 填写收益 | H15: 东方财富（A股）
E16: 219.6 | F16: 长桥证券（美港股） | H16: 长桥证券（美港股）
C17: #VALUE! | E17: 0 | F17: 比特币 | H17: 比特币
E18: 289.77 | F18: 基金（招行） | H18: 基金（招行）
A19: 汇总 | E19: =SUBTOTAL(109,ExpDec投资组合[金额]) -> 518.44

Sheet 提示
A1: 模板提示
A2: 有无在“支出趋势”摘要表和“每月支出明细”之间跳转的简单方法？
A3: 若要快速导航到特定月份的支出，请单击图表上方的相关导航链接，如 B2 中的 1 月导航链接。若要返回“支出趋势”工作表，请单击 D1 中的摘要导航链接。
A4: 若要返回此提示工作表，请在摘要工作表中选择 N2。从所有月份工作表中选择 E1。
A5: 如何将新的支出类型添加到“支出摘要”或新的每月支出？
A6: 图表下方的“支出摘要”和每月支出详细信息是 Excel 表格。若要向任何 Excel 表格添加新行，请执行下列操作之一：
A7: =ROW(A1)&". 如果表格中没有总计行，请在表格下方开始键入，当你按下 Enter 或 Tab 键时，它将自动展开。" -> 1. 如果表格中没有总计行，请在表格下方开始键入，当你按下 Enter 或 Tab 键时，它将自动展开。
A8: =ROW(A2)&". 将单元格指针放在总计行上方的最后一个单元格（如，最后一个费用的总计），然后按 Tab 键。" -> 2. 将单元格指针放在总计行上方的最后一个单元格（如，最后一个费用的总计），然后按 Tab 键。
A9: =ROW(A3)&". 右键单击表格，然后在弹出菜单上，指向“插入”，然后单击“在上方插入表行”或“在下方插入表行”。" -> 3. 右键单击表格，然后在弹出菜单上，指向“插入”，然后单击“在上方插入表行”或“在下方插入表行”。
A10: =ROW(A4)&". 在表格的右下角，将鼠标放在表格的尺寸控点上并向下拖动以增加可用表行数。" -> 4. 在表格的右下角，将鼠标放在表格的尺寸控点上并向下拖动以增加可用表行数。
A11: 在摘要工作表中“支出摘要”表的“支出”列输入支出。
A12: 在支出适用的月工作表中添加每种支出类型的支出金额。
A13: 例如:1 月到 6 月以及 12 月中有“支出 1”。
A14: =ROW(A1)&". 在“费用汇总”表的“费用”下的汇总工作表中输入“费用 1”（作为费用类型的标题）" -> 1. 在“费用汇总”表的“费用”下的汇总工作表中输入“费用 1”（作为费用类型的标题）
A15: =ROW(A2)&". 对于发生费用的每个月，在相应的月份工作表中输入费用金额。" -> 2. 对于发生费用的每个月，在相应的月份工作表中输入费用金额。
A16: =ROW(A3)&". “费用汇总”工作表的费用类型为每月工作表的“类别”列创建了类别列表。" -> 3. “费用汇总”工作表的费用类型为每月工作表的“类别”列创建了类别列表。
A17: =ROW(A4)&". 使用“类别”列的类别列表为输入的费用金额选择相应的费用类型" -> 4. 使用“类别”列的类别列表为输入的费用金额选择相应的费用类型
A18: =ROW(A5)&". 若要添加每个月份的新增费用，请在汇总工作表的“费用汇总”表中添加新行，然后在适用的月份工作表中输入相应的费用详细信息。" -> 5. 若要添加每个月份的新增费用，请在汇总工作表的“费用汇总”表中添加新行，然后在适用的月份工作表中输入相应的费用详细信息。

Sheet Kutools_Chart
A1: 0 | B1: =SUM(总资产摘要!$B$5:$M$5)/SUM(总资产摘要!$B$5:$M$13)*100 -> 12.529 | C1: =SUM(总资产摘要!$B$5:$M$5)/SUM(总资产摘要!$B$5:$M$13)*100 -> 12.529 | D1: =SUM(总资产摘要!$B$6:$M$6)/SUM(总资产摘要!$B$5:$M$13)*100+Kutools_Chart!$B$1 -> 74.131252 | E1: =SUM(总资产摘要!$B$6:$M$6)/SUM(总资产摘要!$B$5:$M$13)*100+Kutools_Chart!$B$1 -> 74.131252 | F1: =SUM(总资产摘要!$B$7:$M$7)/SUM(总资产摘要!$B$5:$M$13)*100+Kutools_Chart!$D$1 -> 75.016798 | G1: =SUM(总资产摘要!$B$7:$M$7)/SUM(总资产摘要!$B$5:$M$13)*100+Kutools_Chart!$D$1 -> 75.016798 | H1: =SUM(总资产摘要!$B$8:$M$8)/SUM(总资产摘要!$B$5:$M$13)*100+Kutools_Chart!$F$1 -> 75.142445 | I1: =SUM(总资产摘要!$B$8:$M$8)/SUM(总资产摘要!$B$5:$M$13)*100+Kutools_Chart!$F$1 -> 75.142445 | J1: =SUM(总资产摘要!$B$9:$M$9)/SUM(总资产摘要!$B$5:$M$13)*100+Kutools_Chart!$H$1 -> 75.374139 | K1: =SUM(总资产摘要!$B$9:$M$9)/SUM(总资产摘要!$B$5:$M$13)*100+Kutools_Chart!$H$1 -> 75.374139 | L1: =SUM(总资产摘要!$B$10:$M$10)/SUM(总资产摘要!$B$5:$M$13)*100+Kutools_Chart!$J$1 -> 75.428795 | M1: =SUM(总资产摘要!$B$10:$M$10)/SUM(总资产摘要!$B$5:$M$13)*100+Kutools_Chart!$J$1 -> 75.428795 | N1: =SUM(总资产摘要!$B$11:$M$11)/SUM(总资产摘要!$B$5:$M$13)*100+Kutools_Chart!$L$1 -> 88.072822 | O1: =SUM(总资产摘要!$B$11:$M$11)/SUM(总资产摘要!$B$5:$M$13)*100+Kutools_Chart!$L$1 -> 88.072822 | P1: =SUM(总资产摘要!$B$12:$M$12)/SUM(总资产摘要!$B$5:$M$13)*100+Kutools_Chart!$N$1 -> 97.724765 | Q1: =SUM(总资产摘要!$B$12:$M$12)/SUM(总资产摘要!$B$5:$M$13)*100+Kutools_Chart!$N$1 -> 97.724765 | R1: =SUM(总资产摘要!$B$13:$M$13)/SUM(总资产摘要!$B$5:$M$13)*100+Kutools_Chart!$P$1 -> 100 | S1: =SUM(总资产摘要!$B$13:$M$13)/SUM(总资产摘要!$B$5:$M$13)*100+Kutools_Chart!$P$1 -> 100 | T1: 100
A2: =总资产摘要!$B$5/SUM(总资产摘要!$B$5:$M$5) -> 0.081079586 | B2: =总资产摘要!$B$5/SUM(总资产摘要!$B$5:$M$5) -> 0.081079586 | C2: =总资产摘要!$B$6/SUM(总资产摘要!$B$6:$M$6) -> 0.069022433 | D2: =总资产摘要!$B$6/SUM(总资产摘要!$B$6:$M$6) -> 0.069022433 | E2: =总资产摘要!$B$7/SUM(总资产摘要!$B$7:$M$7) -> 0.052743634 | F2: =总资产摘要!$B$7/SUM(总资产摘要!$B$7:$M$7) -> 0.052743634 | G2: =总资产摘要!$B$8/SUM(总资产摘要!$B$8:$M$8) -> 1.607863e-06 | H2: =总资产摘要!$B$8/SUM(总资产摘要!$B$8:$M$8) -> 1.607863e-06 | I2: =总资产摘要!$B$9/SUM(总资产摘要!$B$9:$M$9) -> 1.9023486e-05 | J2: =总资产摘要!$B$9/SUM(总资产摘要!$B$9:$M$9) -> 1.9023486e-05 | K2: =总资产摘要!$B$10/SUM(总资产摘要!$B$10:$M$10) -> 0.054377497 | L2: =总资产摘要!$B$10/SUM(总资产摘要!$B$10:$M$10) -> 0.054377497 | M2: =总资产摘要!$B$11/SUM(总资产摘要!$B$11:$M$11) -> 0.071983081 | N2: =总资产摘要!$B$11/SUM(总资产摘要!$B$11:$M$11) -> 0.071983081 | O2: =总资产摘要!$B$12/SUM(总资产摘要!$B$12:$M$12) -> 0.10637501 | P2: =总资产摘要!$B$12/SUM(总资产摘要!$B$12:$M$12) -> 0.10637501 | Q2: =总资产摘要!$B$13/SUM(总资产摘要!$B$13:$M$13) -> 0.085683778 | R2: =总资产摘要!$B$13/SUM(总资产摘要!$B$13:$M$13) -> 0.085683778 | S2: =总资产摘要!#REF!/SUM(总资产摘要!#REF!) -> #REF! | T2: =总资产摘要!#REF!/SUM(总资产摘要!#REF!) -> #REF!
A3: =总资产摘要!$C$5/SUM(总资产摘要!$B$5:$M$5) -> 1.7589671e-08 | B3: =总资产摘要!$C$5/SUM(总资产摘要!$B$5:$M$5) -> 1.7589671e-08 | C3: =总资产摘要!$C$6/SUM(总资产摘要!$B$6:$M$6) -> 0.093081637 | D3: =总资产摘要!$C$6/SUM(总资产摘要!$B$6:$M$6) -> 0.093081637 | E3: =总资产摘要!$C$7/SUM(总资产摘要!$B$7:$M$7) -> 0.051883557 | F3: =总资产摘要!$C$7/SUM(总资产摘要!$B$7:$M$7) -> 0.051883557 | G3: =总资产摘要!$C$8/SUM(总资产摘要!$B$8:$M$8) -> 1.607863e-06 | H3: =总资产摘要!$C$8/SUM(总资产摘要!$B$8:$M$8) -> 1.607863e-06 | I3: =总资产摘要!$C$9/SUM(总资产摘要!$B$9:$M$9) -> 0.95942861 | J3: =总资产摘要!$C$9/SUM(总资产摘要!$B$9:$M$9) -> 0.95942861 | K3: =总资产摘要!$C$10/SUM(总资产摘要!$B$10:$M$10) -> 0.34926837 | L3: =总资产摘要!$C$10/SUM(总资产摘要!$B$10:$M$10) -> 0.34926837 | M3: =总资产摘要!$C$11/SUM(总资产摘要!$B$11:$M$11) -> 0.074290645 | N3: =总资产摘要!$C$11/SUM(总资产摘要!$B$11:$M$11) -> 0.074290645 | O3: =总资产摘要!$C$12/SUM(总资产摘要!$B$12:$M$12) -> 0.11139426 | P3: =总资产摘要!$C$12/SUM(总资产摘要!$B$12:$M$12) -> 0.11139426 | Q3: =总资产摘要!$C$13/SUM(总资产摘要!$B$13:$M$13) -> 0.072940297 | R3: =总资产摘要!$C$13/SUM(总资产摘要!$B$13:$M$13) -> 0.072940297 | S3: =总资产摘要!#REF!/SUM(总资产摘要!#REF!) -> #REF! | T3: =总资产摘要!#REF!/SUM(总资产摘要!#REF!) -> #REF!
A4: =总资产摘要!$D$5/SUM(总资产摘要!$B$5:$M$5) -> 1.7589671e-08 | B4: =总资产摘要!$D$5/SUM(总资产摘要!$B$5:$M$5) -> 1.7589671e-08 | C4: =总资产摘要!$D$6/SUM(总资产摘要!$B$6:$M$6) -> 0.15350079 | D4: =总资产摘要!$D$6/SUM(总资产摘要!$B$6:$M$6) -> 0.15350079 | E4: =总资产摘要!$D$7/SUM(总资产摘要!$B$7:$M$7) -> 0.04912315 | F4: =总资产摘要!$D$7/SUM(总资产摘要!$B$7:$M$7) -> 0.04912315 | G4: =总资产摘要!$D$8/SUM(总资产摘要!$B$8:$M$8) -> 1.607863e-06 | H4: =总资产摘要!$D$8/SUM(总资产摘要!$B$8:$M$8) -> 1.607863e-06 | I4: =总资产摘要!$D$9/SUM(总资产摘要!$B$9:$M$9) -> 1.9023486e-06 | J4: =总资产摘要!$D$9/SUM(总资产摘要!$B$9:$M$9) -> 1.9023486e-06 | K4: =总资产摘要!$D$10/SUM(总资产摘要!$B$10:$M$10) -> 0.0029595939 | L4: =总资产摘要!$D$10/SUM(总资产摘要!$B$10:$M$10) -> 0.0029595939 | M4: =总资产摘要!$D$11/SUM(总资产摘要!$B$11:$M$11) -> 0.095670011 | N4: =总资产摘要!$D$11/SUM(总资产摘要!$B$11:$M$11) -> 0.095670011 | O4: =总资产摘要!$D$12/SUM(总资产摘要!$B$12:$M$12) -> 0.11020506 | P4: =总资产摘要!$D$12/SUM(总资产摘要!$B$12:$M$12) -> 0.11020506 | Q4: =总资产摘要!$D$13/SUM(总资产摘要!$B$13:$M$13) -> 0.075991414 | R4: =总资产摘要!$D$13/SUM(总资产摘要!$B$13:$M$13) -> 0.075991414 | S4: =总资产摘要!#REF!/SUM(总资产摘要!#REF!) -> #REF! | T4: =总资产摘要!#REF!/SUM(总资产摘要!#REF!) -> #REF!
A5: =总资产摘要!$E$5/SUM(总资产摘要!$B$5:$M$5) -> 0 | B5: =总资产摘要!$E$5/SUM(总资产摘要!$B$5:$M$5) -> 0 | C5: =总资产摘要!$E$6/SUM(总资产摘要!$B$6:$M$6) -> 0.12652519 | D5: =总资产摘要!$E$6/SUM(总资产摘要!$B$6:$M$6) -> 0.12652519 | E5: =总资产摘要!$E$7/SUM(总资产摘要!$B$7:$M$7) -> 0.0013209737 | F5: =总资产摘要!$E$7/SUM(总资产摘要!$B$7:$M$7) -> 0.0013209737 | G5: =总资产摘要!$E$8/SUM(总资产摘要!$B$8:$M$8) -> 1.607863e-06 | H5: =总资产摘要!$E$8/SUM(总资产摘要!$B$8:$M$8) -> 1.607863e-06 | I5: =总资产摘要!$E$9/SUM(总资产摘要!$B$9:$M$9) -> 3.8046973e-06 | J5: =总资产摘要!$E$9/SUM(总资产摘要!$B$9:$M$9) -> 3.8046973e-06 | K5: =总资产摘要!$E$10/SUM(总资产摘要!$B$10:$M$10) -> 0.00076610741 | L5: =总资产摘要!$E$10/SUM(总资产摘要!$B$10:$M$10) -> 0.00076610741 | M5: =总资产摘要!$E$11/SUM(总资产摘要!$B$11:$M$11) -> 0.2440578 | N5: =总资产摘要!$E$11/SUM(总资产摘要!$B$11:$M$11) -> 0.2440578 | O5: =总资产摘要!$E$12/SUM(总资产摘要!$B$12:$M$12) -> 0.11108545 | P5: =总资产摘要!$E$12/SUM(总资产摘要!$B$12:$M$12) -> 0.11108545 | Q5: =总资产摘要!$E$13/SUM(总资产摘要!$B$13:$M$13) -> 0.07737381 | R5: =总资产摘要!$E$13/SUM(总资产摘要!$B$13:$M$13) -> 0.07737381 | S5: =总资产摘要!#REF!/SUM(总资产摘要!#REF!) -> #REF! | T5: =总资产摘要!#REF!/SUM(总资产摘要!#REF!) -> #REF!
A6: =总资产摘要!$F$5/SUM(总资产摘要!$B$5:$M$5) -> 0 | B6: =总资产摘要!$F$5/SUM(总资产摘要!$B$5:$M$5) -> 0 | C6: =总资产摘要!$F$6/SUM(总资产摘要!$B$6:$M$6) -> 0.13329857 | D6: =总资产摘要!$F$6/SUM(总资产摘要!$B$6:$M$6) -> 0.13329857 | E6: =总资产摘要!$F$7/SUM(总资产摘要!$B$7:$M$7) -> 0.0013177385 | F6: =总资产摘要!$F$7/SUM(总资产摘要!$B$7:$M$7) -> 0.0013177385 | G6: =总资产摘要!$F$8/SUM(总资产摘要!$B$8:$M$8) -> 1.607863e-06 | H6: =总资产摘要!$F$8/SUM(总资产摘要!$B$8:$M$8) -> 1.607863e-06 | I6: =总资产摘要!$F$9/SUM(总资产摘要!$B$9:$M$9) -> 9.8922129e-05 | J6: =总资产摘要!$F$9/SUM(总资产摘要!$B$9:$M$9) -> 9.8922129e-05 | K6: =总资产摘要!$F$10/SUM(总资产摘要!$B$10:$M$10) -> 0.0039918228 | L6: =总资产摘要!$F$10/SUM(总资产摘要!$B$10:$M$10) -> 0.0039918228 | M6: =总资产摘要!$F$11/SUM(总资产摘要!$B$11:$M$11) -> 0.24453214 | N6: =总资产摘要!$F$11/SUM(总资产摘要!$B$11:$M$11) -> 0.24453214 | O6: =总资产摘要!$F$12/SUM(总资产摘要!$B$12:$M$12) -> 0.11378584 | P6: =总资产摘要!$F$12/SUM(总资产摘要!$B$12:$M$12) -> 0.11378584 | Q6: =总资产摘要!$F$13/SUM(总资产摘要!$B$13:$M$13) -> 0.080599563 | R6: =总资产摘要!$F$13/SUM(总资产摘要!$B$13:$M$13) -> 0.080599563 | S6: =总资产摘要!#REF!/SUM(总资产摘要!#REF!) -> #REF! | T6: =总资产摘要!#REF!/SUM(总资产摘要!#REF!) -> #REF!
A7: =总资产摘要!$G$5/SUM(总资产摘要!$B$5:$M$5) -> 0.14329617 | B7: =总资产摘要!$G$5/SUM(总资产摘要!$B$5:$M$5) -> 0.14329617 | C7: =总资产摘要!$G$6/SUM(总资产摘要!$B$6:$M$6) -> 0.054877671 | D7: =总资产摘要!$G$6/SUM(总资产摘要!$B$6:$M$6) -> 0.054877671 | E7: =总资产摘要!$G$7/SUM(总资产摘要!$B$7:$M$7) -> 0.26028483 | F7: =总资产摘要!$G$7/SUM(总资产摘要!$B$7:$M$7) -> 0.26028483 | G7: =总资产摘要!$G$8/SUM(总资产摘要!$B$8:$M$8) -> 0.99995856 | H7: =总资产摘要!$G$8/SUM(总资产摘要!$B$8:$M$8) -> 0.99995856 | I7: =总资产摘要!$G$9/SUM(总资产摘要!$B$9:$M$9) -> 0.029579619 | J7: =总资产摘要!$G$9/SUM(总资产摘要!$B$9:$M$9) -> 0.029579619 | K7: =总资产摘要!$G$10/SUM(总资产摘要!$B$10:$M$10) -> 0.51857004 | L7: =总资产摘要!$G$10/SUM(总资产摘要!$B$10:$M$10) -> 0.51857004 | M7: =总资产摘要!$G$11/SUM(总资产摘要!$B$11:$M$11) -> 0.036618354 | N7: =总资产摘要!$G$11/SUM(总资产摘要!$B$11:$M$11) -> 0.036618354 | O7: =总资产摘要!$G$12/SUM(总资产摘要!$B$12:$M$12) -> 0.019373459 | P7: =总资产摘要!$G$12/SUM(总资产摘要!$B$12:$M$12) -> 0.019373459 | Q7: =总资产摘要!$G$13/SUM(总资产摘要!$B$13:$M$13) -> 0.088313 | R7: =总资产摘要!$G$13/SUM(总资产摘要!$B$13:$M$13) -> 0.088313 | S7: =总资产摘要!#REF!/SUM(总资产摘要!#REF!) -> #REF! | T7: =总资产摘要!#REF!/SUM(总资产摘要!#REF!) -> #REF!
A8: =总资产摘要!$H$5/SUM(总资产摘要!$B$5:$M$5) -> 0.14336188 | B8: =总资产摘要!$H$5/SUM(总资产摘要!$B$5:$M$5) -> 0.14336188 | C8: =总资产摘要!$H$6/SUM(总资产摘要!$B$6:$M$6) -> 0.057983817 | D8: =总资产摘要!$H$6/SUM(总资产摘要!$B$6:$M$6) -> 0.057983817 | E8: =总资产摘要!$H$7/SUM(总资产摘要!$B$7:$M$7) -> 0.31387361 | F8: =总资产摘要!$H$7/SUM(总资产摘要!$B$7:$M$7) -> 0.31387361 | G8: =总资产摘要!$H$8/SUM(总资产摘要!$B$8:$M$8) -> 1.2499482e-05 | H8: =总资产摘要!$H$8/SUM(总资产摘要!$B$8:$M$8) -> 1.2499482e-05 | I8: =总资产摘要!$H$9/SUM(总资产摘要!$B$9:$M$9) -> 0.0044267653 | J8: =总资产摘要!$H$9/SUM(总资产摘要!$B$9:$M$9) -> 0.0044267653 | K8: =总资产摘要!$H$10/SUM(总资产摘要!$B$10:$M$10) -> 0.0011814183 | L8: =总资产摘要!$H$10/SUM(总资产摘要!$B$10:$M$10) -> 0.0011814183 | M8: =总资产摘要!$H$11/SUM(总资产摘要!$B$11:$M$11) -> 0.036485087 | N8: =总资产摘要!$H$11/SUM(总资产摘要!$B$11:$M$11) -> 0.036485087 | O8: =总资产摘要!$H$12/SUM(总资产摘要!$B$12:$M$12) -> 0.033300105 | P8: =总资产摘要!$H$12/SUM(总资产摘要!$B$12:$M$12) -> 0.033300105 | Q8: =总资产摘要!$H$13/SUM(总资产摘要!$B$13:$M$13) -> 0.088179473 | R8: =总资产摘要!$H$13/SUM(总资产摘要!$B$13:$M$13) -> 0.088179473 | S8: =总资产摘要!#REF!/SUM(总资产摘要!#REF!) -> #REF! | T8: =总资产摘要!#REF!/SUM(总资产摘要!#REF!) -> #REF!
A9: =总资产摘要!$I$5/SUM(总资产摘要!$B$5:$M$5) -> 0.14351664 | B9: =总资产摘要!$I$5/SUM(总资产摘要!$B$5:$M$5) -> 0.14351664 | C9: =总资产摘要!$I$6/SUM(总资产摘要!$B$6:$M$6) -> 0.060600016 | D9: =总资产摘要!$I$6/SUM(总资产摘要!$B$6:$M$6) -> 0.060600016 | E9: =总资产摘要!$I$7/SUM(总资产摘要!$B$7:$M$7) -> 0.25029192 | F9: =总资产摘要!$I$7/SUM(总资产摘要!$B$7:$M$7) -> 0.25029192 | G9: =总资产摘要!$I$8/SUM(总资产摘要!$B$8:$M$8) -> 1.607863e-06 | H9: =总资产摘要!$I$8/SUM(总资产摘要!$B$8:$M$8) -> 1.607863e-06 | I9: =总资产摘要!$I$9/SUM(总资产摘要!$B$9:$M$9) -> 0.00018643017 | J9: =总资产摘要!$I$9/SUM(总资产摘要!$B$9:$M$9) -> 0.00018643017 | K9: =总资产摘要!$I$10/SUM(总资产摘要!$B$10:$M$10) -> 0.0023991258 | L9: =总资产摘要!$I$10/SUM(总资产摘要!$B$10:$M$10) -> 0.0023991258 | M9: =总资产摘要!$I$11/SUM(总资产摘要!$B$11:$M$11) -> 0.036729172 | N9: =总资产摘要!$I$11/SUM(总资产摘要!$B$11:$M$11) -> 0.036729172 | O9: =总资产摘要!$I$12/SUM(总资产摘要!$B$12:$M$12) -> 0.034193439 | P9: =总资产摘要!$I$12/SUM(总资产摘要!$B$12:$M$12) -> 0.034193439 | Q9: =总资产摘要!$I$13/SUM(总资产摘要!$B$13:$M$13) -> 0.088433751 | R9: =总资产摘要!$I$13/SUM(总资产摘要!$B$13:$M$13) -> 0.088433751 | S9: =总资产摘要!#REF!/SUM(总资产摘要!#REF!) -> #REF! | T9: =总资产摘要!#REF!/SUM(总资产摘要!#REF!) -> #REF!
A10: =总资产摘要!$J$5/SUM(总资产摘要!$B$5:$M$5) -> 0.13652339 | B10: =总资产摘要!$J$5/SUM(总资产摘要!$B$5:$M$5) -> 0.13652339 | C10: =总资产摘要!$J$6/SUM(总资产摘要!$B$6:$M$6) -> 0.061696693 | D10: =总资产摘要!$J$6/SUM(总资产摘要!$B$6:$M$6) -> 0.061696693 | E10: =总资产摘要!$J$7/SUM(总资产摘要!$B$7:$M$7) -> 0.007330558 | F10: =总资产摘要!$J$7/SUM(总资产摘要!$B$7:$M$7) -> 0.007330558 | G10: =总资产摘要!$J$8/SUM(总资产摘要!$B$8:$M$8) -> 1.607863e-05 | H10: =总资产摘要!$J$8/SUM(总资产摘要!$B$8:$M$8) -> 1.607863e-05 | I10: =总资产摘要!$J$9/SUM(总资产摘要!$B$9:$M$9) -> 9.1312735e-05 | J10: =总资产摘要!$J$9/SUM(总资产摘要!$B$9:$M$9) -> 9.1312735e-05 | K10: =总资产摘要!$J$10/SUM(总资产摘要!$B$10:$M$10) -> 0.00080642885 | L10: =总资产摘要!$J$10/SUM(总资产摘要!$B$10:$M$10) -> 0.00080642885 | M10: =总资产摘要!$J$11/SUM(总资产摘要!$B$11:$M$11) -> 0.036430654 | N10: =总资产摘要!$J$11/SUM(总资产摘要!$B$11:$M$11) -> 0.036430654 | O10: =总资产摘要!$J$12/SUM(总资产摘要!$B$12:$M$12) -> 0.052210103 | P10: =总资产摘要!$J$12/SUM(总资产摘要!$B$12:$M$12) -> 0.052210103 | Q10: =总资产摘要!$J$13/SUM(总资产摘要!$B$13:$M$13) -> 0.086814946 | R10: =总资产摘要!$J$13/SUM(总资产摘要!$B$13:$M$13) -> 0.086814946 | S10: =总资产摘要!#REF!/SUM(总资产摘要!#REF!) -> #REF! | T10: =总资产摘要!#REF!/SUM(总资产摘要!#REF!) -> #REF!
A11: =总资产摘要!$K$5/SUM(总资产摘要!$B$5:$M$5) -> 0.12994626 | B11: =总资产摘要!$K$5/SUM(总资产摘要!$B$5:$M$5) -> 0.12994626 | C11: =总资产摘要!$K$6/SUM(总资产摘要!$B$6:$M$6) -> 0.060184967 | D11: =总资产摘要!$K$6/SUM(总资产摘要!$B$6:$M$6) -> 0.060184967 | E11: =总资产摘要!$K$7/SUM(总资产摘要!$B$7:$M$7) -> 0.00017072117 | F11: =总资产摘要!$K$7/SUM(总资产摘要!$B$7:$M$7) -> 0.00017072117 | G11: =总资产摘要!$K$8/SUM(总资产摘要!$B$8:$M$8) -> 0 | H11: =总资产摘要!$K$8/SUM(总资产摘要!$B$8:$M$8) -> 0 | I11: =总资产摘要!$K$9/SUM(总资产摘要!$B$9:$M$9) -> 0.00010938505 | J11: =总资产摘要!$K$9/SUM(总资产摘要!$B$9:$M$9) -> 0.00010938505 | K11: =总资产摘要!$K$10/SUM(总资产摘要!$B$10:$M$10) -> 0.064889297 | L11: =总资产摘要!$K$10/SUM(总资产摘要!$B$10:$M$10) -> 0.064889297 | M11: =总资产摘要!$K$11/SUM(总资产摘要!$B$11:$M$11) -> 0.037970669 | N11: =总资产摘要!$K$11/SUM(总资产摘要!$B$11:$M$11) -> 0.037970669 | O11: =总资产摘要!$K$12/SUM(总资产摘要!$B$12:$M$12) -> 0.09909749 | P11: =总资产摘要!$K$12/SUM(总资产摘要!$B$12:$M$12) -> 0.09909749 | Q11: =总资产摘要!$K$13/SUM(总资产摘要!$B$13:$M$13) -> 0.085151396 | R11: =总资产摘要!$K$13/SUM(总资产摘要!$B$13:$M$13) -> 0.085151396 | S11: =总资产摘要!#REF!/SUM(总资产摘要!#REF!) -> #REF! | T11: =总资产摘要!#REF!/SUM(总资产摘要!#REF!) -> #REF!
A12: =总资产摘要!$L$5/SUM(总资产摘要!$B$5:$M$5) -> 0.12256898 | B12: =总资产摘要!$L$5/SUM(总资产摘要!$B$5:$M$5) -> 0.12256898 | C12: =总资产摘要!$L$6/SUM(总资产摘要!$B$6:$M$6) -> 0.062116203 | D12: =总资产摘要!$L$6/SUM(总资产摘要!$B$6:$M$6) -> 0.062116203 | E12: =总资产摘要!$L$7/SUM(总资产摘要!$B$7:$M$7) -> 7.9636697e-06 | F12: =总资产摘要!$L$7/SUM(总资产摘要!$B$7:$M$7) -> 7.9636697e-06 | G12: =总资产摘要!$L$8/SUM(总资产摘要!$B$8:$M$8) -> 1.607863e-06 | H12: =总资产摘要!$L$8/SUM(总资产摘要!$B$8:$M$8) -> 1.607863e-06 | I12: =总资产摘要!$L$9/SUM(总资产摘要!$B$9:$M$9) -> 1.4267615e-05 | J12: =总资产摘要!$L$9/SUM(总资产摘要!$B$9:$M$9) -> 1.4267615e-05 | K12: =总资产摘要!$L$10/SUM(总资产摘要!$B$10:$M$10) -> 0.00036289298 | L12: =总资产摘要!$L$10/SUM(总资产摘要!$B$10:$M$10) -> 0.00036289298 | M12: =总资产摘要!$L$11/SUM(总资产摘要!$B$11:$M$11) -> 0.039189001 | N12: =总资产摘要!$L$11/SUM(总资产摘要!$B$11:$M$11) -> 0.039189001 | O12: =总资产摘要!$L$12/SUM(总资产摘要!$B$12:$M$12) -> 0.10593432 | P12: =总资产摘要!$L$12/SUM(总资产摘要!$B$12:$M$12) -> 0.10593432 | Q12: =总资产摘要!$L$13/SUM(总资产摘要!$B$13:$M$13) -> 0.086789038 | R12: =总资产摘要!$L$13/SUM(总资产摘要!$B$13:$M$13) -> 0.086789038 | S12: =总资产摘要!#REF!/SUM(总资产摘要!#REF!) -> #REF! | T12: =总资产摘要!#REF!/SUM(总资产摘要!#REF!) -> #REF!
A13: =总资产摘要!$M$5/SUM(总资产摘要!$B$5:$M$5) -> 0.099707065 | B13: =总资产摘要!$M$5/SUM(总资产摘要!$B$5:$M$5) -> 0.099707065 | C13: =总资产摘要!$M$6/SUM(总资产摘要!$B$6:$M$6) -> 0.067112015 | D13: =总资产摘要!$M$6/SUM(总资产摘要!$B$6:$M$6) -> 0.067112015 | E13: =总资产摘要!$M$7/SUM(总资产摘要!$B$7:$M$7) -> 0.011651347 | F13: =总资产摘要!$M$7/SUM(总资产摘要!$B$7:$M$7) -> 0.011651347 | G13: =总资产摘要!$M$8/SUM(总资产摘要!$B$8:$M$8) -> 1.607863e-06 | H13: =总资产摘要!$M$8/SUM(总资产摘要!$B$8:$M$8) -> 1.607863e-06 | I13: =总资产摘要!$M$9/SUM(总资产摘要!$B$9:$M$9) -> 0.0060399569 | J13: =总资产摘要!$M$9/SUM(总资产摘要!$B$9:$M$9) -> 0.0060399569 | K13: =总资产摘要!$M$10/SUM(总资产摘要!$B$10:$M$10) -> 0.00042740729 | L13: =总资产摘要!$M$10/SUM(总资产摘要!$B$10:$M$10) -> 0.00042740729 | M13: =总资产摘要!$M$11/SUM(总资产摘要!$B$11:$M$11) -> 0.046043386 | N13: =总资产摘要!$M$11/SUM(总资产摘要!$B$11:$M$11) -> 0.046043386 | O13: =总资产摘要!$M$12/SUM(总资产摘要!$B$12:$M$12) -> 0.10304547 | P13: =总资产摘要!$M$12/SUM(总资产摘要!$B$12:$M$12) -> 0.10304547 | Q13: =总资产摘要!$M$13/SUM(总资产摘要!$B$13:$M$13) -> 0.083729533 | R13: =总资产摘要!$M$13/SUM(总资产摘要!$B$13:$M$13) -> 0.083729533 | S13: =总资产摘要!#REF!/SUM(总资产摘要!#REF!) -> #REF! | T13: =总资产摘要!#REF!/SUM(总资产摘要!#REF!) -> #REF!
A14: =Kutools_Chart!$C$1/2 -> 6.2645002 | B14: =(Kutools_Chart!$D$1-Kutools_Chart!$C$1)/2+Kutools_Chart!$C$1 -> 43.330126 | C14: =(Kutools_Chart!$F$1-Kutools_Chart!$E$1)/2+Kutools_Chart!$E$1 -> 74.574025 | D14: =(Kutools_Chart!$H$1-Kutools_Chart!$G$1)/2+Kutools_Chart!$G$1 -> 75.079621 | E14: =(Kutools_Chart!$J$1-Kutools_Chart!$I$1)/2+Kutools_Chart!$I$1 -> 75.258292 | F14: =(Kutools_Chart!$L$1-Kutools_Chart!$K$1)/2+Kutools_Chart!$K$1 -> 75.401467 | G14: =(Kutools_Chart!$N$1-Kutools_Chart!$M$1)/2+Kutools_Chart!$M$1 -> 81.750808 | H14: =(Kutools_Chart!$P$1-Kutools_Chart!$O$1)/2+Kutools_Chart!$O$1 -> 92.898793 | I14: =(Kutools_Chart!$R$1-Kutools_Chart!$Q$1)/2+Kutools_Chart!$Q$1 -> 98.862382 | J14: =(Kutools_Chart!$T$1-Kutools_Chart!$S$1)/2+Kutools_Chart!$S$1 -> 100
A15: =Kutools_Chart!$C$1/100 -> 0.12529 | B15: =(Kutools_Chart!$D$1-Kutools_Chart!$C$1)/100 -> 0.61602252 | C15: =(Kutools_Chart!$F$1-Kutools_Chart!$E$1)/100 -> 0.0088554546 | D15: =(Kutools_Chart!$H$1-Kutools_Chart!$G$1)/100 -> 0.0012564705 | E15: =(Kutools_Chart!$J$1-Kutools_Chart!$I$1)/100 -> 0.0023169358 | F15: =(Kutools_Chart!$L$1-Kutools_Chart!$K$1)/100 -> 0.00054656028 | G15: =(Kutools_Chart!$N$1-Kutools_Chart!$M$1)/100 -> 0.12644028 | H15: =(Kutools_Chart!$P$1-Kutools_Chart!$O$1)/100 -> 0.096519422 | I15: =(Kutools_Chart!$R$1-Kutools_Chart!$Q$1)/100 -> 0.022752355 | J15: =(Kutools_Chart!$T$1-Kutools_Chart!$S$1)/100 -> 7.1054274e-16
A16: =总资产摘要!$B$5/SUM(总资产摘要!$B$5:$M$5)/2 -> 0.040539793 | B16: =总资产摘要!$C$5/SUM(总资产摘要!$B$5:$M$5)/2+总资产摘要!$B$5/SUM(总资产摘要!$B$5:$M$5) -> 0.081079595 | C16: =总资产摘要!$D$5/SUM(总资产摘要!$B$5:$M$5)/2+SUM(总资产摘要!$B$5:$C$5)/SUM(总资产摘要!$B$5:$M$5) -> 0.081079613 | D16: =总资产摘要!$E$5/SUM(总资产摘要!$B$5:$M$5)/2+SUM(总资产摘要!$B$5:$D$5)/SUM(总资产摘要!$B$5:$M$5) -> 0.081079622 | E16: =总资产摘要!$F$5/SUM(总资产摘要!$B$5:$M$5)/2+SUM(总资产摘要!$B$5:$E$5)/SUM(总资产摘要!$B$5:$M$5) -> 0.081079622 | F16: =总资产摘要!$G$5/SUM(总资产摘要!$B$5:$M$5)/2+SUM(总资产摘要!$B$5:$F$5)/SUM(总资产摘要!$B$5:$M$5) -> 0.15272771 | G16: =总资产摘要!$H$5/SUM(总资产摘要!$B$5:$M$5)/2+SUM(总资产摘要!$B$5:$G$5)/SUM(总资产摘要!$B$5:$M$5) -> 0.29605673 | H16: =总资产摘要!$I$5/SUM(总资产摘要!$B$5:$M$5)/2+SUM(总资产摘要!$B$5:$H$5)/SUM(总资产摘要!$B$5:$M$5) -> 0.43949599 | I16: =总资产摘要!$J$5/SUM(总资产摘要!$B$5:$M$5)/2+SUM(总资产摘要!$B$5:$I$5)/SUM(总资产摘要!$B$5:$M$5) -> 0.57951601 | J16: =总资产摘要!$K$5/SUM(总资产摘要!$B$5:$M$5)/2+SUM(总资产摘要!$B$5:$J$5)/SUM(总资产摘要!$B$5:$M$5) -> 0.71275083 | K16: =总资产摘要!$L$5/SUM(总资产摘要!$B$5:$M$5)/2+SUM(总资产摘要!$B$5:$K$5)/SUM(总资产摘要!$B$5:$M$5) -> 0.83900845 | L16: =总资产摘要!$M$5/SUM(总资产摘要!$B$5:$M$5)/2+SUM(总资产摘要!$B$5:$L$5)/SUM(总资产摘要!$B$5:$M$5) -> 0.95014647
A17: =总资产摘要!$B$6/SUM(总资产摘要!$B$6:$M$6)/2 -> 0.034511217 | B17: =总资产摘要!$C$6/SUM(总资产摘要!$B$6:$M$6)/2+总资产摘要!$B$6/SUM(总资产摘要!$B$6:$M$6) -> 0.11556325 | C17: =总资产摘要!$D$6/SUM(总资产摘要!$B$6:$M$6)/2+SUM(总资产摘要!$B$6:$C$6)/SUM(总资产摘要!$B$6:$M$6) -> 0.23885447 | D17: =总资产摘要!$E$6/SUM(总资产摘要!$B$6:$M$6)/2+SUM(总资产摘要!$B$6:$D$6)/SUM(总资产摘要!$B$6:$M$6) -> 0.37886746 | E17: =总资产摘要!$F$6/SUM(总资产摘要!$B$6:$M$6)/2+SUM(总资产摘要!$B$6:$E$6)/SUM(总资产摘要!$B$6:$M$6) -> 0.50877933 | F17: =总资产摘要!$G$6/SUM(总资产摘要!$B$6:$M$6)/2+SUM(总资产摘要!$B$6:$F$6)/SUM(总资产摘要!$B$6:$M$6) -> 0.60286745 | G17: =总资产摘要!$H$6/SUM(总资产摘要!$B$6:$M$6)/2+SUM(总资产摘要!$B$6:$G$6)/SUM(总资产摘要!$B$6:$M$6) -> 0.6592982 | H17: =总资产摘要!$I$6/SUM(总资产摘要!$B$6:$M$6)/2+SUM(总资产摘要!$B$6:$H$6)/SUM(总资产摘要!$B$6:$M$6) -> 0.71859011 | I17: =总资产摘要!$J$6/SUM(总资产摘要!$B$6:$M$6)/2+SUM(总资产摘要!$B$6:$I$6)/SUM(总资产摘要!$B$6:$M$6) -> 0.77973847 | J17: =总资产摘要!$K$6/SUM(总资产摘要!$B$6:$M$6)/2+SUM(总资产摘要!$B$6:$J$6)/SUM(总资产摘要!$B$6:$M$6) -> 0.8406793 | K17: =总资产摘要!$L$6/SUM(总资产摘要!$B$6:$M$6)/2+SUM(总资产摘要!$B$6:$K$6)/SUM(总资产摘要!$B$6:$M$6) -> 0.90182988 | L17: =总资产摘要!$M$6/SUM(总资产摘要!$B$6:$M$6)/2+SUM(总资产摘要!$B$6:$L$6)/SUM(总资产摘要!$B$6:$M$6) -> 0.96644399
A18: =总资产摘要!$B$7/SUM(总资产摘要!$B$7:$M$7)/2 -> 0.026371817 | B18: =总资产摘要!$C$7/SUM(总资产摘要!$B$7:$M$7)/2+总资产摘要!$B$7/SUM(总资产摘要!$B$7:$M$7) -> 0.078685412 | C18: =总资产摘要!$D$7/SUM(总资产摘要!$B$7:$M$7)/2+SUM(总资产摘要!$B$7:$C$7)/SUM(总资产摘要!$B$7:$M$7) -> 0.12918877 | D18: =总资产摘要!$E$7/SUM(总资产摘要!$B$7:$M$7)/2+SUM(总资产摘要!$B$7:$D$7)/SUM(总资产摘要!$B$7:$M$7) -> 0.15441083 | E18: =总资产摘要!$F$7/SUM(总资产摘要!$B$7:$M$7)/2+SUM(总资产摘要!$B$7:$E$7)/SUM(总资产摘要!$B$7:$M$7) -> 0.15573018 | F18: =总资产摘要!$G$7/SUM(总资产摘要!$B$7:$M$7)/2+SUM(总资产摘要!$B$7:$F$7)/SUM(总资产摘要!$B$7:$M$7) -> 0.28653147 | G18: =总资产摘要!$H$7/SUM(总资产摘要!$B$7:$M$7)/2+SUM(总资产摘要!$B$7:$G$7)/SUM(总资产摘要!$B$7:$M$7) -> 0.57361069 | H18: =总资产摘要!$I$7/SUM(总资产摘要!$B$7:$M$7)/2+SUM(总资产摘要!$B$7:$H$7)/SUM(总资产摘要!$B$7:$M$7) -> 0.85569345 | I18: =总资产摘要!$J$7/SUM(总资产摘要!$B$7:$M$7)/2+SUM(总资产摘要!$B$7:$I$7)/SUM(总资产摘要!$B$7:$M$7) -> 0.98450469 | J18: =总资产摘要!$K$7/SUM(总资产摘要!$B$7:$M$7)/2+SUM(总资产摘要!$B$7:$J$7)/SUM(总资产摘要!$B$7:$M$7) -> 0.98825533 | K18: =总资产摘要!$L$7/SUM(总资产摘要!$B$7:$M$7)/2+SUM(总资产摘要!$B$7:$K$7)/SUM(总资产摘要!$B$7:$M$7) -> 0.98834467 | L18: =总资产摘要!$M$7/SUM(总资产摘要!$B$7:$M$7)/2+SUM(总资产摘要!$B$7:$L$7)/SUM(总资产摘要!$B$7:$M$7) -> 0.99417433
A19: =总资产摘要!$B$8/SUM(总资产摘要!$B$8:$M$8)/2 -> 8.0393152e-07 | B19: =总资产摘要!$C$8/SUM(总资产摘要!$B$8:$M$8)/2+总资产摘要!$B$8/SUM(总资产摘要!$B$8:$M$8) -> 2.4117946e-06 | C19: =总资产摘要!$D$8/SUM(总资产摘要!$B$8:$M$8)/2+SUM(总资产摘要!$B$8:$C$8)/SUM(总资产摘要!$B$8:$M$8) -> 4.0196576e-06 | D19: =总资产摘要!$E$8/SUM(总资产摘要!$B$8:$M$8)/2+SUM(总资产摘要!$B$8:$D$8)/SUM(总资产摘要!$B$8:$M$8) -> 5.6275206e-06 | E19: =总资产摘要!$F$8/SUM(总资产摘要!$B$8:$M$8)/2+SUM(总资产摘要!$B$8:$E$8)/SUM(总资产摘要!$B$8:$M$8) -> 7.2353837e-06 | F19: =总资产摘要!$G$8/SUM(总资产摘要!$B$8:$M$8)/2+SUM(总资产摘要!$B$8:$F$8)/SUM(总资产摘要!$B$8:$M$8) -> 0.49998732 | G19: =总资产摘要!$H$8/SUM(总资产摘要!$B$8:$M$8)/2+SUM(总资产摘要!$B$8:$G$8)/SUM(总资产摘要!$B$8:$M$8) -> 0.99997285 | H19: =总资产摘要!$I$8/SUM(总资产摘要!$B$8:$M$8)/2+SUM(总资产摘要!$B$8:$H$8)/SUM(总资产摘要!$B$8:$M$8) -> 0.9999799 | I19: =总资产摘要!$J$8/SUM(总资产摘要!$B$8:$M$8)/2+SUM(总资产摘要!$B$8:$I$8)/SUM(总资产摘要!$B$8:$M$8) -> 0.99998874 | J19: =总资产摘要!$K$8/SUM(总资产摘要!$B$8:$M$8)/2+SUM(总资产摘要!$B$8:$J$8)/SUM(总资产摘要!$B$8:$M$8) -> 0.99999678 | K19: =总资产摘要!$L$8/SUM(总资产摘要!$B$8:$M$8)/2+SUM(总资产摘要!$B$8:$K$8)/SUM(总资产摘要!$B$8:$M$8) -> 0.99999759 | L19: =总资产摘要!$M$8/SUM(总资产摘要!$B$8:$M$8)/2+SUM(总资产摘要!$B$8:$L$8)/SUM(总资产摘要!$B$8:$M$8) -> 0.9999992
A20: =总资产摘要!$B$9/SUM(总资产摘要!$B$9:$M$9)/2 -> 9.5117432e-06 | B20: =总资产摘要!$C$9/SUM(总资产摘要!$B$9:$M$9)/2+总资产摘要!$B$9/SUM(总资产摘要!$B$9:$M$9) -> 0.47973333 | C20: =总资产摘要!$D$9/SUM(总资产摘要!$B$9:$M$9)/2+SUM(总资产摘要!$B$9:$C$9)/SUM(总资产摘要!$B$9:$M$9) -> 0.95944859 | D20: =总资产摘要!$E$9/SUM(总资产摘要!$B$9:$M$9)/2+SUM(总资产摘要!$B$9:$D$9)/SUM(总资产摘要!$B$9:$M$9) -> 0.95945144 | E20: =总资产摘要!$F$9/SUM(总资产摘要!$B$9:$M$9)/2+SUM(总资产摘要!$B$9:$E$9)/SUM(总资产摘要!$B$9:$M$9) -> 0.9595028 | F20: =总资产摘要!$G$9/SUM(总资产摘要!$B$9:$M$9)/2+SUM(总资产摘要!$B$9:$F$9)/SUM(总资产摘要!$B$9:$M$9) -> 0.97434207 | G20: =总资产摘要!$H$9/SUM(总资产摘要!$B$9:$M$9)/2+SUM(总资产摘要!$B$9:$G$9)/SUM(总资产摘要!$B$9:$M$9) -> 0.99134526 | H20: =总资产摘要!$I$9/SUM(总资产摘要!$B$9:$M$9)/2+SUM(总资产摘要!$B$9:$H$9)/SUM(总资产摘要!$B$9:$M$9) -> 0.99365186 | I20: =总资产摘要!$J$9/SUM(总资产摘要!$B$9:$M$9)/2+SUM(总资产摘要!$B$9:$I$9)/SUM(总资产摘要!$B$9:$M$9) -> 0.99379073 | J20: =总资产摘要!$K$9/SUM(总资产摘要!$B$9:$M$9)/2+SUM(总资产摘要!$B$9:$J$9)/SUM(总资产摘要!$B$9:$M$9) -> 0.99389108 | K20: =总资产摘要!$L$9/SUM(总资产摘要!$B$9:$M$9)/2+SUM(总资产摘要!$B$9:$K$9)/SUM(总资产摘要!$B$9:$M$9) -> 0.99395291 | L20: =总资产摘要!$M$9/SUM(总资产摘要!$B$9:$M$9)/2+SUM(总资产摘要!$B$9:$L$9)/SUM(总资产摘要!$B$9:$M$9) -> 0.99698002
A21: =总资产摘要!$B$10/SUM(总资产摘要!$B$10:$M$10)/2 -> 0.027188749 | B21: =总资产摘要!$C$10/SUM(总资产摘要!$B$10:$M$10)/2+总资产摘要!$B$10/SUM(总资产摘要!$B$10:$M$10) -> 0.22901168 | C21: =总资产摘要!$D$10/SUM(总资产摘要!$B$10:$M$10)/2+SUM(总资产摘要!$B$10:$C$10)/SUM(总资产摘要!$B$10:$M$10) -> 0.40512566 | D21: =总资产摘要!$E$10/SUM(总资产摘要!$B$10:$M$10)/2+SUM(总资产摘要!$B$10:$D$10)/SUM(总资产摘要!$B$10:$M$10) -> 0.40698851 | E21: =总资产摘要!$F$10/SUM(总资产摘要!$B$10:$M$10)/2+SUM(总资产摘要!$B$10:$E$10)/SUM(总资产摘要!$B$10:$M$10) -> 0.40936748 | F21: =总资产摘要!$G$10/SUM(总资产摘要!$B$10:$M$10)/2+SUM(总资产摘要!$B$10:$F$10)/SUM(总资产摘要!$B$10:$M$10) -> 0.67064841 | G21: =总资产摘要!$H$10/SUM(总资产摘要!$B$10:$M$10)/2+SUM(总资产摘要!$B$10:$G$10)/SUM(总资产摘要!$B$10:$M$10) -> 0.93052414 | H21: =总资产摘要!$I$10/SUM(总资产摘要!$B$10:$M$10)/2+SUM(总资产摘要!$B$10:$H$10)/SUM(总资产摘要!$B$10:$M$10) -> 0.93231441 | I21: =总资产摘要!$J$10/SUM(总资产摘要!$B$10:$M$10)/2+SUM(总资产摘要!$B$10:$I$10)/SUM(总资产摘要!$B$10:$M$10) -> 0.93391719 | J21: =总资产摘要!$K$10/SUM(总资产摘要!$B$10:$M$10)/2+SUM(总资产摘要!$B$10:$J$10)/SUM(总资产摘要!$B$10:$M$10) -> 0.96676505 | K21: =总资产摘要!$L$10/SUM(总资产摘要!$B$10:$M$10)/2+SUM(总资产摘要!$B$10:$K$10)/SUM(总资产摘要!$B$10:$M$10) -> 0.99939115 | L21: =总资产摘要!$M$10/SUM(总资产摘要!$B$10:$M$10)/2+SUM(总资产摘要!$B$10:$L$10)/SUM(总资产摘要!$B$10:$M$10) -> 0.9997863
A22: =总资产摘要!$B$11/SUM(总资产摘要!$B$11:$M$11)/2 -> 0.03599154 | B22: =总资产摘要!$C$11/SUM(总资产摘要!$B$11:$M$11)/2+总资产摘要!$B$11/SUM(总资产摘要!$B$11:$M$11) -> 0.1091284 | C22: =总资产摘要!$D$11/SUM(总资产摘要!$B$11:$M$11)/2+SUM(总资产摘要!$B$11:$C$11)/SUM(总资产摘要!$B$11:$M$11) -> 0.19410873 | D22: =总资产摘要!$E$11/SUM(总资产摘要!$B$11:$M$11)/2+SUM(总资产摘要!$B$11:$D$11)/SUM(总资产摘要!$B$11:$M$11) -> 0.36397263 | E22: =总资产摘要!$F$11/SUM(总资产摘要!$B$11:$M$11)/2+SUM(总资产摘要!$B$11:$E$11)/SUM(总资产摘要!$B$11:$M$11) -> 0.6082676 | F22: =总资产摘要!$G$11/SUM(总资产摘要!$B$11:$M$11)/2+SUM(总资产摘要!$B$11:$F$11)/SUM(总资产摘要!$B$11:$M$11) -> 0.74884285 | G22: =总资产摘要!$H$11/SUM(总资产摘要!$B$11:$M$11)/2+SUM(总资产摘要!$B$11:$G$11)/SUM(总资产摘要!$B$11:$M$11) -> 0.78539457 | H22: =总资产摘要!$I$11/SUM(总资产摘要!$B$11:$M$11)/2+SUM(总资产摘要!$B$11:$H$11)/SUM(总资产摘要!$B$11:$M$11) -> 0.8220017 | I22: =总资产摘要!$J$11/SUM(总资产摘要!$B$11:$M$11)/2+SUM(总资产摘要!$B$11:$I$11)/SUM(总资产摘要!$B$11:$M$11) -> 0.85858162 | J22: =总资产摘要!$K$11/SUM(总资产摘要!$B$11:$M$11)/2+SUM(总资产摘要!$B$11:$J$11)/SUM(总资产摘要!$B$11:$M$11) -> 0.89578228 | K22: =总资产摘要!$L$11/SUM(总资产摘要!$B$11:$M$11)/2+SUM(总资产摘要!$B$11:$K$11)/SUM(总资产摘要!$B$11:$M$11) -> 0.93436211 | L22: =总资产摘要!$M$11/SUM(总资产摘要!$B$11:$M$11)/2+SUM(总资产摘要!$B$11:$L$11)/SUM(总资产摘要!$B$11:$M$11) -> 0.97697831
A23: =总资产摘要!$B$12/SUM(总资产摘要!$B$12:$M$12)/2 -> 0.053187507 | B23: =总资产摘要!$C$12/SUM(总资产摘要!$B$12:$M$12)/2+总资产摘要!$B$12/SUM(总资产摘要!$B$12:$M$12) -> 0.16207215 | C23: =总资产摘要!$D$12/SUM(总资产摘要!$B$12:$M$12)/2+SUM(总资产摘要!$B$12:$C$12)/SUM(总资产摘要!$B$12:$M$12) -> 0.27287181 | D23: =总资产摘要!$E$12/SUM(总资产摘要!$B$12:$M$12)/2+SUM(总资产摘要!$B$12:$D$12)/SUM(总资产摘要!$B$12:$M$12) -> 0.38351706 | E23: =总资产摘要!$F$12/SUM(总资产摘要!$B$12:$M$12)/2+SUM(总资产摘要!$B$12:$E$12)/SUM(总资产摘要!$B$12:$M$12) -> 0.4959527 | F23: =总资产摘要!$G$12/SUM(总资产摘要!$B$12:$M$12)/2+SUM(总资产摘要!$B$12:$F$12)/SUM(总资产摘要!$B$12:$M$12) -> 0.56253235 | G23: =总资产摘要!$H$12/SUM(总资产摘要!$B$12:$M$12)/2+SUM(总资产摘要!$B$12:$G$12)/SUM(总资产摘要!$B$12:$M$12) -> 0.58886913 | H23: =总资产摘要!$I$12/SUM(总资产摘要!$B$12:$M$12)/2+SUM(总资产摘要!$B$12:$H$12)/SUM(总资产摘要!$B$12:$M$12) -> 0.6226159 | I23: =总资产摘要!$J$12/SUM(总资产摘要!$B$12:$M$12)/2+SUM(总资产摘要!$B$12:$I$12)/SUM(总资产摘要!$B$12:$M$12) -> 0.66581767 | J23: =总资产摘要!$K$12/SUM(总资产摘要!$B$12:$M$12)/2+SUM(总资产摘要!$B$12:$J$12)/SUM(总资产摘要!$B$12:$M$12) -> 0.74147147 | K23: =总资产摘要!$L$12/SUM(总资产摘要!$B$12:$M$12)/2+SUM(总资产摘要!$B$12:$K$12)/SUM(总资产摘要!$B$12:$M$12) -> 0.84398737 | L23: =总资产摘要!$M$12/SUM(总资产摘要!$B$12:$M$12)/2+SUM(总资产摘要!$B$12:$L$12)/SUM(总资产摘要!$B$12:$M$12) -> 0.94847727
A24: =总资产摘要!$B$13/SUM(总资产摘要!$B$13:$M$13)/2 -> 0.042841889 | B24: =总资产摘要!$C$13/SUM(总资产摘要!$B$13:$M$13)/2+总资产摘要!$B$13/SUM(总资产摘要!$B$13:$M$13) -> 0.12215393 | C24: =总资产摘要!$D$13/SUM(总资产摘要!$B$13:$M$13)/2+SUM(总资产摘要!$B$13:$C$13)/SUM(总资产摘要!$B$13:$M$13) -> 0.19661978 | D24: =总资产摘要!$E$13/SUM(总资产摘要!$B$13:$M$13)/2+SUM(总资产摘要!$B$13:$D$13)/SUM(总资产摘要!$B$13:$M$13) -> 0.27330239 | E24: =总资产摘要!$F$13/SUM(总资产摘要!$B$13:$M$13)/2+SUM(总资产摘要!$B$13:$E$13)/SUM(总资产摘要!$B$13:$M$13) -> 0.35228908 | F24: =总资产摘要!$G$13/SUM(总资产摘要!$B$13:$M$13)/2+SUM(总资产摘要!$B$13:$F$13)/SUM(总资产摘要!$B$13:$M$13) -> 0.43674536 | G24: =总资产摘要!$H$13/SUM(总资产摘要!$B$13:$M$13)/2+SUM(总资产摘要!$B$13:$G$13)/SUM(总资产摘要!$B$13:$M$13) -> 0.5249916 | H24: =总资产摘要!$I$13/SUM(总资产摘要!$B$13:$M$13)/2+SUM(总资产摘要!$B$13:$H$13)/SUM(总资产摘要!$B$13:$M$13) -> 0.61329821 | I24: =总资产摘要!$J$13/SUM(总资产摘要!$B$13:$M$13)/2+SUM(总资产摘要!$B$13:$I$13)/SUM(总资产摘要!$B$13:$M$13) -> 0.70092256 | J24: =总资产摘要!$K$13/SUM(总资产摘要!$B$13:$M$13)/2+SUM(总资产摘要!$B$13:$J$13)/SUM(总资产摘要!$B$13:$M$13) -> 0.78690573 | K24: =总资产摘要!$L$13/SUM(总资产摘要!$B$13:$M$13)/2+SUM(总资产摘要!$B$13:$K$13)/SUM(总资产摘要!$B$13:$M$13) -> 0.87287595 | L24: =总资产摘要!$M$13/SUM(总资产摘要!$B$13:$M$13)/2+SUM(总资产摘要!$B$13:$L$13)/SUM(总资产摘要!$B$13:$M$13) -> 0.95813523
A25: =总资产摘要!#REF!/SUM(总资产摘要!#REF!)/2 -> #REF! | B25: =总资产摘要!#REF!/SUM(总资产摘要!#REF!)/2+总资产摘要!#REF!/SUM(总资产摘要!#REF!) -> #REF! | C25: =总资产摘要!#REF!/SUM(总资产摘要!#REF!)/2+SUM(总资产摘要!#REF!)/SUM(总资产摘要!#REF!) -> #REF! | D25: =总资产摘要!#REF!/SUM(总资产摘要!#REF!)/2+SUM(总资产摘要!#REF!)/SUM(总资产摘要!#REF!) -> #REF! | E25: =总资产摘要!#REF!/SUM(总资产摘要!#REF!)/2+SUM(总资产摘要!#REF!)/SUM(总资产摘要!#REF!) -> #REF! | F25: =总资产摘要!#REF!/SUM(总资产摘要!#REF!)/2+SUM(总资产摘要!#REF!)/SUM(总资产摘要!#REF!) -> #REF! | G25: =总资产摘要!#REF!/SUM(总资产摘要!#REF!)/2+SUM(总资产摘要!#REF!)/SUM(总资产摘要!#REF!) -> #REF! | H25: =总资产摘要!#REF!/SUM(总资产摘要!#REF!)/2+SUM(总资产摘要!#REF!)/SUM(总资产摘要!#REF!) -> #REF! | I25: =总资产摘要!#REF!/SUM(总资产摘要!#REF!)/2+SUM(总资产摘要!#REF!)/SUM(总资产摘要!#REF!) -> #REF! | J25: =总资产摘要!#REF!/SUM(总资产摘要!#REF!)/2+SUM(总资产摘要!#REF!)/SUM(总资产摘要!#REF!) -> #REF! | ... L25: =总资产摘要!#REF!/SUM(总资产摘要!#REF!)/2+SUM(总资产摘要!#REF!)/SUM(总资产摘要!#REF!) -> #REF!
A26: Kutools: Intermediate data of the marimekko chart
A28: =IFERROR(MAX(总资产摘要!$B$5:$B$13)*1.1-总资产摘要!$B5,0) -> 166134.34 | B28: =IFERROR(MAX(总资产摘要!$C$5:$C$13)*1.1-总资产摘要!$C5,0) -> 286206.27 | C28: =IFERROR(MAX(总资产摘要!$D$5:$D$13)*1.1-总资产摘要!$D5,0) -> 471982.35 | D28: =IFERROR(MAX(总资产摘要!$E$5:$E$13)*1.1-总资产摘要!$E5,0) -> 389038.11 | E28: =IFERROR(MAX(总资产摘要!$F$5:$F$13)*1.1-总资产摘要!$F5,0) -> 409864.81 | F28: =IFERROR(MAX(总资产摘要!$G$5:$G$13)*1.1-总资产摘要!$G5,0) -> 87271.105 | G28: =IFERROR(MAX(总资产摘要!$H$5:$H$13)*1.1-总资产摘要!$H5,0) -> 96784.484 | H28: =IFERROR(MAX(总资产摘要!$I$5:$I$13)*1.1-总资产摘要!$I5,0) -> 104740.76 | I28: =IFERROR(MAX(总资产摘要!$J$5:$J$13)*1.1-总资产摘要!$J5,0) -> 112088.58 | J28: =IFERROR(MAX(总资产摘要!$K$5:$K$13)*1.1-总资产摘要!$K5,0) -> 111179.54 | K28: =IFERROR(MAX(总资产摘要!$L$5:$L$13)*1.1-总资产摘要!$L5,0) -> 121311.78 | L28: =IFERROR(MAX(总资产摘要!$M$5:$M$13)*1.1-总资产摘要!$M5,0) -> 149670.19
A29: =IFERROR(MAX(总资产摘要!$B$5:$B$13)*1.1-总资产摘要!$B6,0) -> 19293.576 | B29: =IFERROR(MAX(总资产摘要!$C$5:$C$13)*1.1-总资产摘要!$C6,0) -> 26018.753 | C29: =IFERROR(MAX(总资产摘要!$D$5:$D$13)*1.1-总资产摘要!$D6,0) -> 42907.487 | D29: =IFERROR(MAX(总资产摘要!$E$5:$E$13)*1.1-总资产摘要!$E6,0) -> 35367.101 | E29: =IFERROR(MAX(总资产摘要!$F$5:$F$13)*1.1-总资产摘要!$F6,0) -> 37260.437 | F29: =IFERROR(MAX(总资产摘要!$G$5:$G$13)*1.1-总资产摘要!$G6,0) -> 15339.745 | G29: =IFERROR(MAX(总资产摘要!$H$5:$H$13)*1.1-总资产摘要!$H6,0) -> 16207.994 | H29: =IFERROR(MAX(总资产摘要!$I$5:$I$13)*1.1-总资产摘要!$I6,0) -> 16939.29 | I29: =IFERROR(MAX(总资产摘要!$J$5:$J$13)*1.1-总资产摘要!$J6,0) -> 17245.84 | J29: =IFERROR(MAX(总资产摘要!$K$5:$K$13)*1.1-总资产摘要!$K6,0) -> 16823.273 | K29: =IFERROR(MAX(总资产摘要!$L$5:$L$13)*1.1-总资产摘要!$L6,0) -> 17363.104 | L29: =IFERROR(MAX(总资产摘要!$M$5:$M$13)*1.1-总资产摘要!$M6,0) -> 18759.564
A30: =IFERROR(MAX(总资产摘要!$B$5:$B$13)*1.1-总资产摘要!$B7,0) -> 210109.97 | B30: =IFERROR(MAX(总资产摘要!$C$5:$C$13)*1.1-总资产摘要!$C7,0) -> 284121.47 | C30: =IFERROR(MAX(总资产摘要!$D$5:$D$13)*1.1-总资产摘要!$D7,0) -> 470008.47 | D30: =IFERROR(MAX(总资产摘要!$E$5:$E$13)*1.1-总资产摘要!$E7,0) -> 388985.03 | E30: =IFERROR(MAX(总资产摘要!$F$5:$F$13)*1.1-总资产摘要!$F7,0) -> 409811.86 | F30: =IFERROR(MAX(总资产摘要!$G$5:$G$13)*1.1-总资产摘要!$G7,0) -> 158278.31 | G30: =IFERROR(MAX(总资产摘要!$H$5:$H$13)*1.1-总资产摘要!$H7,0) -> 165675.71 | H30: =IFERROR(MAX(总资产摘要!$I$5:$I$13)*1.1-总资产摘要!$I7,0) -> 176274.84 | I30: =IFERROR(MAX(总资产摘要!$J$5:$J$13)*1.1-总资产摘要!$J7,0) -> 189409.68 | J30: =IFERROR(MAX(总资产摘要!$K$5:$K$13)*1.1-总资产摘要!$K7,0) -> 185049.14 | K30: =IFERROR(MAX(总资产摘要!$L$5:$L$13)*1.1-总资产摘要!$L7,0) -> 190993.82 | L30: =IFERROR(MAX(总资产摘要!$M$5:$M$13)*1.1-总资产摘要!$M7,0) -> 205887.02
A31: =IFERROR(MAX(总资产摘要!$B$5:$B$13)*1.1-总资产摘要!$B8,0) -> 212229.33 | B31: =IFERROR(MAX(总资产摘要!$C$5:$C$13)*1.1-总资产摘要!$C8,0) -> 286206.27 | C31: =IFERROR(MAX(总资产摘要!$D$5:$D$13)*1.1-总资产摘要!$D8,0) -> 471982.35 | D31: =IFERROR(MAX(总资产摘要!$E$5:$E$13)*1.1-总资产摘要!$E8,0) -> 389038.1 | E31: =IFERROR(MAX(总资产摘要!$F$5:$F$13)*1.1-总资产摘要!$F8,0) -> 409864.8 | F31: =IFERROR(MAX(总资产摘要!$G$5:$G$13)*1.1-总资产摘要!$G8,0) -> 163036.08 | G31: =IFERROR(MAX(总资产摘要!$H$5:$H$13)*1.1-总资产摘要!$H8,0) -> 178287.86 | H31: =IFERROR(MAX(总资产摘要!$I$5:$I$13)*1.1-总资产摘要!$I8,0) -> 186332.18 | I31: =IFERROR(MAX(总资产摘要!$J$5:$J$13)*1.1-总资产摘要!$J8,0) -> 189704.15 | J31: =IFERROR(MAX(总资产摘要!$K$5:$K$13)*1.1-总资产摘要!$K8,0) -> 185056 | K31: =IFERROR(MAX(总资产摘要!$L$5:$L$13)*1.1-总资产摘要!$L8,0) -> 190994.13 | L31: =IFERROR(MAX(总资产摘要!$M$5:$M$13)*1.1-总资产摘要!$M8,0) -> 206355.19
A32: =IFERROR(MAX(总资产摘要!$B$5:$B$13)*1.1-总资产摘要!$B9,0) -> 212229.14 | B32: =IFERROR(MAX(总资产摘要!$C$5:$C$13)*1.1-总资产摘要!$C9,0) -> 276119.5 | C32: =IFERROR(MAX(总资产摘要!$D$5:$D$13)*1.1-总资产摘要!$D9,0) -> 471982.34 | D32: =IFERROR(MAX(总资产摘要!$E$5:$E$13)*1.1-总资产摘要!$E9,0) -> 389038.07 | E32: =IFERROR(MAX(总资产摘要!$F$5:$F$13)*1.1-总资产摘要!$F9,0) -> 409863.77 | F32: =IFERROR(MAX(总资产摘要!$G$5:$G$13)*1.1-总资产摘要!$G9,0) -> 168426.22 | G32: =IFERROR(MAX(总资产摘要!$H$5:$H$13)*1.1-总资产摘要!$H9,0) -> 178241.39 | H32: =IFERROR(MAX(总资产摘要!$I$5:$I$13)*1.1-总资产摘要!$I9,0) -> 186330.23 | I32: =IFERROR(MAX(总资产摘要!$J$5:$J$13)*1.1-总资产摘要!$J9,0) -> 189703.28 | J32: =IFERROR(MAX(总资产摘要!$K$5:$K$13)*1.1-总资产摘要!$K9,0) -> 185054.85 | K32: =IFERROR(MAX(总资产摘要!$L$5:$L$13)*1.1-总资产摘要!$L9,0) -> 190993.99 | L32: =IFERROR(MAX(总资产摘要!$M$5:$M$13)*1.1-总资产摘要!$M9,0) -> 206291.7
A33: =IFERROR(MAX(总资产摘要!$B$5:$B$13)*1.1-总资产摘要!$B10,0) -> 212094.48 | B33: =IFERROR(MAX(总资产摘要!$C$5:$C$13)*1.1-总资产摘要!$C10,0) -> 285340.07 | C33: =IFERROR(MAX(总资产摘要!$D$5:$D$13)*1.1-总资产摘要!$D10,0) -> 471975.02 | D33: =IFERROR(MAX(总资产摘要!$E$5:$E$13)*1.1-总资产摘要!$E10,0) -> 389036.21 | E33: =IFERROR(MAX(总资产摘要!$F$5:$F$13)*1.1-总资产摘要!$F10,0) -> 409854.91 | F33: =IFERROR(MAX(总资产摘要!$G$5:$G$13)*1.1-总资产摘要!$G10,0) -> 167451.11 | G33: =IFERROR(MAX(总资产摘要!$H$5:$H$13)*1.1-总资产摘要!$H10,0) -> 178285 | H33: =IFERROR(MAX(总资产摘要!$I$5:$I$13)*1.1-总资产摘要!$I10,0) -> 186326.24 | I33: =IFERROR(MAX(总资产摘要!$J$5:$J$13)*1.1-总资产摘要!$J10,0) -> 189702.24 | J33: =IFERROR(MAX(总资产摘要!$K$5:$K$13)*1.1-总资产摘要!$K10,0) -> 184895.07 | K33: =IFERROR(MAX(总资产摘要!$L$5:$L$13)*1.1-总资产摘要!$L10,0) -> 190993.24 | L33: =IFERROR(MAX(总资产摘要!$M$5:$M$13)*1.1-总资产摘要!$M10,0) -> 206354.14
A34: =IFERROR(MAX(总资产摘要!$B$5:$B$13)*1.1-总资产摘要!$B11,0) -> 170930.13 | B34: =IFERROR(MAX(总资产摘要!$C$5:$C$13)*1.1-总资产摘要!$C11,0) -> 243583.14 | C34: =IFERROR(MAX(总资产摘要!$D$5:$D$13)*1.1-总资产摘要!$D11,0) -> 417093.13 | D34: =IFERROR(MAX(总资产摘要!$E$5:$E$13)*1.1-总资产摘要!$E11,0) -> 249013.62 | E34: =IFERROR(MAX(总资产摘要!$F$5:$F$13)*1.1-总资产摘要!$F11,0) -> 269568.17 | F34: =IFERROR(MAX(总资产摘要!$G$5:$G$13)*1.1-总资产摘要!$G11,0) -> 147727.97 | G34: =IFERROR(MAX(总资产摘要!$H$5:$H$13)*1.1-总资产摘要!$H11,0) -> 157355.16 | H34: =IFERROR(MAX(总资产摘要!$I$5:$I$13)*1.1-总资产摘要!$I11,0) -> 165259.38 | I34: =IFERROR(MAX(总资产摘要!$J$5:$J$13)*1.1-总资产摘要!$J11,0) -> 168802.7 | J34: =IFERROR(MAX(总资产摘要!$K$5:$K$13)*1.1-总资产摘要!$K11,0) -> 163270.9 | K34: =IFERROR(MAX(总资产摘要!$L$5:$L$13)*1.1-总资产摘要!$L11,0) -> 168510.04 | L34: =IFERROR(MAX(总资产摘要!$M$5:$M$13)*1.1-总资产摘要!$M11,0) -> 179938.5
A35: =IFERROR(MAX(总资产摘要!$B$5:$B$13)*1.1-总资产摘要!$B12,0) -> 165640.68 | B35: =IFERROR(MAX(总资产摘要!$C$5:$C$13)*1.1-总资产摘要!$C12,0) -> 237419.36 | C35: =IFERROR(MAX(总资产摘要!$D$5:$D$13)*1.1-总资产摘要!$D12,0) -> 423716.27 | D35: =IFERROR(MAX(总资产摘要!$E$5:$E$13)*1.1-总资产摘要!$E12,0) -> 340386.44 | E35: =IFERROR(MAX(总资产摘要!$F$5:$F$13)*1.1-总资产摘要!$F12,0) -> 360030.46 | F35: =IFERROR(MAX(总资产摘要!$G$5:$G$13)*1.1-总资产摘要!$G12,0) -> 160252.28 | G35: =IFERROR(MAX(总资产摘要!$H$5:$H$13)*1.1-总资产摘要!$H12,0) -> 163703.61 | H35: =IFERROR(MAX(总资产摘要!$I$5:$I$13)*1.1-总资产摘要!$I12,0) -> 171356.62 | I35: =IFERROR(MAX(总资产摘要!$J$5:$J$13)*1.1-总资产摘要!$J12,0) -> 166837.98 | J35: =IFERROR(MAX(总资产摘要!$K$5:$K$13)*1.1-总资产摘要!$K12,0) -> 141654.65 | K35: =IFERROR(MAX(总资产摘要!$L$5:$L$13)*1.1-总资产摘要!$L12,0) -> 144598.49 | L35: =IFERROR(MAX(总资产摘要!$M$5:$M$13)*1.1-总资产摘要!$M12,0) -> 161224.77
A36: =IFERROR(MAX(总资产摘要!$B$5:$B$13)*1.1-总资产摘要!$B13,0) -> 203383.26 | B36: =IFERROR(MAX(总资产摘要!$C$5:$C$13)*1.1-总资产摘要!$C13,0) -> 278675.85 | C36: =IFERROR(MAX(总资产摘要!$D$5:$D$13)*1.1-总资产摘要!$D13,0) -> 464136.93 | D36: =IFERROR(MAX(总资产摘要!$E$5:$E$13)*1.1-总资产摘要!$E13,0) -> 381049.96 | E36: =IFERROR(MAX(总资产摘要!$F$5:$F$13)*1.1-总资产摘要!$F13,0) -> 401543.63 | F36: =IFERROR(MAX(总资产摘要!$G$5:$G$13)*1.1-总资产摘要!$G13,0) -> 159619.67 | G36: =IFERROR(MAX(总资产摘要!$H$5:$H$13)*1.1-总资产摘要!$H13,0) -> 169184.2 | H36: =IFERROR(MAX(总资产摘要!$I$5:$I$13)*1.1-总资产摘要!$I13,0) -> 177202.2 | I36: =IFERROR(MAX(总资产摘要!$J$5:$J$13)*1.1-总资产摘要!$J13,0) -> 180741.38 | J36: =IFERROR(MAX(总资产摘要!$K$5:$K$13)*1.1-总资产摘要!$K13,0) -> 176264.89 | K36: =IFERROR(MAX(总资产摘要!$L$5:$L$13)*1.1-总资产摘要!$L13,0) -> 182033.96 | L36: =IFERROR(MAX(总资产摘要!$M$5:$M$13)*1.1-总资产摘要!$M13,0) -> 197710.88
A37: =IFERROR(MAX(总资产摘要!$B$5:$B$13)*1.1-总资产摘要!#REF!,0) -> 0 | B37: =IFERROR(MAX(总资产摘要!$C$5:$C$13)*1.1-总资产摘要!#REF!,0) -> 0 | C37: =IFERROR(MAX(总资产摘要!$D$5:$D$13)*1.1-总资产摘要!#REF!,0) -> 0 | D37: =IFERROR(MAX(总资产摘要!$E$5:$E$13)*1.1-总资产摘要!#REF!,0) -> 0 | E37: =IFERROR(MAX(总资产摘要!$F$5:$F$13)*1.1-总资产摘要!#REF!,0) -> 0 | F37: =IFERROR(MAX(总资产摘要!$G$5:$G$13)*1.1-总资产摘要!#REF!,0) -> 0 | G37: =IFERROR(MAX(总资产摘要!$H$5:$H$13)*1.1-总资产摘要!#REF!,0) -> 0 | H37: =IFERROR(MAX(总资产摘要!$I$5:$I$13)*1.1-总资产摘要!#REF!,0) -> 0 | I37: =IFERROR(MAX(总资产摘要!$J$5:$J$13)*1.1-总资产摘要!#REF!,0) -> 0 | J37: =IFERROR(MAX(总资产摘要!$K$5:$K$13)*1.1-总资产摘要!#REF!,0) -> 0 | K37: =IFERROR(MAX(总资产摘要!$L$5:$L$13)*1.1-总资产摘要!#REF!,0) -> 0 | L37: =IFERROR(MAX(总资产摘要!$M$5:$M$13)*1.1-总资产摘要!#REF!,0) -> 0
A38: 0 | B38: =IFERROR(MAX(总资产摘要!$B$5:$B$13)*1.1+Kutools_Chart!$A$38,0) -> 212229.34 | C38: =IFERROR(MAX(总资产摘要!$C$5:$C$13)*1.1+Kutools_Chart!$B$38,0) -> 498435.62 | D38: =IFERROR(MAX(总资产摘要!$D$5:$D$13)*1.1+Kutools_Chart!$C$38,0) -> 970417.98 | E38: =IFERROR(MAX(总资产摘要!$E$5:$E$13)*1.1+Kutools_Chart!$D$38,0) -> 1359456.1 | F38: =IFERROR(MAX(总资产摘要!$F$5:$F$13)*1.1+Kutools_Chart!$E$38,0) -> 1769320.9 | G38: =IFERROR(MAX(总资产摘要!$G$5:$G$13)*1.1+Kutools_Chart!$F$38,0) -> 1938058.1 | H38: =IFERROR(MAX(总资产摘要!$H$5:$H$13)*1.1+Kutools_Chart!$G$38,0) -> 2116346 | I38: =IFERROR(MAX(总资产摘要!$I$5:$I$13)*1.1+Kutools_Chart!$H$38,0) -> 2302678.2 | J38: =IFERROR(MAX(总资产摘要!$J$5:$J$13)*1.1+Kutools_Chart!$I$38,0) -> 2492382.5 | K38: =IFERROR(MAX(总资产摘要!$K$5:$K$13)*1.1+Kutools_Chart!$J$38,0) -> 2677438.5 | L38: =IFERROR(MAX(总资产摘要!$L$5:$L$13)*1.1+Kutools_Chart!$K$38,0) -> 2868432.6
A39: 0 | B39: =MAX(总资产摘要!$B$5:$B$13) -> 192935.76 | C39: =Kutools_Chart!$B$39+MAX(总资产摘要!$B$5:$B$13)*0.1 -> 212229.34 | D39: =Kutools_Chart!$C$39+MAX(总资产摘要!$C$5:$C$13) -> 472416.87 | E39: =Kutools_Chart!$D$39+MAX(总资产摘要!$C$5:$C$13)*0.1 -> 498435.62 | F39: =Kutools_Chart!$E$39+MAX(总资产摘要!$D$5:$D$13) -> 927510.49 | G39: =Kutools_Chart!$F$39+MAX(总资产摘要!$D$5:$D$13)*0.1 -> 970417.98 | H39: =Kutools_Chart!$G$39+MAX(总资产摘要!$E$5:$E$13) -> 1324089 | I39: =Kutools_Chart!$H$39+MAX(总资产摘要!$E$5:$E$13)*0.1 -> 1359456.1 | J39: =Kutools_Chart!$I$39+MAX(总资产摘要!$F$5:$F$13) -> 1732060.5 | K39: =Kutools_Chart!$J$39+MAX(总资产摘要!$F$5:$F$13)*0.1 -> 1769320.9 | L39: =Kutools_Chart!$K$39+MAX(总资产摘要!$G$5:$G$13) -> 1922718.3 | M39: =Kutools_Chart!$L$39+MAX(总资产摘要!$G$5:$G$13)*0.1 -> 1938058.1 | N39: =Kutools_Chart!$M$39+MAX(总资产摘要!$H$5:$H$13) -> 2100138 | O39: =Kutools_Chart!$N$39+MAX(总资产摘要!$H$5:$H$13)*0.1 -> 2116346 | P39: =Kutools_Chart!$O$39+MAX(总资产摘要!$I$5:$I$13) -> 2285738.9 | Q39: =Kutools_Chart!$P$39+MAX(总资产摘要!$I$5:$I$13)*0.1 -> 2302678.2 | R39: =Kutools_Chart!$Q$39+MAX(总资产摘要!$J$5:$J$13) -> 2475136.6 | S39: =Kutools_Chart!$R$39+MAX(总资产摘要!$J$5:$J$13)*0.1 -> 2492382.5 | T39: =Kutools_Chart!$S$39+MAX(总资产摘要!$K$5:$K$13) -> 2660615.2 | U39: =Kutools_Chart!$T$39+MAX(总资产摘要!$K$5:$K$13)*0.1 -> 2677438.5 | V39: =Kutools_Chart!$U$39+MAX(总资产摘要!$L$5:$L$13) -> 2851069.5 | W39: =Kutools_Chart!$V$39+MAX(总资产摘要!$L$5:$L$13)*0.1 -> 2868432.6 | X39: =Kutools_Chart!$W$39+MAX(总资产摘要!$M$5:$M$13) -> 3056028.2
A40: 0 | B40: =MAX(总资产摘要!$B$5:$B$13) -> 192935.76 | C40: 0 | D40: =MAX(总资产摘要!$C$5:$C$13) -> 260187.53 | E40: 0 | F40: =MAX(总资产摘要!$D$5:$D$13) -> 429074.87 | G40: 0 | H40: =MAX(总资产摘要!$E$5:$E$13) -> 353671.01 | I40: 0 | J40: =MAX(总资产摘要!$F$5:$F$13) -> 372604.37 | K40: 0 | L40: =MAX(总资产摘要!$G$5:$G$13) -> 153397.45 | M40: 0 | N40: =MAX(总资产摘要!$H$5:$H$13) -> 162079.94 | O40: 0 | P40: =MAX(总资产摘要!$I$5:$I$13) -> 169392.9 | Q40: 0 | R40: =MAX(总资产摘要!$J$5:$J$13) -> 172458.4 | S40: 0 | T40: =MAX(总资产摘要!$K$5:$K$13) -> 168232.73 | U40: 0 | V40: =MAX(总资产摘要!$L$5:$L$13) -> 173631.04 | W40: 0 | X40: =MAX(总资产摘要!$M$5:$M$13) -> 187595.64
A41: Kutools: Intermediate data of the multi-layer column chart
A43: =总资产摘要!B5/Kutools_Chart!A53 -> 0.13636801 | B43: =总资产摘要!C5/Kutools_Chart!B53 -> 2.6869742e-08 | C43: =总资产摘要!D5/Kutools_Chart!C53 -> 1.8448248e-08 | D43: =总资产摘要!E5/Kutools_Chart!D53 -> 0 | E43: =总资产摘要!F5/Kutools_Chart!E53 -> 0 | F43: =总资产摘要!G5/Kutools_Chart!F53 -> 0.2797289 | G43: =总资产摘要!H5/Kutools_Chart!G53 -> 0.2708962 | H43: =总资产摘要!I5/Kutools_Chart!H53 -> 0.26644016 | ... L43: =总资产摘要!M5/Kutools_Chart!L53 -> 0.17441281
A44: =总资产摘要!B6/Kutools_Chart!A53 -> 0.57078352 | B44: =总资产摘要!C6/Kutools_Chart!B53 -> 0.69911718 | C44: =总资产摘要!D6/Kutools_Chart!C53 -> 0.79156797 | D44: =总资产摘要!E6/Kutools_Chart!D53 -> 0.64258214 | E44: =总资产摘要!F6/Kutools_Chart!E53 -> 0.65240945 | F44: =总资产摘要!G6/Kutools_Chart!F53 -> 0.52671855 | G44: =总资产摘要!H6/Kutools_Chart!G53 -> 0.53871142 | H44: =总资产摘要!I6/Kutools_Chart!H53 -> 0.55315947 | ... L44: =总资产摘要!M6/Kutools_Chart!L53 -> 0.57720874
A45: =总资产摘要!B7/Kutools_Chart!A53 -> 0.0062699702 | B45: =总资产摘要!C7/Kutools_Chart!B53 -> 0.0056018306 | C45: =总资产摘要!D7/Kutools_Chart!C53 -> 0.0036414813 | D45: =总资产摘要!E7/Kutools_Chart!D53 -> 9.6440644e-05 | E45: =总资产摘要!F7/Kutools_Chart!E53 -> 9.2712493e-05 | F45: =总资产摘要!G7/Kutools_Chart!F53 -> 0.035912535 | G45: =总资产摘要!H7/Kutools_Chart!G53 -> 0.041919728 | H45: =总资产摘要!I7/Kutools_Chart!H53 -> 0.032842689 | ... L45: =总资产摘要!M7/Kutools_Chart!L53 -> 0.0014405323
A46: =总资产摘要!B8/Kutools_Chart!A53 -> 2.7119765e-08 | B46: =总资产摘要!C8/Kutools_Chart!B53 -> 2.4631492e-08 | C46: =总资产摘要!D8/Kutools_Chart!C53 -> 1.6911509e-08 | D46: =总资产摘要!E8/Kutools_Chart!D53 -> 1.6655452e-08 | E46: =总资产摘要!F8/Kutools_Chart!E53 -> 1.6050905e-08 | F46: =总资产摘要!G8/Kutools_Chart!F53 -> 0.019575851 | G46: =总资产摘要!H8/Kutools_Chart!G53 -> 2.3686294e-07 | H46: =总资产摘要!I8/Kutools_Chart!H53 -> 2.9935215e-08 | ... L46: =总资产摘要!M8/Kutools_Chart!L53 -> 2.8205733e-08
A47: =总资产摘要!B9/Kutools_Chart!A53 -> 5.9168246e-07 | B47: =总资产摘要!C9/Kutools_Chart!B53 -> 0.027102917 | C47: =总资产摘要!D9/Kutools_Chart!C53 -> 3.6896496e-08 | D47: =总资产摘要!E9/Kutools_Chart!D53 -> 7.2675693e-08 | E47: =总资产摘要!F9/Kutools_Chart!E53 -> 1.8209819e-06 | F47: =总资产摘要!G9/Kutools_Chart!F53 -> 0.0010678074 | G47: =总资产摘要!H9/Kutools_Chart!G53 -> 0.00015468682 | H47: =总资产摘要!I9/Kutools_Chart!H53 -> 6.4004604e-06 | ... L47: =总资产摘要!M9/Kutools_Chart!L53 -> 0.0001953817
A48: =总资产摘要!B10/Kutools_Chart!A53 -> 0.00039897148 | B48: =总资产摘要!C10/Kutools_Chart!B53 -> 0.0023274839 | C48: =总资产摘要!D10/Kutools_Chart!C53 -> 1.3541014e-05 | D48: =总资产摘要!E10/Kutools_Chart!D53 -> 3.4520954e-06 | E48: =总资产摘要!F10/Kutools_Chart!E53 -> 1.7334347e-05 | F48: =总资产摘要!G10/Kutools_Chart!F53 -> 0.0044160281 | G48: =总资产摘要!H10/Kutools_Chart!G53 -> 9.7385554e-06 | H48: =总资产摘要!I10/Kutools_Chart!H53 -> 1.9429969e-05 | ... L48: =总资产摘要!M10/Kutools_Chart!L53 -> 3.2614898e-06
A49: =总资产摘要!B11/Kutools_Chart!A53 -> 0.12218009 | B49: =总资产摘要!C11/Kutools_Chart!B53 -> 0.11452728 | C49: =总资产摘要!D11/Kutools_Chart!C53 -> 0.10126101 | D49: =总资产摘要!E11/Kutools_Chart!D53 -> 0.25440942 | E49: =总资产摘要!F11/Kutools_Chart!E53 -> 0.24565158 | F49: =总资产摘要!G11/Kutools_Chart!F53 -> 0.072139081 | G49: =总资产摘要!H11/Kutools_Chart!G53 -> 0.069575065 | H49: =总资产摘要!I11/Kutools_Chart!H53 -> 0.068814126 | ... L49: =总资产摘要!M11/Kutools_Chart!L53 -> 0.081280941
A50: =总资产摘要!B12/Kutools_Chart!A53 -> 0.13782846 | B50: =总资产摘要!C12/Kutools_Chart!B53 -> 0.13108919 | C50: =总资产摘要!D12/Kutools_Chart!C53 -> 0.089042481 | D50: =总资产摘要!E12/Kutools_Chart!D53 -> 0.088394846 | E50: =总资产摘要!F12/Kutools_Chart!E53 -> 0.087257164 | F50: =总资产摘要!G12/Kutools_Chart!F53 -> 0.029134544 | G50: =总资产摘要!H12/Kutools_Chart!G53 -> 0.048474474 | H50: =总资产摘要!I12/Kutools_Chart!H53 -> 0.048903338 | ... L50: =总资产摘要!M12/Kutools_Chart!L53 -> 0.13886079
A51: =总资产摘要!B13/Kutools_Chart!A53 -> 0.02617035 | B51: =总资产摘要!C13/Kutools_Chart!B53 -> 0.02023407 | C51: =总资产摘要!D13/Kutools_Chart!C53 -> 0.014473444 | D51: =总资产摘要!E13/Kutools_Chart!D53 -> 0.014513608 | E51: =总资产摘要!F13/Kutools_Chart!E53 -> 0.014569922 | F51: =总资产摘要!G13/Kutools_Chart!F53 -> 0.031306703 | G51: =总资产摘要!H13/Kutools_Chart!G53 -> 0.030258448 | H51: =总资产摘要!I13/Kutools_Chart!H53 -> 0.029814355 | ... L51: =总资产摘要!M13/Kutools_Chart!L53 -> 0.026597514
A52: =总资产摘要!#REF!/Kutools_Chart!A53 -> #REF! | B52: =总资产摘要!#REF!/Kutools_Chart!B53 -> #REF! | C52: =总资产摘要!#REF!/Kutools_Chart!C53 -> #REF! | D52: =总资产摘要!#REF!/Kutools_Chart!D53 -> #REF! | E52: =总资产摘要!#REF!/Kutools_Chart!E53 -> #REF! | F52: =总资产摘要!#REF!/Kutools_Chart!F53 -> #REF! | G52: =总资产摘要!#REF!/Kutools_Chart!G53 -> #REF! | H52: =总资产摘要!#REF!/Kutools_Chart!H53 -> #REF! | ... L52: =总资产摘要!#REF!/Kutools_Chart!L53 -> #REF!
A53: =SUBTOTAL(109,总资产摘要!B5:B13) -> 338019.15 | B53: =SUBTOTAL(109,总资产摘要!C5:C13) -> 372165.84 | C53: =SUBTOTAL(109,总资产摘要!D5:D13) -> 542056.89 | D53: =SUBTOTAL(109,总资产摘要!E5:E13) -> 550390.35 | E53: =SUBTOTAL(109,总资产摘要!F5:F13) -> 571120.44 | F53: =SUBTOTAL(109,总资产摘要!G5:G13) -> 291232.29 | G53: =SUBTOTAL(109,总资产摘要!H5:H13) -> 300865.98 | H53: =SUBTOTAL(109,总资产摘要!I5:I13) -> 306227.97 | ... L53: =SUBTOTAL(109,总资产摘要!M5:M13) -> 325004.85
A54: 注：该组数据是创建显示百分比堆积图时所生成的，请勿随意修改删除，以免引起显示百分比堆积图错误
A56: 0.25130758 | B56: 0.15706724 | C56: 1.5706724e-05 | D56: 0.10994707 | E56: 0.15706724 | F56: 0.041874126
A57: =IF(((ROW(Kutools_Chart!A57)-56)/100)<=(投资收益表!$B$17+投资收益表!$B$18+投资收益表!$B$19+投资收益表!$B$20+投资收益表!$B$21+投资收益表!$B$22),(MOD((ROW(Kutools_Chart!A57)- 57),10)+1),NA()) -> #VALUE! | B57: =IF(((ROW(Kutools_Chart!B57)-56)/100)<=(投资收益表!$B$18+投资收益表!$B$19+投资收益表!$B$20+投资收益表!$B$21+投资收益表!$B$22),(MOD((ROW(Kutools_Chart!B57)- 57),10)+1),NA()) -> #VALUE! | C57: =IF(((ROW(Kutools_Chart!C57)-56)/100)<=(投资收益表!$B$19+投资收益表!$B$20+投资收益表!$B$21+投资收益表!$B$22),(MOD((ROW(Kutools_Chart!C57)- 57),10)+1),NA()) -> #VALUE! | D57: =IF(((ROW(Kutools_Chart!D57)-56)/100)<=(投资收益表!$B$20+投资收益表!$B$21+投资收益表!$B$22),(MOD((ROW(Kutools_Chart!D57)- 57),10)+1),NA()) -> #VALUE! | E57: =IF(((ROW(Kutools_Chart!E57)-56)/100)<=(投资收益表!$B$21+投资收益表!$B$22),(MOD((ROW(Kutools_Chart!E57)- 57),10)+1),NA()) -> #VALUE! | F57: =IF(((ROW(Kutools_Chart!F57)-56)/100)<=(投资收益表!$B$22),(MOD((ROW(Kutools_Chart!F57)- 57),10)+1),NA()) -> 1
A58: =IF(((ROW(Kutools_Chart!A58)-56)/100)<=(投资收益表!$B$17+投资收益表!$B$18+投资收益表!$B$19+投资收益表!$B$20+投资收益表!$B$21+投资收益表!$B$22),(MOD((ROW(Kutools_Chart!A58)- 57),10)+1),NA()) -> #VALUE! | B58: =IF(((ROW(Kutools_Chart!B58)-56)/100)<=(投资收益表!$B$18+投资收益表!$B$19+投资收益表!$B$20+投资收益表!$B$21+投资收益表!$B$22),(MOD((ROW(Kutools_Chart!B58)- 57),10)+1),NA()) -> #VALUE! | C58: =IF(((ROW(Kutools_Chart!C58)-56)/100)<=(投资收益表!$B$19+投资收益表!$B$20+投资收益表!$B$21+投资收益表!$B$22),(MOD((ROW(Kutools_Chart!C58)- 57),10)+1),NA()) -> #VALUE! | D58: =IF(((ROW(Kutools_Chart!D58)-56)/100)<=(投资收益表!$B$20+投资收益表!$B$21+投资收益表!$B$22),(MOD((ROW(Kutools_Chart!D58)- 57),10)+1),NA()) -> #VALUE! | E58: =IF(((ROW(Kutools_Chart!E58)-56)/100)<=(投资收益表!$B$21+投资收益表!$B$22),(MOD((ROW(Kutools_Chart!E58)- 57),10)+1),NA()) -> #VALUE! | F58: =IF(((ROW(Kutools_Chart!F58)-56)/100)<=(投资收益表!$B$22),(MOD((ROW(Kutools_Chart!F58)- 57),10)+1),NA()) -> 2
A59: =IF(((ROW(Kutools_Chart!A59)-56)/100)<=(投资收益表!$B$17+投资收益表!$B$18+投资收益表!$B$19+投资收益表!$B$20+投资收益表!$B$21+投资收益表!$B$22),(MOD((ROW(Kutools_Chart!A59)- 57),10)+1),NA()) -> #VALUE! | B59: =IF(((ROW(Kutools_Chart!B59)-56)/100)<=(投资收益表!$B$18+投资收益表!$B$19+投资收益表!$B$20+投资收益表!$B$21+投资收益表!$B$22),(MOD((ROW(Kutools_Chart!B59)- 57),10)+1),NA()) -> #VALUE! | C59: =IF(((ROW(Kutools_Chart!C59)-56)/100)<=(投资收益表!$B$19+投资收益表!$B$20+投资收益表!$B$21+投资收益表!$B$22),(MOD((ROW(Kutools_Chart!C59)- 57),10)+1),NA()) -> #VALUE! | D59: =IF(((ROW(Kutools_Chart!D59)-56)/100)<=(投资收益表!$B$20+投资收益表!$B$21+投资收益表!$B$22),(MOD((ROW(Kutools_Chart!D59)- 57),10)+1),NA()) -> #VALUE! | E59: =IF(((ROW(Kutools_Chart!E59)-56)/100)<=(投资收益表!$B$21+投资收益表!$B$22),(MOD((ROW(Kutools_Chart!E59)- 57),10)+1),NA()) -> #VALUE! | F59: =IF(((ROW(Kutools_Chart!F59)-56)/100)<=(投资收益表!$B$22),(MOD((ROW(Kutools_Chart!F59)- 57),10)+1),NA()) -> 3
A60: =IF(((ROW(Kutools_Chart!A60)-56)/100)<=(投资收益表!$B$17+投资收益表!$B$18+投资收益表!$B$19+投资收益表!$B$20+投资收益表!$B$21+投资收益表!$B$22),(MOD((ROW(Kutools_Chart!A60)- 57),10)+1),NA()) -> #VALUE! | B60: =IF(((ROW(Kutools_Chart!B60)-56)/100)<=(投资收益表!$B$18+投资收益表!$B$19+投资收益表!$B$20+投资收益表!$B$21+投资收益表!$B$22),(MOD((ROW(Kutools_Chart!B60)- 57),10)+1),NA()) -> #VALUE! | C60: =IF(((ROW(Kutools_Chart!C60)-56)/100)<=(投资收益表!$B$19+投资收益表!$B$20+投资收益表!$B$21+投资收益表!$B$22),(MOD((ROW(Kutools_Chart!C60)- 57),10)+1),NA()) -> #VALUE! | D60: =IF(((ROW(Kutools_Chart!D60)-56)/100)<=(投资收益表!$B$20+投资收益表!$B$21+投资收益表!$B$22),(MOD((ROW(Kutools_Chart!D60)- 57),10)+1),NA()) -> #VALUE! | E60: =IF(((ROW(Kutools_Chart!E60)-56)/100)<=(投资收益表!$B$21+投资收益表!$B$22),(MOD((ROW(Kutools_Chart!E60)- 57),10)+1),NA()) -> #VALUE! | F60: =IF(((ROW(Kutools_Chart!F60)-56)/100)<=(投资收益表!$B$22),(MOD((ROW(Kutools_Chart!F60)- 57),10)+1),NA()) -> 4
A61: =IF(((ROW(Kutools_Chart!A61)-56)/100)<=(投资收益表!$B$17+投资收益表!$B$18+投资收益表!$B$19+投资收益表!$B$20+投资收益表!$B$21+投资收益表!$B$22),(MOD((ROW(Kutools_Chart!A61)- 57),10)+1),NA()) -> #VALUE! | B61: =IF(((ROW(Kutools_Chart!B61)-56)/100)<=(投资收益表!$B$18+投资收益表!$B$19+投资收益表!$B$20+投资收益表!$B$21+投资收益表!$B$22),(MOD((ROW(Kutools_Chart!B61)- 57),10)+1),NA()) -> #VALUE! | C61: =IF(((ROW(Kutools_Chart!C61)-56)/100)<=(投资收益表!$B$19+投资收益表!$B$20+投资收益表!$B$21+投资收益表!$B$22),(MOD((ROW(Kutools_Chart!C61)- 57),10)+1),NA()) -> #VALUE! | D61: =IF(((ROW(Kutools_Chart!D61)-56)/100)<=(投资收益表!$B$20+投资收益表!$B$21+投资收益表!$B$22),(MOD((ROW(Kutools_Chart!D61)- 57),10)+1),NA()) -> #VALUE! | E61: =IF(((ROW(Kutools_Chart!E61)-56)/100)<=(投资收益表!$B$21+投资收益表!$B$22),(MOD((ROW(Kutools_Chart!E61)- 57),10)+1),NA()) -> #VALUE! | F61: =IF(((ROW(Kutools_Chart!F61)-56)/100)<=(投资收益表!$B$22),(MOD((ROW(Kutools_Chart!F61)- 57),10)+1),NA()) -> 5
A62: =IF(((ROW(Kutools_Chart!A62)-56)/100)<=(投资收益表!$B$17+投资收益表!$B$18+投资收益表!$B$19+投资收益表!$B$20+投资收益表!$B$21+投资收益表!$B$22),(MOD((ROW(Kutools_Chart!A62)- 57),10)+1),NA()) -> #VALUE! | B62: =IF(((ROW(Kutools_Chart!B62)-56)/100)<=(投资收益表!$B$18+投资收益表!$B$19+投资收益表!$B$20+投资收益表!$B$21+投资收益表!$B$22),(MOD((ROW(Kutools_Chart!B62)- 57),10)+1),NA()) -> #VALUE! | C62: =IF(((ROW(Kutools_Chart!C62)-56)/100)<=(投资收益表!$B$19+投资收益表!$B$20+投资收益表!$B$21+投资收益表!$B$22),(MOD((ROW(Kutools_Chart!C62)- 57),10)+1),NA()) -> #VALUE! | D62: =IF(((ROW(Kutools_Chart!D62)-56)/100)<=(投资收益表!$B$20+投资收益表!$B$21+投资收益表!$B$22),(MOD((ROW(Kutools_Chart!D62)- 57),10)+1),NA()) -> #VALUE! | E62: =IF(((ROW(Kutools_Chart!E62)-56)/100)<=(投资收益表!$B$21+投资收益表!$B$22),(MOD((ROW(Kutools_Chart!E62)- 57),10)+1),NA()) -> #VALUE! | F62: =IF(((ROW(Kutools_Chart!F62)-56)/100)<=(投资收益表!$B$22),(MOD((ROW(Kutools_Chart!F62)- 57),10)+1),NA()) -> 6
A63: =IF(((ROW(Kutools_Chart!A63)-56)/100)<=(投资收益表!$B$17+投资收益表!$B$18+投资收益表!$B$19+投资收益表!$B$20+投资收益表!$B$21+投资收益表!$B$22),(MOD((ROW(Kutools_Chart!A63)- 57),10)+1),NA()) -> #VALUE! | B63: =IF(((ROW(Kutools_Chart!B63)-56)/100)<=(投资收益表!$B$18+投资收益表!$B$19+投资收益表!$B$20+投资收益表!$B$21+投资收益表!$B$22),(MOD((ROW(Kutools_Chart!B63)- 57),10)+1),NA()) -> #VALUE! | C63: =IF(((ROW(Kutools_Chart!C63)-56)/100)<=(投资收益表!$B$19+投资收益表!$B$20+投资收益表!$B$21+投资收益表!$B$22),(MOD((ROW(Kutools_Chart!C63)- 57),10)+1),NA()) -> #VALUE! | D63: =IF(((ROW(Kutools_Chart!D63)-56)/100)<=(投资收益表!$B$20+投资收益表!$B$21+投资收益表!$B$22),(MOD((ROW(Kutools_Chart!D63)- 57),10)+1),NA()) -> #VALUE! | E63: =IF(((ROW(Kutools_Chart!E63)-56)/100)<=(投资收益表!$B$21+投资收益表!$B$22),(MOD((ROW(Kutools_Chart!E63)- 57),10)+1),NA()) -> #VALUE! | F63: =IF(((ROW(Kutools_Chart!F63)-56)/100)<=(投资收益表!$B$22),(MOD((ROW(Kutools_Chart!F63)- 57),10)+1),NA()) -> 7
A64: =IF(((ROW(Kutools_Chart!A64)-56)/100)<=(投资收益表!$B$17+投资收益表!$B$18+投资收益表!$B$19+投资收益表!$B$20+投资收益表!$B$21+投资收益表!$B$22),(MOD((ROW(Kutools_Chart!A64)- 57),10)+1),NA()) -> #VALUE! | B64: =IF(((ROW(Kutools_Chart!B64)-56)/100)<=(投资收益表!$B$18+投资收益表!$B$19+投资收益表!$B$20+投资收益表!$B$21+投资收益表!$B$22),(MOD((ROW(Kutools_Chart!B64)- 57),10)+1),NA()) -> #VALUE! | C64: =IF(((ROW(Kutools_Chart!C64)-56)/100)<=(投资收益表!$B$19+投资收益表!$B$20+投资收益表!$B$21+投资收益表!$B$22),(MOD((ROW(Kutools_Chart!C64)- 57),10)+1),NA()) -> #VALUE! | D64: =IF(((ROW(Kutools_Chart!D64)-56)/100)<=(投资收益表!$B$20+投资收益表!$B$21+投资收益表!$B$22),(MOD((ROW(Kutools_Chart!D64)- 57),10)+1),NA()) -> #VALUE! | E64: =IF(((ROW(Kutools_Chart!E64)-56)/100)<=(投资收益表!$B$21+投资收益表!$B$22),(MOD((ROW(Kutools_Chart!E64)- 57),10)+1),NA()) -> #VALUE! | F64: =IF(((ROW(Kutools_Chart!F64)-56)/100)<=(投资收益表!$B$22),(MOD((ROW(Kutools_Chart!F64)- 57),10)+1),NA()) -> 8
A65: =IF(((ROW(Kutools_Chart!A65)-56)/100)<=(投资收益表!$B$17+投资收益表!$B$18+投资收益表!$B$19+投资收益表!$B$20+投资收益表!$B$21+投资收益表!$B$22),(MOD((ROW(Kutools_Chart!A65)- 57),10)+1),NA()) -> #VALUE! | B65: =IF(((ROW(Kutools_Chart!B65)-56)/100)<=(投资收益表!$B$18+投资收益表!$B$19+投资收益表!$B$20+投资收益表!$B$21+投资收益表!$B$22),(MOD((ROW(Kutools_Chart!B65)- 57),10)+1),NA()) -> #VALUE! | C65: =IF(((ROW(Kutools_Chart!C65)-56)/100)<=(投资收益表!$B$19+投资收益表!$B$20+投资收益表!$B$21+投资收益表!$B$22),(MOD((ROW(Kutools_Chart!C65)- 57),10)+1),NA()) -> #VALUE! | D65: =IF(((ROW(Kutools_Chart!D65)-56)/100)<=(投资收益表!$B$20+投资收益表!$B$21+投资收益表!$B$22),(MOD((ROW(Kutools_Chart!D65)- 57),10)+1),NA()) -> #VALUE! | E65: =IF(((ROW(Kutools_Chart!E65)-56)/100)<=(投资收益表!$B$21+投资收益表!$B$22),(MOD((ROW(Kutools_Chart!E65)- 57),10)+1),NA()) -> #VALUE! | F65: =IF(((ROW(Kutools_Chart!F65)-56)/100)<=(投资收益表!$B$22),(MOD((ROW(Kutools_Chart!F65)- 57),10)+1),NA()) -> 9
A66: =IF(((ROW(Kutools_Chart!A66)-56)/100)<=(投资收益表!$B$17+投资收益表!$B$18+投资收益表!$B$19+投资收益表!$B$20+投资收益表!$B$21+投资收益表!$B$22),(MOD((ROW(Kutools_Chart!A66)- 57),10)+1),NA()) -> #VALUE! | B66: =IF(((ROW(Kutools_Chart!B66)-56)/100)<=(投资收益表!$B$18+投资收益表!$B$19+投资收益表!$B$20+投资收益表!$B$21+投资收益表!$B$22),(MOD((ROW(Kutools_Chart!B66)- 57),10)+1),NA()) -> #VALUE! | C66: =IF(((ROW(Kutools_Chart!C66)-56)/100)<=(投资收益表!$B$19+投资收益表!$B$20+投资收益表!$B$21+投资收益表!$B$22),(MOD((ROW(Kutools_Chart!C66)- 57),10)+1),NA()) -> #VALUE! | D66: =IF(((ROW(Kutools_Chart!D66)-56)/100)<=(投资收益表!$B$20+投资收益表!$B$21+投资收益表!$B$22),(MOD((ROW(Kutools_Chart!D66)- 57),10)+1),NA()) -> #VALUE! | E66: =IF(((ROW(Kutools_Chart!E66)-56)/100)<=(投资收益表!$B$21+投资收益表!$B$22),(MOD((ROW(Kutools_Chart!E66)- 57),10)+1),NA()) -> #VALUE! | F66: =IF(((ROW(Kutools_Chart!F66)-56)/100)<=(投资收益表!$B$22),(MOD((ROW(Kutools_Chart!F66)- 57),10)+1),NA()) -> 10
A67: =IF(((ROW(Kutools_Chart!A67)-56)/100)<=(投资收益表!$B$17+投资收益表!$B$18+投资收益表!$B$19+投资收益表!$B$20+投资收益表!$B$21+投资收益表!$B$22),(MOD((ROW(Kutools_Chart!A67)- 57),10)+1),NA()) -> #VALUE! | B67: =IF(((ROW(Kutools_Chart!B67)-56)/100)<=(投资收益表!$B$18+投资收益表!$B$19+投资收益表!$B$20+投资收益表!$B$21+投资收益表!$B$22),(MOD((ROW(Kutools_Chart!B67)- 57),10)+1),NA()) -> #VALUE! | C67: =IF(((ROW(Kutools_Chart!C67)-56)/100)<=(投资收益表!$B$19+投资收益表!$B$20+投资收益表!$B$21+投资收益表!$B$22),(MOD((ROW(Kutools_Chart!C67)- 57),10)+1),NA()) -> #VALUE! | D67: =IF(((ROW(Kutools_Chart!D67)-56)/100)<=(投资收益表!$B$20+投资收益表!$B$21+投资收益表!$B$22),(MOD((ROW(Kutools_Chart!D67)- 57),10)+1),NA()) -> #VALUE! | E67: =IF(((ROW(Kutools_Chart!E67)-56)/100)<=(投资收益表!$B$21+投资收益表!$B$22),(MOD((ROW(Kutools_Chart!E67)- 57),10)+1),NA()) -> #VALUE! | F67: =IF(((ROW(Kutools_Chart!F67)-56)/100)<=(投资收益表!$B$22),(MOD((ROW(Kutools_Chart!F67)- 57),10)+1),NA()) -> 1
A68: =IF(((ROW(Kutools_Chart!A68)-56)/100)<=(投资收益表!$B$17+投资收益表!$B$18+投资收益表!$B$19+投资收益表!$B$20+投资收益表!$B$21+投资收益表!$B$22),(MOD((ROW(Kutools_Chart!A68)- 57),10)+1),NA()) -> #VALUE! | B68: =IF(((ROW(Kutools_Chart!B68)-56)/100)<=(投资收益表!$B$18+投资收益表!$B$19+投资收益表!$B$20+投资收益表!$B$21+投资收益表!$B$22),(MOD((ROW(Kutools_Chart!B68)- 57),10)+1),NA()) -> #VALUE! | C68: =IF(((ROW(Kutools_Chart!C68)-56)/100)<=(投资收益表!$B$19+投资收益表!$B$20+投资收益表!$B$21+投资收益表!$B$22),(MOD((ROW(Kutools_Chart!C68)- 57),10)+1),NA()) -> #VALUE! | D68: =IF(((ROW(Kutools_Chart!D68)-56)/100)<=(投资收益表!$B$20+投资收益表!$B$21+投资收益表!$B$22),(MOD((ROW(Kutools_Chart!D68)- 57),10)+1),NA()) -> #VALUE! | E68: =IF(((ROW(Kutools_Chart!E68)-56)/100)<=(投资收益表!$B$21+投资收益表!$B$22),(MOD((ROW(Kutools_Chart!E68)- 57),10)+1),NA()) -> #VALUE! | F68: =IF(((ROW(Kutools_Chart!F68)-56)/100)<=(投资收益表!$B$22),(MOD((ROW(Kutools_Chart!F68)- 57),10)+1),NA()) -> 2
... A156: =IF(((ROW(Kutools_Chart!A156)-56)/100)<=(投资收益表!$B$17+投资收益表!$B$18+投资收益表!$B$19+投资收益表!$B$20+投资收益表!$B$21+投资收益表!$B$22),(MOD((ROW(Kutools_Chart!A156)- 57),10)+1),NA()) -> #VALUE! | B156: =IF(((ROW(Kutools_Chart!B156)-56)/100)<=(投资收益表!$B$18+投资收益表!$B$19+投资收益表!$B$20+投资收益表!$B$21+投资收益表!$B$22),(MOD((ROW(Kutools_Chart!B156)- 57),10)+1),NA()) -> #VALUE! | C156: =IF(((ROW(Kutools_Chart!C156)-56)/100)<=(投资收益表!$B$19+投资收益表!$B$20+投资收益表!$B$21+投资收益表!$B$22),(MOD((ROW(Kutools_Chart!C156)- 57),10)+1),NA()) -> #VALUE! | D156: =IF(((ROW(Kutools_Chart!D156)-56)/100)<=(投资收益表!$B$20+投资收益表!$B$21+投资收益表!$B$22),(MOD((ROW(Kutools_Chart!D156)- 57),10)+1),NA()) -> #VALUE! | E156: =IF(((ROW(Kutools_Chart!E156)-56)/100)<=(投资收益表!$B$21+投资收益表!$B$22),(MOD((ROW(Kutools_Chart!E156)- 57),10)+1),NA()) -> #VALUE! | F156: =IF(((ROW(Kutools_Chart!F156)-56)/100)<=(投资收益表!$B$22),(MOD((ROW(Kutools_Chart!F156)- 57),10)+1),NA()) -> 10
A157: 注：该组数据是创建按占比堆积图时所生成的，请勿随意修改删除，以免引起占比堆积图错误
A159: =IF(投资收益表!J16>投资收益表!K16,投资收益表!J16,投资收益表!K16) -> 0.95984721 | B159: =IF(投资收益表!J16>投资收益表!K16,0.34,-0.34) -> 0.34 | C159: =IF(投资收益表!J16>投资收益表!K16,投资收益表!J16-投资收益表!K16,NA()) -> 0.45984721 | D159: =IF(投资收益表!K16>投资收益表!J16,投资收益表!J16-投资收益表!K16,NA()) -> #N/A | E159: =IF(投资收益表!K16=0,"",(投资收益表!J16-投资收益表!K16)/投资收益表!K16) -> 0.91969441
A160: =IF(投资收益表!J17>投资收益表!K17,投资收益表!J17,投资收益表!K17) -> 0.15 | B160: =IF(投资收益表!J17>投资收益表!K17,0.34,-0.34) -> -0.34 | C160: =IF(投资收益表!J17>投资收益表!K17,投资收益表!J17-投资收益表!K17,NA()) -> #N/A | D160: =IF(投资收益表!K17>投资收益表!J17,投资收益表!J17-投资收益表!K17,NA()) -> -0.15 | E160: =IF(投资收益表!K17=0,"",(投资收益表!J17-投资收益表!K17)/投资收益表!K17) -> -1
A161: =IF(投资收益表!J18>投资收益表!K18,投资收益表!J18,投资收益表!K18) -> 0.15 | B161: =IF(投资收益表!J18>投资收益表!K18,0.34,-0.34) -> -0.34 | C161: =IF(投资收益表!J18>投资收益表!K18,投资收益表!J18-投资收益表!K18,NA()) -> #N/A | D161: =IF(投资收益表!K18>投资收益表!J18,投资收益表!J18-投资收益表!K18,NA()) -> -0.14696285 | E161: =IF(投资收益表!K18=0,"",(投资收益表!J18-投资收益表!K18)/投资收益表!K18) -> -0.97975235
A162: =IF(投资收益表!J19>投资收益表!K19,投资收益表!J19,投资收益表!K19) -> 0.15 | B162: =IF(投资收益表!J19>投资收益表!K19,0.34,-0.34) -> -0.34 | C162: =IF(投资收益表!J19>投资收益表!K19,投资收益表!J19-投资收益表!K19,NA()) -> #N/A | D162: =IF(投资收益表!K19>投资收益表!J19,投资收益表!J19-投资收益表!K19,NA()) -> -0.11434994 | E162: =IF(投资收益表!K19=0,"",(投资收益表!J19-投资收益表!K19)/投资收益表!K19) -> -0.76233297
A163: =IF(投资收益表!J20>投资收益表!K20,投资收益表!J20,投资收益表!K20) -> 0.05 | B163: =IF(投资收益表!J20>投资收益表!K20,0.34,-0.34) -> -0.34 | C163: =IF(投资收益表!J20>投资收益表!K20,投资收益表!J20-投资收益表!K20,NA()) -> #N/A | D163: =IF(投资收益表!K20>投资收益表!J20,投资收益表!J20-投资收益表!K20,NA()) -> -0.04853441 | E163: =IF(投资收益表!K20=0,"",(投资收益表!J20-投资收益表!K20)/投资收益表!K20) -> -0.97068819
A164: =IF(投资收益表!J21>投资收益表!K21,投资收益表!J21,投资收益表!K21) -> 0 | B164: =IF(投资收益表!J21>投资收益表!K21,0.34,-0.34) -> -0.34 | C164: =IF(投资收益表!J21>投资收益表!K21,投资收益表!J21-投资收益表!K21,NA()) -> #N/A | D164: =IF(投资收益表!K21>投资收益表!J21,投资收益表!J21-投资收益表!K21,NA()) -> #N/A | E164: =IF(投资收益表!K21=0,"",(投资收益表!J21-投资收益表!K21)/投资收益表!K21)
A165: =IF(投资收益表!J22>投资收益表!K22,投资收益表!J22,投资收益表!K22) -> 2.0548227e-05 | B165: =IF(投资收益表!J22>投资收益表!K22,0.34,-0.34) -> 0.34 | C165: =IF(投资收益表!J22>投资收益表!K22,投资收益表!J22-投资收益表!K22,NA()) -> 2.0548227e-05 | D165: =IF(投资收益表!K22>投资收益表!J22,投资收益表!J22-投资收益表!K22,NA()) -> #N/A | E165: =IF(投资收益表!K22=0,"",(投资收益表!J22-投资收益表!K22)/投资收益表!K22)
A166: 注：该组数据是创建差值箭头图时所生成的，请勿随意修改删除，以免引起差值箭头图错误
A168: =IF(投资收益表!J16<投资收益表!K16,投资收益表!J16,投资收益表!K16) -> 0.5 | B168: =IF(投资收益表!J16>=投资收益表!K16,投资收益表!J16-投资收益表!K16,NA()) -> 0.45984721 | C168: =IF(投资收益表!K16>投资收益表!J16,投资收益表!K16-投资收益表!J16,NA()) -> #N/A | D168: 0 | E168: =投资收益表!J16-投资收益表!K16 -> 0.45984721
A169: =IF(投资收益表!J17<投资收益表!K17,投资收益表!J17,投资收益表!K17) -> 0 | B169: =IF(投资收益表!J17>=投资收益表!K17,投资收益表!J17-投资收益表!K17,NA()) -> #N/A | C169: =IF(投资收益表!K17>投资收益表!J17,投资收益表!K17-投资收益表!J17,NA()) -> 0.15 | D169: 0 | E169: =投资收益表!J17-投资收益表!K17 -> -0.15
A170: =IF(投资收益表!J18<投资收益表!K18,投资收益表!J18,投资收益表!K18) -> 0.0030371469 | B170: =IF(投资收益表!J18>=投资收益表!K18,投资收益表!J18-投资收益表!K18,NA()) -> #N/A | C170: =IF(投资收益表!K18>投资收益表!J18,投资收益表!K18-投资收益表!J18,NA()) -> 0.14696285 | D170: 0 | E170: =投资收益表!J18-投资收益表!K18 -> -0.14696285
A171: =IF(投资收益表!J19<投资收益表!K19,投资收益表!J19,投资收益表!K19) -> 0.035650055 | B171: =IF(投资收益表!J19>=投资收益表!K19,投资收益表!J19-投资收益表!K19,NA()) -> #N/A | C171: =IF(投资收益表!K19>投资收益表!J19,投资收益表!K19-投资收益表!J19,NA()) -> 0.11434994 | D171: 0 | E171: =投资收益表!J19-投资收益表!K19 -> -0.11434994
A172: =IF(投资收益表!J20<投资收益表!K20,投资收益表!J20,投资收益表!K20) -> 0.0014655905 | B172: =IF(投资收益表!J20>=投资收益表!K20,投资收益表!J20-投资收益表!K20,NA()) -> #N/A | C172: =IF(投资收益表!K20>投资收益表!J20,投资收益表!K20-投资收益表!J20,NA()) -> 0.04853441 | D172: 0 | E172: =投资收益表!J20-投资收益表!K20 -> -0.04853441
A173: =IF(投资收益表!J21<投资收益表!K21,投资收益表!J21,投资收益表!K21) -> 0 | B173: =IF(投资收益表!J21>=投资收益表!K21,投资收益表!J21-投资收益表!K21,NA()) -> 0 | C173: =IF(投资收益表!K21>投资收益表!J21,投资收益表!K21-投资收益表!J21,NA()) -> #N/A | D173: 0 | E173: =投资收益表!J21-投资收益表!K21 -> 0
A174: =IF(投资收益表!J22<投资收益表!K22,投资收益表!J22,投资收益表!K22) -> 0 | B174: =IF(投资收益表!J22>=投资收益表!K22,投资收益表!J22-投资收益表!K22,NA()) -> 2.0548227e-05 | C174: =IF(投资收益表!K22>投资收益表!J22,投资收益表!K22-投资收益表!J22,NA()) -> #N/A | D174: 0 | E174: =投资收益表!J22-投资收益表!K22 -> 2.0548227e-05
